Workbook

Sheet RZiS ->>>

Sheet Check RZiS
A3: Etykiety wierszy | B3: Suma z 2025 | G3: Etykiety wierszy | H3: Suma z 2024
A4: A. Przychody netto ze sprzedaży i zrównane z nimi, w tym: | B4: 22183111 | G4: A. Przychody netto ze sprzedaży i zrównane z nimi, w tym: | H4: 21358215
A5: B. Koszty działalności operacyjnej | B5: 21801950 | G5: B. Koszty działalności operacyjnej | H5: 21107239
A6: D. Pozostałe przychody operacyjne | B6: 126275.61 | G6: D. Pozostałe przychody operacyjne | H6: 482321.98
A7: E. Pozostałe koszty operacyjne | B7: 18914.54 | G7: E. Pozostałe koszty operacyjne | H7: 19294.28
A8: G. Przychody finansowe | B8: 18.29 | G8: G. Przychody finansowe | H8: 362.63
A9: H. Koszty finansowe | B9: 5152.3 | G9: H. Koszty finansowe | H9: -5155.11
A10: J. Podatek dochodowy | B10: 158751.35 | G10: J. Podatek dochodowy | H10: 377232.61
A11: Suma końcowa | B11: 44294173 | G11: Suma końcowa | H11: 43339511
A13: Zysk netto RZiS | B13: =B6+B4+B8-B5-B7-B9-B10 -> 324636.34 | G13: Zysk netto RZiS | H13: =H6+H4+H8-H5-H7-H9-H10 -> 342288.94
A14: Per TB | B14: =SUMIF('2025 ZOiS'!D:D,"Wynikowe",'2025 ZOiS'!Q:Q) -> -324636.34 | G14: Per TB | H14: =SUMIF('2024 ZOiS'!D:D,"Wynikowe",'2024 ZOiS'!Q:Q) -> 342288.94
B15: =B13+B14 -> -1.6647391e-08 | H15: =H13-H14 -> -9.0803951e-09

Sheet 25 RZiS Zmapowane P+
A1: Rodzaj1 | B1: Rodzaj2 | C1: Rodzaj3 | D1: Numer konta | E1: Nazwa konta | F1: Rodzaj konta (bilansowe/wynikowe) | G1: 2025-01 | H1: 2025-02 | I1: 2025-03 | J1: 2025-04 | K1: 2025-05 | L1: 2025-06 | M1: 2025-07 | N1: 2025-08 | O1: 2025-09 | P1: 2025-10 | Q1: 2025-11 | R1: 2025-12 | S1: 2025 | T1: -1
A2: =IF(ISNUMBER(SEARCH("przychody",B2)),"Przychody","Koszty") -> Przychody | B2: A. Przychody netto ze sprzedaży i zrównane z nimi, w tym: | C2: I. Przychody netto ze sprzedaży produktów | D2: 45510000 | E2: 45510000 Prowizja Cost+ | F2: Wynikowe | G2: 1877205 | H2: 1844622 | I2: 1802379 | J2: 1430181 | K2: 1741817 | L2: 1686073 | M2: 1733363 | N2: 1733363 | O2: 1733363 | P2: 1711660 | Q2: 1711660 | R2: 3177425 | S2: =SUM(_25[[#This Row],[2025-01]:[2025-12]]) -> 22183111
A3: =IF(ISNUMBER(SEARCH("przychody",B3)),"Przychody","Koszty") -> Przychody | B3: A. Przychody netto ze sprzedaży i zrównane z nimi, w tym: | C3: I. Przychody netto ze sprzedaży produktów | D3: 44000000 | E3: 44000000 Przychód operacyjny - opłata za konosament | F3: Wynikowe | G3: 0 | H3: 0 | I3: 0 | J3: 0 | K3: 0 | L3: 0 | M3: 0 | N3: 0 | O3: 0 | P3: 0 | Q3: 0 | R3: 0 | S3: =SUM(_25[[#This Row],[2025-01]:[2025-12]]) -> 0
A4: =IF(ISNUMBER(SEARCH("przychody",B4)),"Przychody","Koszty") -> Przychody | B4: A. Przychody netto ze sprzedaży i zrównane z nimi, w tym: | C4: I. Przychody netto ze sprzedaży produktów | D4: 44000005 | E4: 44000005 Przychód operacyjny - opłata dokumentacyjna EXP | F4: Wynikowe | G4: 0 | H4: 0 | I4: 0 | J4: 0 | K4: 0 | L4: 0 | M4: 0 | N4: 0 | O4: 0 | P4: 0 | Q4: 0 | R4: 0 | S4: =SUM(_25[[#This Row],[2025-01]:[2025-12]]) -> 0
A5: =IF(ISNUMBER(SEARCH("przychody",B5)),"Przychody","Koszty") -> Przychody | B5: A. Przychody netto ze sprzedaży i zrównane z nimi, w tym: | C5: I. Przychody netto ze sprzedaży produktów | D5: 44006000 | E5: 44006000 Przychód operacyjny - korekta manifestu | F5: Wynikowe | G5: 0 | H5: 0 | I5: 0 | J5: 0 | K5: 0 | L5: 0 | M5: 0 | N5: 0 | O5: 0 | P5: 0 | Q5: 0 | R5: 0 | S5: =SUM(_25[[#This Row],[2025-01]:[2025-12]]) -> 0
A6: =IF(ISNUMBER(SEARCH("przychody",B6)),"Przychody","Koszty") -> Koszty | B6: B. Koszty działalności operacyjnej | C6: I. Amortyzacja | D6: 61000000 | E6: 61000000 Oprogramowanie i licencje IT - Amortyzacja | F6: Wynikowe | G6: 926.5 | H6: 926.5 | I6: 926.5 | J6: 926.5 | K6: 926.5 | L6: 926.5 | M6: 926.5 | N6: 926.5 | O6: 926.5 | P6: 926.5 | Q6: 926.5 | R6: 926.5 | S6: =SUM(_25[[#This Row],[2025-01]:[2025-12]]) -> 11118
A7: =IF(ISNUMBER(SEARCH("przychody",B7)),"Przychody","Koszty") -> Koszty | B7: B. Koszty działalności operacyjnej | C7: =C6 -> I. Amortyzacja | D7: 61502000 | E7: 61502000 Budynki - Amortyzacja | F7: Wynikowe | G7: 17326.2 | H7: 17326.2 | I7: 17326.21 | J7: 17326.2 | K7: 17326.2 | L7: 17326.2 | M7: 17326.2 | N7: 17326.2 | O7: 17326.21 | P7: 17326.2 | Q7: 17326.2 | R7: 17326.2 | S7: =SUM(_25[[#This Row],[2025-01]:[2025-12]]) -> 207914.42
A8: =IF(ISNUMBER(SEARCH("przychody",B8)),"Przychody","Koszty") -> Koszty | B8: B. Koszty działalności operacyjnej | C8: =C7 -> I. Amortyzacja | D8: 61504000 | E8: 61504000 Nakłady w obcych środkach trwał - Amortyzacja | F8: Wynikowe | G8: 313.46 | H8: 313.45 | I8: 313.46 | J8: 313.46 | K8: 6769.34 | L8: 1604.64 | M8: 1604.64 | N8: 1604.63 | O8: 1604.64 | P8: 1604.63 | Q8: 1604.63 | R8: 1604.64 | S8: =SUM(_25[[#This Row],[2025-01]:[2025-12]]) -> 19255.62
A9: =IF(ISNUMBER(SEARCH("przychody",B9)),"Przychody","Koszty") -> Koszty | B9: B. Koszty działalności operacyjnej | C9: =C8 -> I. Amortyzacja | D9: 61508000 | E9: 61508000 Komputery i sprzęt IT - Amortyzacja | F9: Wynikowe | G9: 10218.3 | H9: 8464.79 | I9: 11588.15 | J9: 24240.21 | K9: 459 | L9: 0 | M9: 16357.33 | N9: 579 | O9: 4146.34 | P9: 12895.39 | Q9: 2065.04 | R9: 11369.44 | S9: =SUM(_25[[#This Row],[2025-01]:[2025-12]]) -> 102382.99
A10: =IF(ISNUMBER(SEARCH("przychody",B10)),"Przychody","Koszty") -> Koszty | B10: B. Koszty działalności operacyjnej | C10: =C9 -> I. Amortyzacja | D10: 61512000 | E10: 61512000 Meble - Amortyzacja | F10: Wynikowe | G10: 965.04 | H10: 1635.1 | I10: 3421.14 | J10: 18409.02 | K10: 1749.81 | L10: 1749.8 | M10: 3748.51 | N10: 1749.81 | O10: 1749.8 | P10: 4649.8 | Q10: 1749.8 | R10: 816.98 | S10: =SUM(_25[[#This Row],[2025-01]:[2025-12]]) -> 42394.61
A11: =IF(ISNUMBER(SEARCH("przychody",B11)),"Przychody","Koszty") -> Koszty | B11: B. Koszty działalności operacyjnej | C11: =C10 -> I. Amortyzacja | D11: 61518000 | E11: 61518000 Samochody - Amortyzacja | F11: Wynikowe | G11: 16100.98 | H11: 16101 | I11: 16100.99 | J11: 13559.44 | K11: 8113.52 | L11: 6162.77 | M11: 6162.45 | N11: 6162.46 | O11: 6162.48 | P11: 6162.47 | Q11: 6162.46 | R11: 6162.46 | S11: =SUM(_25[[#This Row],[2025-01]:[2025-12]]) -> 113113.48
A12: =IF(ISNUMBER(SEARCH("przychody",B12)),"Przychody","Koszty") -> Koszty | B12: B. Koszty działalności operacyjnej | C12: II. Zużycie materiałów i energii | D12: 58502000 | E12: 58502000 Energia cieplna | F12: Wynikowe | G12: 4570.88 | H12: 4099.71 | I12: 4862.37 | J12: 4987.16 | K12: 4558.32 | L12: 4744.18 | M12: 8241.36 | N12: 5397.11 | O12: 5554.37 | P12: 4288.71 | Q12: 5699.53 | R12: 5270.55 | S12: =SUM(_25[[#This Row],[2025-01]:[2025-12]]) -> 62274.25
A13: =IF(ISNUMBER(SEARCH("przychody",B13)),"Przychody","Koszty") -> Koszty | B13: B. Koszty działalności operacyjnej | C13: =C12 -> II. Zużycie materiałów i energii | D13: 58502001 | E13: 58502001 Woda | F13: Wynikowe | G13: 928.32 | H13: 1511.16 | I13: 1199.06 | J13: 1726 | K13: 844.52 | L13: 966.37 | M13: -148.66 | N13: 1216.82 | O13: 1255.33 | P13: 1280.2 | Q13: 814.72 | R13: 1139.18 | S13: =SUM(_25[[#This Row],[2025-01]:[2025-12]]) -> 12733.02
A14: =IF(ISNUMBER(SEARCH("przychody",B14)),"Przychody","Koszty") -> Koszty | B14: B. Koszty działalności operacyjnej | C14: =C13 -> II. Zużycie materiałów i energii | D14: 58502002 | E14: 58502002 Energia elektryczna | F14: Wynikowe | G14: 872.32 | H14: 5284.06 | I14: 2746.11 | J14: 10086.23 | K14: 4947.58 | L14: 1981.79 | M14: 7500.2 | N14: 4769.2 | O14: 5214.36 | P14: 4125.63 | Q14: 5412.44 | R14: 4570.41 | S14: =SUM(_25[[#This Row],[2025-01]:[2025-12]]) -> 57510.33
A15: =IF(ISNUMBER(SEARCH("przychody",B15)),"Przychody","Koszty") -> Koszty | B15: B. Koszty działalności operacyjnej | C15: =C14 -> II. Zużycie materiałów i energii | D15: 58508000 | E15: 58508000 Materiały biurowe | F15: Wynikowe | G15: 3888.21 | H15: 8046.53 | I15: 5925.51 | J15: 10591.79 | K15: 3481.33 | L15: 5980.06 | M15: 5804.8 | N15: 2975.62 | O15: 28115.14 | P15: 3405.81 | Q15: 26075.62 | R15: 5416.46 | S15: =SUM(_25[[#This Row],[2025-01]:[2025-12]]) -> 109706.88
A16: =IF(ISNUMBER(SEARCH("przychody",B16)),"Przychody","Koszty") -> Koszty | B16: B. Koszty działalności operacyjnej | C16: =C15 -> II. Zużycie materiałów i energii | D16: 58552002 | E16: 58552002 Samochody - paliwo 75% | F16: Wynikowe | G16: 0 | H16: 13424.82 | I16: 13326.33 | J16: 7673.38 | K16: 3423.14 | L16: 6973.6 | M16: 9473.02 | N16: 6485.65 | O16: 11046.43 | P16: 8643.36 | Q16: 13399.64 | R16: 6568.65 | S16: =SUM(_25[[#This Row],[2025-01]:[2025-12]]) -> 100438.02
A17: =IF(ISNUMBER(SEARCH("przychody",B17)),"Przychody","Koszty") -> Koszty | B17: B. Koszty działalności operacyjnej | C17: =C16 -> II. Zużycie materiałów i energii | D17: 58552003 | E17: 58552003 Samochody - paliwo 25% | F17: Wynikowe | G17: 0 | H17: 4474.94 | I17: 4442.11 | J17: 2557.79 | K17: 1141.04 | L17: 2324.52 | M17: 3157.65 | N17: 2161.89 | O17: 3701.64 | P17: 2861.56 | Q17: 4466.53 | R17: 2189.54 | S17: =SUM(_25[[#This Row],[2025-01]:[2025-12]]) -> 33479.21
A18: =IF(ISNUMBER(SEARCH("przychody",B18)),"Przychody","Koszty") -> Koszty | B18: B. Koszty działalności operacyjnej | C18: =C17 -> II. Zużycie materiałów i energii | D18: 58552005 | E18: 58552005 Samochody - eksploatacja 75% | F18: Wynikowe | G18: 6578.88 | H18: 7894.13 | I18: 4979.25 | J18: 5105.19 | K18: 7660.35 | L18: 7622.12 | M18: 6784.33 | N18: 3820.27 | O18: 4466.23 | P18: 13632.85 | Q18: 6401.26 | R18: 9230.72 | S18: =SUM(_25[[#This Row],[2025-01]:[2025-12]]) -> 84175.58
A19: =IF(ISNUMBER(SEARCH("przychody",B19)),"Przychody","Koszty") -> Koszty | B19: B. Koszty działalności operacyjnej | C19: =C18 -> II. Zużycie materiałów i energii | D19: 58552025 | E19: 58552025 Samochody - eksploatacja 25% | F19: Wynikowe | G19: 2138.84 | H19: 2975.96 | I19: 1659.72 | J19: 1701.74 | K19: 2563.43 | L19: 2740.7 | M19: 2261.41 | N19: 1273.41 | O19: 1554.23 | P19: 4895.93 | Q19: 2133.71 | R19: 3138.34 | S19: =SUM(_25[[#This Row],[2025-01]:[2025-12]]) -> 29037.42
A20: =IF(ISNUMBER(SEARCH("przychody",B20)),"Przychody","Koszty") -> Koszty | B20: B. Koszty działalności operacyjnej | C20: III. Usługi obce | D20: 53080000 | E20: 53080000 Koszt operacyjny - pozostałe koszty na termin mors | F20: Wynikowe | G20: 22.83 | H20: 0 | I20: 0 | J20: 0 | K20: 0 | L20: 0 | M20: 0 | N20: 0 | O20: 0 | P20: 0 | Q20: 0 | R20: 0 | S20: =SUM(_25[[#This Row],[2025-01]:[2025-12]]) -> 22.83
A21: =IF(ISNUMBER(SEARCH("przychody",B21)),"Przychody","Koszty") -> Koszty | B21: B. Koszty działalności operacyjnej | C21: =C20 -> III. Usługi obce | D21: 58500000 | E21: 58500000 Wynajęcie biura | F21: Wynikowe | G21: 43618.17 | H21: 6220.09 | I21: 65139.98 | J21: 37383.83 | K21: 37738.79 | L21: 36686.81 | M21: 36794.1 | N21: 36392.29 | O21: 36321.9 | P21: 37209.57 | Q21: 37838.26 | R21: 36875.41 | S21: =SUM(_25[[#This Row],[2025-01]:[2025-12]]) -> 448219.2
A22: =IF(ISNUMBER(SEARCH("przychody",B22)),"Przychody","Koszty") -> Koszty | B22: B. Koszty działalności operacyjnej | C22: =C21 -> III. Usługi obce | D22: 58500010 | E22: 58500010 Wynajecie parkingu | F22: Wynikowe | G22: 8194.97 | H22: 2573.17 | I22: 11589.29 | J22: 9158.13 | K22: 9058.49 | L22: 7898.77 | M22: 8730.43 | N22: 8932.14 | O22: 8810.97 | P22: 8314.82 | Q22: 9074.49 | R22: 8581.96 | S22: =SUM(_25[[#This Row],[2025-01]:[2025-12]]) -> 100917.63
A23: =IF(ISNUMBER(SEARCH("przychody",B23)),"Przychody","Koszty") -> Koszty | B23: B. Koszty działalności operacyjnej | C23: =C22 -> III. Usługi obce | D23: 58502003 | E23: 58502003 Ubezpieczenie biura | F23: Wynikowe | G23: 1876.68 | H23: 1894.43 | I23: 1894.43 | J23: 2340.5 | K23: 2102.49 | L23: 2102.49 | M23: 2102.49 | N23: 2102.49 | O23: 2102.49 | P23: 2102.49 | Q23: 2102.49 | R23: 2102.49 | S23: =SUM(_25[[#This Row],[2025-01]:[2025-12]]) -> 24825.96
A24: =IF(ISNUMBER(SEARCH("przychody",B24)),"Przychody","Koszty") -> Koszty | B24: B. Koszty działalności operacyjnej | C24: =C23 -> III. Usługi obce | D24: 58504000 | E24: 58504000 Naprawa biura | F24: Wynikowe | G24: 2588.68 | H24: 1438.68 | I24: 1438.68 | J24: 1984.98 | K24: 2770.21 | L24: 3070.21 | M24: 1570.21 | N24: 1570.21 | O24: 1570.21 | P24: 1570.21 | Q24: 1570.21 | R24: 1570.21 | S24: =SUM(_25[[#This Row],[2025-01]:[2025-12]]) -> 22712.7
A25: =IF(ISNUMBER(SEARCH("przychody",B25)),"Przychody","Koszty") -> Koszty | B25: B. Koszty działalności operacyjnej | C25: =C24 -> III. Usługi obce | D25: 58504001 | E25: 58504001 Eksploatacja biura | F25: Wynikowe | G25: 14370.53 | H25: 3620.96 | I25: 18678.36 | J25: 11848.6 | K25: 20305.13 | L25: 10875.58 | M25: 14371.05 | N25: 10492.94 | O25: 13155.2 | P25: 14632.73 | Q25: 12723.92 | R25: 12812.35 | S25: =SUM(_25[[#This Row],[2025-01]:[2025-12]]) -> 157887.35
A26: =IF(ISNUMBER(SEARCH("przychody",B26)),"Przychody","Koszty") -> Koszty | B26: B. Koszty działalności operacyjnej | C26: =C25 -> III. Usługi obce | D26: 58504002 | E26: 58504002 Sprzątanie biura | F26: Wynikowe | G26: 8520.75 | H26: 1218.86 | I26: 8818.86 | J26: 8292.7 | K26: 6702.42 | L26: 8542.42 | M26: 9100.53 | N26: 8504.31 | O26: 9100.53 | P26: 8504.31 | Q26: 8802.42 | R26: 16700.53 | S26: =SUM(_25[[#This Row],[2025-01]:[2025-12]]) -> 102808.64
A27: =IF(ISNUMBER(SEARCH("przychody",B27)),"Przychody","Koszty") -> Koszty | B27: B. Koszty działalności operacyjnej | C27: IV. Podatki i opłaty | D27: 58506000 | E27: 58506000 Opłaty prawne | F27: Wynikowe | G27: 0 | H27: 33385 | I27: 1 | J27: 0 | K27: 0 | L27: 3 | M27: 350 | N27: 1 | O27: 192 | P27: 900 | Q27: -900 | R27: 0 | S27: =SUM(_25[[#This Row],[2025-01]:[2025-12]]) -> 33932
A28: =IF(ISNUMBER(SEARCH("przychody",B28)),"Przychody","Koszty") -> Koszty | B28: B. Koszty działalności operacyjnej | C28: III. Usługi obce | D28: 58506001 | E28: 58506001 Usługi prawnicze | F28: Wynikowe | G28: 28945.74 | H28: 4580 | I28: 9520 | J28: 4100 | K28: 3500 | L28: 3500 | M28: 3980 | N28: 3500 | O28: 3500 | P28: 3500 | Q28: 4160 | R28: 3740 | S28: =SUM(_25[[#This Row],[2025-01]:[2025-12]]) -> 76525.74
A29: =IF(ISNUMBER(SEARCH("przychody",B29)),"Przychody","Koszty") -> Koszty | B29: B. Koszty działalności operacyjnej | C29: =C28 -> III. Usługi obce | D29: 58506003 | E29: 58506003 Usługi audytorskie | F29: Wynikowe | G29: 0 | H29: 12267.4 | I29: 12302.38 | J29: 0 | K29: 0 | L29: 0 | M29: 0 | N29: 0 | O29: 5020 | P29: 0 | Q29: 0 | R29: 24800 | S29: =SUM(_25[[#This Row],[2025-01]:[2025-12]]) -> 54389.78
A30: =IF(ISNUMBER(SEARCH("przychody",B30)),"Przychody","Koszty") -> Koszty | B30: B. Koszty działalności operacyjnej | C30: =C29 -> III. Usługi obce | D30: 58506004 | E30: 58506004 Usługi doradztwa podatkowego | F30: Wynikowe | G30: 0 | H30: 0 | I30: 0 | J30: 41544.95 | K30: 0 | L30: 0 | M30: 80044.84 | N30: 0 | O30: 24470.6 | P30: 0 | Q30: 22658.13 | R30: 15496.6 | S30: =SUM(_25[[#This Row],[2025-01]:[2025-12]]) -> 184215.12
A31: =IF(ISNUMBER(SEARCH("przychody",B31)),"Przychody","Koszty") -> Koszty | B31: B. Koszty działalności operacyjnej | C31: =C30 -> III. Usługi obce | D31: 58506006 | E31: 58506006 Usługi rekrutacyjne | F31: Wynikowe | G31: 6232.2 | H31: 0 | I31: 0 | J31: 0 | K31: 0 | L31: 0 | M31: 0 | N31: 499 | O31: 0 | P31: 0 | Q31: 0 | R31: 0 | S31: =SUM(_25[[#This Row],[2025-01]:[2025-12]]) -> 6731.2
A32: =IF(ISNUMBER(SEARCH("przychody",B32)),"Przychody","Koszty") -> Koszty | B32: B. Koszty działalności operacyjnej | C32: =C31 -> III. Usługi obce | D32: 58507000 | E32: 58507000 Pozostałe usługi | F32: Wynikowe | G32: 2011 | H32: 1985.88 | I32: 1529.17 | J32: 1038.8 | K32: 6022.8 | L32: 4702.4 | M32: 25.95 | N32: 866.4 | O32: 3533.8 | P32: 1863.85 | Q32: 312.46 | R32: 2305.9 | S32: =SUM(_25[[#This Row],[2025-01]:[2025-12]]) -> 26198.41
A33: =IF(ISNUMBER(SEARCH("przychody",B33)),"Przychody","Koszty") -> Koszty | B33: B. Koszty działalności operacyjnej | C33: =C32 -> III. Usługi obce | D33: 58507001 | E33: 58507001 Archiwizacja | F33: Wynikowe | G33: 0 | H33: 0 | I33: 1755 | J33: 0 | K33: 0 | L33: 0 | M33: 0 | N33: 0 | O33: 0 | P33: 147 | Q33: 0 | R33: 0 | S33: =SUM(_25[[#This Row],[2025-01]:[2025-12]]) -> 1902
A34: =IF(ISNUMBER(SEARCH("przychody",B34)),"Przychody","Koszty") -> Koszty | B34: B. Koszty działalności operacyjnej | C34: =C33 -> III. Usługi obce | D34: 58521000 | E34: 58521000 Telefony stacjonarne | F34: Wynikowe | G34: 5551.22 | H34: 4237.84 | I34: 4189.37 | J34: 4301.69 | K34: 4306.5 | L34: 4199.25 | M34: 4188.08 | N34: 4320.84 | O34: 4167.29 | P34: 4213.27 | Q34: 4302.22 | R34: 4548.96 | S34: =SUM(_25[[#This Row],[2025-01]:[2025-12]]) -> 52526.53
A35: =IF(ISNUMBER(SEARCH("przychody",B35)),"Przychody","Koszty") -> Koszty | B35: B. Koszty działalności operacyjnej | C35: =C34 -> III. Usługi obce | D35: 58522000 | E35: 58522000 Telefony komórkowe | F35: Wynikowe | G35: 1882.58 | H35: 3244.02 | I35: 1787.78 | J35: 1568.18 | K35: 1232.58 | L35: 1224.02 | M35: 360.22 | N35: 2063.55 | O35: 1459.83 | P35: 1478.4 | Q35: 1142.82 | R35: 1147.79 | S35: =SUM(_25[[#This Row],[2025-01]:[2025-12]]) -> 18591.77
A36: =IF(ISNUMBER(SEARCH("przychody",B36)),"Przychody","Koszty") -> Koszty | B36: B. Koszty działalności operacyjnej | C36: =C35 -> III. Usługi obce | D36: 58525000 | E36: 58525000 Internet | F36: Wynikowe | G36: 1950 | H36: 0 | I36: 4519.99 | J36: 2329.99 | K36: 2329.99 | L36: 2190 | M36: 2190 | N36: 2190 | O36: 2190 | P36: 2190 | Q36: 2190 | R36: 2430 | S36: =SUM(_25[[#This Row],[2025-01]:[2025-12]]) -> 26699.97
A37: =IF(ISNUMBER(SEARCH("przychody",B37)),"Przychody","Koszty") -> Koszty | B37: B. Koszty działalności operacyjnej | C37: =C36 -> III. Usługi obce | D37: 58527000 | E37: 58527000 Usługi pocztowe i kurierskie | F37: Wynikowe | G37: 1483.23 | H37: 2603.43 | I37: -1191.97 | J37: 1153.83 | K37: 1127.33 | L37: 1485.05 | M37: 2146.4 | N37: 1513.85 | O37: 1259.56 | P37: 1010.22 | Q37: 1281.68 | R37: 5077.31 | S37: =SUM(_25[[#This Row],[2025-01]:[2025-12]]) -> 18949.92
A38: =IF(ISNUMBER(SEARCH("przychody",B38)),"Przychody","Koszty") -> Koszty | B38: B. Koszty działalności operacyjnej | C38: =C37 -> III. Usługi obce | D38: 58530200 | E38: 58530200 Koszty oprogramowania | F38: Wynikowe | G38: 11019.62 | H38: 8006.1 | I38: 7596.1 | J38: 13813.1 | K38: 7546.1 | L38: 7776.1 | M38: 7643.1 | N38: 6511.1 | O38: 6971.1 | P38: 10946.1 | Q38: 8639.1 | R38: 3006 | S38: =SUM(_25[[#This Row],[2025-01]:[2025-12]]) -> 99473.62
A39: =IF(ISNUMBER(SEARCH("przychody",B39)),"Przychody","Koszty") -> Koszty | B39: B. Koszty działalności operacyjnej | C39: =C38 -> III. Usługi obce | D39: 58530500 | E39: 58530500 Usługi konsultingowe IT | F39: Wynikowe | G39: 3390 | H39: 4580 | I39: 4050 | J39: 5530 | K39: 4170 | L39: 3690 | M39: 4340 | N39: 2140 | O39: 4060 | P39: 5730 | Q39: 10320.2 | R39: 5600 | S39: =SUM(_25[[#This Row],[2025-01]:[2025-12]]) -> 57600.2
A40: =IF(ISNUMBER(SEARCH("przychody",B40)),"Przychody","Koszty") -> Koszty | B40: B. Koszty działalności operacyjnej | C40: =C39 -> III. Usługi obce | D40: 58530700 | E40: 58530700 Pozostałe koszty IT | F40: Wynikowe | G40: 207.45 | H40: 0 | I40: 0 | J40: 1179.2 | K40: 14.7 | L40: 3210.27 | M40: 1121.43 | N40: 0 | O40: 0 | P40: 868.34 | Q40: 926.86 | R40: 0 | S40: =SUM(_25[[#This Row],[2025-01]:[2025-12]]) -> 7528.25
... A49: =IF(ISNUMBER(SEARCH("przychody",B49)),"Przychody","Koszty") -> Koszty | B49: B. Koszty działalności operacyjnej | C49: =C48 -> III. Usługi obce | D49: 58590000 | E49: 58590000 Rafaktura kosztów | F49: Wynikowe | G49: 0 | H49: 0 | I49: 0 | J49: 0 | K49: 0 | L49: 0 | M49: 0 | N49: 975 | O49: 567.16 | P49: 2944.31 | Q49: 489.04 | R49: 1846.81 | S49: =SUM(_25[[#This Row],[2025-01]:[2025-12]]) -> 6822.32
A50: =IF(ISNUMBER(SEARCH("przychody",B50)),"Przychody","Koszty") -> Koszty | B50: B. Koszty działalności operacyjnej | C50: VII. Pozostałe koszty rodzajowe | D50: 59080000 | E50: 59080000 Pozostałe koszty pracownicze | F50: Wynikowe | G50: 0 | H50: 9505.77 | I50: 9304.18 | J50: 6741.03 | K50: 3010.6 | L50: 3789.66 | M50: 10725.92 | N50: 4167.48 | O50: 5261.78 | P50: 5056.64 | Q50: 5493.08 | R50: 10405.06 | S50: =SUM(_25[[#This Row],[2025-01]:[2025-12]]) -> 73461.2
A51: =IF(ISNUMBER(SEARCH("przychody",B51)),"Przychody","Koszty") -> Koszty | B51: B. Koszty działalności operacyjnej | C51: III. Usługi obce | D51: 59504050 | E51: 59504050 Różne koszty operacyjne | F51: Wynikowe | G51: 0 | H51: 0 | I51: 0 | J51: 0 | K51: 0 | L51: 0 | M51: 0 | N51: 0 | O51: 0 | P51: 0 | Q51: 0 | R51: 0 | S51: =SUM(_25[[#This Row],[2025-01]:[2025-12]]) -> 0
A52: =IF(ISNUMBER(SEARCH("przychody",B52)),"Przychody","Koszty") -> Koszty | B52: B. Koszty działalności operacyjnej | C52: III. Usługi obce | D52: 65518000 | E52: 65518000 Opłaty i prowizje bankowe | F52: Wynikowe | G52: 1839.17 | H52: 1610.73 | I52: 1491.76 | J52: 1092.5 | K52: 1059.64 | L52: 2080.95 | M52: 2692.84 | N52: 940.01 | O52: 1459.24 | P52: 1356.76 | Q52: 2192.38 | R52: 895.49 | S52: =SUM(_25[[#This Row],[2025-01]:[2025-12]]) -> 18711.47
A53: =IF(ISNUMBER(SEARCH("przychody",B53)),"Przychody","Koszty") -> Koszty | B53: B. Koszty działalności operacyjnej | C53: IV. Podatki i opłaty | D53: 59080040 | E53: 59080040 PFRON | F53: Wynikowe | G53: 11977 | H53: 11654 | I53: 0 | J53: 24681 | K53: 12213 | L53: 0 | M53: 24954 | N53: 12672 | O53: 9702 | P53: 9640 | Q53: 9660 | R53: 10065 | S53: =SUM(_25[[#This Row],[2025-01]:[2025-12]]) -> 137218
A54: =IF(ISNUMBER(SEARCH("przychody",B54)),"Przychody","Koszty") -> Koszty | B54: B. Koszty działalności operacyjnej | C54: IV. Podatki i opłaty | D54: 59500040 | E54: 59500040 Podatek od nieruchomości | F54: Wynikowe | G54: 2191.55 | H54: 2191.55 | I54: 2191.55 | J54: 2267.68 | K54: 2224.43 | L54: 2224.43 | M54: 2224.43 | N54: 2224.43 | O54: 2224.43 | P54: 2224.43 | Q54: 2224.43 | R54: 2227.43 | S54: =SUM(_25[[#This Row],[2025-01]:[2025-12]]) -> 26640.77
A55: =IF(ISNUMBER(SEARCH("przychody",B55)),"Przychody","Koszty") -> Koszty | B55: B. Koszty działalności operacyjnej | C55: IV. Podatki i opłaty | D55: 59500050 | E55: 59500050 VAT nie do odliczenia KUP | F55: Wynikowe | G55: 5209.71 | H55: 5352.19 | I55: 4832.47 | J55: 4774.46 | K55: 4283.24 | L55: 4688.01 | M55: 4874.48 | N55: 3914.94 | O55: 4540.83 | P55: 5433.43 | Q55: 5472.95 | R55: 4650.4 | S55: =SUM(_25[[#This Row],[2025-01]:[2025-12]]) -> 58027.11
A56: =IF(ISNUMBER(SEARCH("przychody",B56)),"Przychody","Koszty") -> Koszty | B56: B. Koszty działalności operacyjnej | C56: IV. Podatki i opłaty | D56: 59500051 | E56: 59500051 VAT nie do odliczenia NKUP | F56: Wynikowe | G56: 1510.99 | H56: 756.59 | I56: 936.37 | J56: 1281.04 | K56: 925.61 | L56: 1060.22 | M56: 1118.93 | N56: 454.86 | O56: 1094.08 | P56: 1297.81 | Q56: 1471.41 | R56: 885.33 | S56: =SUM(_25[[#This Row],[2025-01]:[2025-12]]) -> 12793.24
A57: =IF(ISNUMBER(SEARCH("przychody",B57)),"Przychody","Koszty") -> Koszty | B57: B. Koszty działalności operacyjnej | C57: V. Wynagrodzenia | D57: 59000000 | E57: 59000000 Wynagrodzenia osobowe | F57: Wynikowe | G57: 1107101.9 | H57: 1089088.7 | I57: 1091297.8 | J57: 1092961.2 | K57: 1071577.3 | L57: 1060328.3 | M57: 1058152.5 | N57: 1086590.2 | O57: 1078871.1 | P57: 1085071.1 | Q57: 1091726.7 | R57: 1102354.8 | S57: =SUM(_25[[#This Row],[2025-01]:[2025-12]]) -> 13015122
A58: =IF(ISNUMBER(SEARCH("przychody",B58)),"Przychody","Koszty") -> Koszty | B58: B. Koszty działalności operacyjnej | C58: V. Wynagrodzenia | D58: 59002000 | E58: 59002000 Premia roczna | F58: Wynikowe | G58: 0 | H58: 0 | I58: 0 | J58: -44723 | K58: 0 | L58: 214871.88 | M58: 0 | N58: 0 | O58: 0 | P58: 0 | Q58: 0 | R58: 1212000 | S58: =SUM(_25[[#This Row],[2025-01]:[2025-12]]) -> 1382148.9
A59: =IF(ISNUMBER(SEARCH("przychody",B59)),"Przychody","Koszty") -> Koszty | B59: B. Koszty działalności operacyjnej | C59: V. Wynagrodzenia | D59: 59002200 | E59: 59002200 Nadgodziny | F59: Wynikowe | G59: 0 | H59: 0 | I59: 0 | J59: 1471.54 | K59: 0 | L59: 0 | M59: 579.46 | N59: 118.33 | O59: 201.01 | P59: 589.17 | Q59: 0 | R59: 1120.69 | S59: =SUM(_25[[#This Row],[2025-01]:[2025-12]]) -> 4080.2
A60: =IF(ISNUMBER(SEARCH("przychody",B60)),"Przychody","Koszty") -> Koszty | B60: B. Koszty działalności operacyjnej | C60: V. Wynagrodzenia | D60: 59018300 | E60: 59018300 Rezerwa na odprawę emerytalną | F60: Wynikowe | G60: 0 | H60: -2375 | I60: 30575 | J60: 0 | K60: 45000 | L60: 0 | M60: 0 | N60: 0 | O60: 0 | P60: 0 | Q60: 7639.17 | R60: -9219.07 | S60: =SUM(_25[[#This Row],[2025-01]:[2025-12]]) -> 71620.1
A61: =IF(ISNUMBER(SEARCH("przychody",B61)),"Przychody","Koszty") -> Koszty | B61: B. Koszty działalności operacyjnej | C61: V. Wynagrodzenia | D61: 59040000 | E61: 59040000 Pozostałe świadczenia pracownicze | F61: Wynikowe | G61: 17114.62 | H61: -5987.01 | I61: -15628.31 | J61: 0 | K61: 0 | L61: 2232.42 | M61: 2678.72 | N61: 2776.87 | O61: 2985.4 | P61: 3493.57 | Q61: 863.52 | R61: 1028.34 | S61: =SUM(_25[[#This Row],[2025-01]:[2025-12]]) -> 11558.14
... A104: =IF(ISNUMBER(SEARCH("przychody",B104)),"Przychody","Koszty") -> Koszty | B104: H. Koszty finansowe | C104: IV. Inne | D104: 65528110 | E104: 65528110 Zrealiz ujemne różnice kursowe od należ | F104: Wynikowe | G104: 15.15 | H104: 0 | I104: 0 | J104: 0 | K104: 0 | L104: 0 | M104: 0 | N104: 0 | O104: 0 | P104: 0 | Q104: 0 | R104: 0 | S104: =SUM(_25[[#This Row],[2025-01]:[2025-12]]) -> 15.15
A105: =IF(ISNUMBER(SEARCH("przychody",B105)),"Przychody","Koszty") -> Koszty | B105: J. Podatek dochodowy | D105: 70000000 | E105: 70000000 Podatek dochodowy - bieżacy okres | F105: Wynikowe | G105: 0 | H105: 44113.25 | I105: 43210.75 | J105: 320688.27 | K105: 43662 | L105: 43662 | M105: 43662 | N105: 43662 | O105: 287538.99 | P105: 43662 | Q105: 43662 | R105: -798771.91 | S105: =SUM(_25[[#This Row],[2025-01]:[2025-12]]) -> 158751.35
A106: =IF(ISNUMBER(SEARCH("przychody",B106)),"Przychody","Koszty") -> Koszty | B106: H. Koszty finansowe | C106: IV. Inne | D106: 60500000 | E106: 60500000 Niezrealiz dodatnie róż kurs od zabezp należ (TFx) | F106: Wynikowe | G106: 0 | H106: 0 | I106: 0 | J106: 0 | K106: 0 | L106: 0 | M106: 0 | N106: 0 | O106: 0 | P106: 0 | Q106: 0 | R106: -416.67 | S106: =SUM(_25[[#This Row],[2025-01]:[2025-12]]) -> -416.67
A107: =IF(ISNUMBER(SEARCH("przychody",B107)),"Przychody","Koszty") -> Koszty | B107: H. Koszty finansowe | C107: IV. Inne | D107: 60501000 | E107: 60501000 Niezrealiz ujemne róż kurs od zabezp należ (TFx) | F107: Wynikowe | G107: 0 | H107: 0 | I107: 0 | J107: 0 | K107: 0 | L107: 0 | M107: 0 | N107: 0 | O107: 0 | P107: 0 | Q107: 0 | R107: 130.12 | S107: =SUM(_25[[#This Row],[2025-01]:[2025-12]]) -> 130.12
B108: C. Zysk/ (strata) ze sprzedaży | G108: =SUMIF($B$2:$B$107,"A. Przychody netto ze sprzedaży i zrównane z nimi, w tym:",G2:G107) - SUMIF($B$2:$B$107,"B. Koszty działalności operacyjnej",G2:G107) -> 182289.91 | H108: =SUMIF($B$2:$B$107,"A. Przychody netto ze sprzedaży i zrównane z nimi, w tym:",H2:H107) - SUMIF($B$2:$B$107,"B. Koszty działalności operacyjnej",H2:H107) -> 202712.45 | I108: =SUMIF($B$2:$B$107,"A. Przychody netto ze sprzedaży i zrównane z nimi, w tym:",I2:I107) - SUMIF($B$2:$B$107,"B. Koszty działalności operacyjnej",I2:I107) -> 47651.57 | J108: =SUMIF($B$2:$B$107,"A. Przychody netto ze sprzedaży i zrównane z nimi, w tym:",J2:J107) - SUMIF($B$2:$B$107,"B. Koszty działalności operacyjnej",J2:J107) -> -246592.82 | K108: =SUMIF($B$2:$B$107,"A. Przychody netto ze sprzedaży i zrównane z nimi, w tym:",K2:K107) - SUMIF($B$2:$B$107,"B. Koszty działalności operacyjnej",K2:K107) -> 123464.15 | L108: =SUMIF($B$2:$B$107,"A. Przychody netto ze sprzedaży i zrównane z nimi, w tym:",L2:L107) - SUMIF($B$2:$B$107,"B. Koszty działalności operacyjnej",L2:L107) -> -144068.71 | M108: =SUMIF($B$2:$B$107,"A. Przychody netto ze sprzedaży i zrównane z nimi, w tym:",M2:M107) - SUMIF($B$2:$B$107,"B. Koszty działalności operacyjnej",M2:M107) -> 60619.56 | N108: =SUMIF($B$2:$B$107,"A. Przychody netto ze sprzedaży i zrównane z nimi, w tym:",N2:N107) - SUMIF($B$2:$B$107,"B. Koszty działalności operacyjnej",N2:N107) -> 163286.38 | ... R108: =SUMIF($B$2:$B$107,"A. Przychody netto ze sprzedaży i zrównane z nimi, w tym:",R2:R107) - SUMIF($B$2:$B$107,"B. Koszty działalności operacyjnej",R2:R107) -> -214097.45 | S108: =SUM(_25[[#This Row],[2025-01]:[2025-12]]) -> 381160.63
B109: F. Zysk/ (strata) z działalności operacyjnej | G109: =G108 + SUMIF($B$2:$B$107,"D. Pozostałe przychody operacyjne",G2:G107) - SUMIF($B$2:$B$107,"E. Pozostałe koszty operacyjne",G2:G107) -> 186990.36 | H109: =H108 + SUMIF($B$2:$B$107,"D. Pozostałe przychody operacyjne",H2:H107) - SUMIF($B$2:$B$107,"E. Pozostałe koszty operacyjne",H2:H107) -> 206231.73 | I109: =I108 + SUMIF($B$2:$B$107,"D. Pozostałe przychody operacyjne",I2:I107) - SUMIF($B$2:$B$107,"E. Pozostałe koszty operacyjne",I2:I107) -> 102967.71 | J109: =J108 + SUMIF($B$2:$B$107,"D. Pozostałe przychody operacyjne",J2:J107) - SUMIF($B$2:$B$107,"E. Pozostałe koszty operacyjne",J2:J107) -> -254701.37 | K109: =K108 + SUMIF($B$2:$B$107,"D. Pozostałe przychody operacyjne",K2:K107) - SUMIF($B$2:$B$107,"E. Pozostałe koszty operacyjne",K2:K107) -> 124566.61 | L109: =L108 + SUMIF($B$2:$B$107,"D. Pozostałe przychody operacyjne",L2:L107) - SUMIF($B$2:$B$107,"E. Pozostałe koszty operacyjne",L2:L107) -> -142517.5 | M109: =M108 + SUMIF($B$2:$B$107,"D. Pozostałe przychody operacyjne",M2:M107) - SUMIF($B$2:$B$107,"E. Pozostałe koszty operacyjne",M2:M107) -> 64765.06 | N109: =N108 + SUMIF($B$2:$B$107,"D. Pozostałe przychody operacyjne",N2:N107) - SUMIF($B$2:$B$107,"E. Pozostałe koszty operacyjne",N2:N107) -> 166611.07 | ... R109: =R108 + SUMIF($B$2:$B$107,"D. Pozostałe przychody operacyjne",R2:R107) - SUMIF($B$2:$B$107,"E. Pozostałe koszty operacyjne",R2:R107) -> -201866.96 | S109: =SUM(_25[[#This Row],[2025-01]:[2025-12]]) -> 488521.7
B110: I. Zysk/ (strata) brutto | G110: =G109 + SUMIF($B$2:$B$107,"G. Przychody finansowe",G2:G107) - SUMIF($B$2:$B$107,"H. Koszty finansowe",G2:G107) -> 181516.08 | H110: =H109 + SUMIF($B$2:$B$107,"G. Przychody finansowe",H2:H107) - SUMIF($B$2:$B$107,"H. Koszty finansowe",H2:H107) -> 205894.24 | I110: =I109 + SUMIF($B$2:$B$107,"G. Przychody finansowe",I2:I107) - SUMIF($B$2:$B$107,"H. Koszty finansowe",I2:I107) -> 97515.32 | J110: =J109 + SUMIF($B$2:$B$107,"G. Przychody finansowe",J2:J107) - SUMIF($B$2:$B$107,"H. Koszty finansowe",J2:J107) -> -255104.99 | K110: =K109 + SUMIF($B$2:$B$107,"G. Przychody finansowe",K2:K107) - SUMIF($B$2:$B$107,"H. Koszty finansowe",K2:K107) -> 124566.46 | L110: =L109 + SUMIF($B$2:$B$107,"G. Przychody finansowe",L2:L107) - SUMIF($B$2:$B$107,"H. Koszty finansowe",L2:L107) -> -139941.6 | M110: =M109 + SUMIF($B$2:$B$107,"G. Przychody finansowe",M2:M107) - SUMIF($B$2:$B$107,"H. Koszty finansowe",M2:M107) -> 65304.13 | N110: =N109 + SUMIF($B$2:$B$107,"G. Przychody finansowe",N2:N107) - SUMIF($B$2:$B$107,"H. Koszty finansowe",N2:N107) -> 166775.27 | ... R110: =R109 + SUMIF($B$2:$B$107,"G. Przychody finansowe",R2:R107) - SUMIF($B$2:$B$107,"H. Koszty finansowe",R2:R107) -> -199900.63 | S110: =SUM(_25[[#This Row],[2025-01]:[2025-12]]) -> 483387.69
B111: L. Zysk/ (strata) netto | G111: =G116 -> 181516.08 | H111: =H116 -> 161780.99 | I111: =I116 -> 54304.57 | J111: =J116 -> -575793.26 | K111: =K116 -> 80904.46 | L111: =L116 -> -183603.6 | M111: =M116 -> 21642.13 | N111: =N116 -> 123113.27 | ... R111: =R116 -> 598871.28 | S111: =SUM(_25[[#This Row],[2025-01]:[2025-12]]) -> 324636.34
F114: P | G114: =SUMIF($A$2:$A$107,"Przychody",G2:G107) -> 1882845.9 | H114: =SUMIF($A$2:$A$111,"Przychody",H2:H111) -> 1848141.3 | I114: =SUMIF($A$2:$A$111,"Przychody",I2:I111) -> 1857702 | J114: =SUMIF($A$2:$A$111,"Przychody",J2:J111) -> 1432072.4 | K114: =SUMIF($A$2:$A$111,"Przychody",K2:K111) -> 1742919.5 | L114: =SUMIF($A$2:$A$111,"Przychody",L2:L111) -> 1688124.2 | M114: =SUMIF($A$2:$A$111,"Przychody",M2:M111) -> 1737508.5 | N114: =SUMIF($A$2:$A$111,"Przychody",N2:N111) -> 1736687.7 | O114: =SUMIF($A$2:$A$111,"Przychody",O2:O111) -> 1736319 | ... R114: =SUMIF($A$2:$A$111,"Przychody",R2:R111) -> 3193141
F115: K | G115: =SUMIF($A$2:$A$107,"Koszty",G2:G107) -> 1701329.8 | H115: =SUMIF($A$2:$A$111,"Koszty",H2:H111) -> 1686360.3 | I115: =SUMIF($A$2:$A$111,"Koszty",I2:I111) -> 1803397.5 | J115: =SUMIF($A$2:$A$111,"Koszty",J2:J111) -> 2007865.7 | K115: =SUMIF($A$2:$A$111,"Koszty",K2:K111) -> 1662015 | L115: =SUMIF($A$2:$A$111,"Koszty",L2:L111) -> 1871727.8 | M115: =SUMIF($A$2:$A$111,"Koszty",M2:M111) -> 1715866.4 | N115: =SUMIF($A$2:$A$111,"Koszty",N2:N111) -> 1613574.4 | O115: =SUMIF($A$2:$A$111,"Koszty",O2:O111) -> 1930244.2 | ... R115: =SUMIF($A$2:$A$111,"Koszty",R2:R111) -> 2594269.7
F116: Z | G116: =G114-G115 -> 181516.08 | H116: =H114-H115 -> 161780.99 | I116: =I114-I115 -> 54304.57 | J116: =J114-J115 -> -575793.26 | K116: =K114-K115 -> 80904.46 | L116: =L114-L115 -> -183603.6 | M116: =M114-M115 -> 21642.13 | N116: =N114-N115 -> 123113.27 | ... R116: =R114-R115 -> 598871.28 | S116: =SUM(G116:R116) -> 324636.34
G119: 2025-01 | H119: 2025-02 | I119: 2025-03 | J119: 2025-04 | K119: 2025-05 | L119: 2025-06 | M119: 2025-07 | N119: 2025-08 | O119: 2025-09 | P119: 2025-10 | Q119: 2025-11 | R119: 2025-12

Sheet 25 RZiS Zmapowane
A1: Rodzaj1 | B1: Rodzaj2 | C1: Rodzaj3 | D1: Numer konta | E1: Nazwa konta | F1: Rodzaj konta (bilansowe/wynikowe) | G1: 2025/Jan | H1: 2025/Feb | I1: 2025/Mar | J1: 2025/Apr | K1: 2025/May | L1: 2025/Jun | M1: 2025/Jul | N1: 2025/Aug | O1: 2025/Sep | P1: 2025/Oct | Q1: 2025/Nov | R1: 2025/Dec
A2: =IF(ISNUMBER(SEARCH("przychody",C2)),"Przychody","Koszty") -> Przychody | B2: A. Przychody netto ze sprzedaży i zrównane z nimi, w tym: | C2: I. Przychody netto ze sprzedaży produktów | D2: 45510000 | E2: 45510000 Prowizja Cost+ | F2: Wynikowe | G2: -1877205 | H2: -1844622 | I2: -1802379 | J2: -1430181 | K2: -1741817 | L2: -1686073 | M2: -1733363 | N2: -1733363 | O2: -1733363 | P2: -1711660 | Q2: -1711660 | R2: -3177425
A3: =IF(ISNUMBER(SEARCH("przychody",C3)),"Przychody","Koszty") -> Przychody | B3: A. Przychody netto ze sprzedaży i zrównane z nimi, w tym: | C3: I. Przychody netto ze sprzedaży produktów | D3: 44000000 | E3: 44000000 Przychód operacyjny - opłata za konosament | F3: Wynikowe | G3: 0 | H3: 0 | I3: 0 | J3: 0 | K3: 0 | L3: 0 | M3: 0 | N3: 0 | O3: 0 | P3: 0 | Q3: 0 | R3: 0
A4: =IF(ISNUMBER(SEARCH("przychody",C4)),"Przychody","Koszty") -> Przychody | B4: A. Przychody netto ze sprzedaży i zrównane z nimi, w tym: | C4: I. Przychody netto ze sprzedaży produktów | D4: 44000005 | E4: 44000005 Przychód operacyjny - opłata dokumentacyjna EXP | F4: Wynikowe | G4: 0 | H4: 0 | I4: 0 | J4: 0 | K4: 0 | L4: 0 | M4: 0 | N4: 0 | O4: 0 | P4: 0 | Q4: 0 | R4: 0
A5: =IF(ISNUMBER(SEARCH("przychody",C5)),"Przychody","Koszty") -> Przychody | B5: A. Przychody netto ze sprzedaży i zrównane z nimi, w tym: | C5: I. Przychody netto ze sprzedaży produktów | D5: 44006000 | E5: 44006000 Przychód operacyjny - korekta manifestu | F5: Wynikowe | G5: 0 | H5: 0 | I5: 0 | J5: 0 | K5: 0 | L5: 0 | M5: 0 | N5: 0 | O5: 0 | P5: 0 | Q5: 0 | R5: 0
A6: =IF(ISNUMBER(SEARCH("przychody",C6)),"Przychody","Koszty") -> Koszty | B6: B. Koszty działalności operacyjnej | C6: I. Amortyzacja | D6: 61000000 | E6: 61000000 Oprogramowanie i licencje IT - Amortyzacja | F6: Wynikowe | G6: 926.5 | H6: 926.5 | I6: 926.5 | J6: 926.5 | K6: 926.5 | L6: 926.5 | M6: 926.5 | N6: 926.5 | O6: 926.5 | P6: 926.5 | Q6: 926.5 | R6: 926.5
A7: =IF(ISNUMBER(SEARCH("przychody",C7)),"Przychody","Koszty") -> Koszty | B7: B. Koszty działalności operacyjnej | C7: =C6 -> I. Amortyzacja | D7: 61502000 | E7: 61502000 Budynki - Amortyzacja | F7: Wynikowe | G7: 17326.2 | H7: 17326.2 | I7: 17326.21 | J7: 17326.2 | K7: 17326.2 | L7: 17326.2 | M7: 17326.2 | N7: 17326.2 | O7: 17326.21 | P7: 17326.2 | Q7: 17326.2 | R7: 17326.2
A8: =IF(ISNUMBER(SEARCH("przychody",C8)),"Przychody","Koszty") -> Koszty | B8: B. Koszty działalności operacyjnej | C8: =C7 -> I. Amortyzacja | D8: 61504000 | E8: 61504000 Nakłady w obcych środkach trwał - Amortyzacja | F8: Wynikowe | G8: 313.46 | H8: 313.45 | I8: 313.46 | J8: 313.46 | K8: 6769.34 | L8: 1604.64 | M8: 1604.64 | N8: 1604.63 | O8: 1604.64 | P8: 1604.63 | Q8: 1604.63 | R8: 1604.64
A9: =IF(ISNUMBER(SEARCH("przychody",C9)),"Przychody","Koszty") -> Koszty | B9: B. Koszty działalności operacyjnej | C9: =C8 -> I. Amortyzacja | D9: 61508000 | E9: 61508000 Komputery i sprzęt IT - Amortyzacja | F9: Wynikowe | G9: 10218.3 | H9: 8464.79 | I9: 11588.15 | J9: 24240.21 | K9: 459 | L9: 0 | M9: 16357.33 | N9: 579 | O9: 4146.34 | P9: 12895.39 | Q9: 2065.04 | R9: 11369.44
A10: =IF(ISNUMBER(SEARCH("przychody",C10)),"Przychody","Koszty") -> Koszty | B10: B. Koszty działalności operacyjnej | C10: =C9 -> I. Amortyzacja | D10: 61512000 | E10: 61512000 Meble - Amortyzacja | F10: Wynikowe | G10: 965.04 | H10: 1635.1 | I10: 3421.14 | J10: 18409.02 | K10: 1749.81 | L10: 1749.8 | M10: 3748.51 | N10: 1749.81 | O10: 1749.8 | P10: 4649.8 | Q10: 1749.8 | R10: 816.98
A11: =IF(ISNUMBER(SEARCH("przychody",C11)),"Przychody","Koszty") -> Koszty | B11: B. Koszty działalności operacyjnej | C11: =C10 -> I. Amortyzacja | D11: 61518000 | E11: 61518000 Samochody - Amortyzacja | F11: Wynikowe | G11: 16100.98 | H11: 16101 | I11: 16100.99 | J11: 13559.44 | K11: 8113.52 | L11: 6162.77 | M11: 6162.45 | N11: 6162.46 | O11: 6162.48 | P11: 6162.47 | Q11: 6162.46 | R11: 6162.46
A12: =IF(ISNUMBER(SEARCH("przychody",C12)),"Przychody","Koszty") -> Koszty | B12: B. Koszty działalności operacyjnej | C12: II. Zużycie materiałów i energii | D12: 58502000 | E12: 58502000 Energia cieplna | F12: Wynikowe | G12: 4570.88 | H12: 4099.71 | I12: 4862.37 | J12: 4987.16 | K12: 4558.32 | L12: 4744.18 | M12: 8241.36 | N12: 5397.11 | O12: 5554.37 | P12: 4288.71 | Q12: 5699.53 | R12: 5270.55
A13: =IF(ISNUMBER(SEARCH("przychody",C13)),"Przychody","Koszty") -> Koszty | B13: B. Koszty działalności operacyjnej | C13: =C12 -> II. Zużycie materiałów i energii | D13: 58502001 | E13: 58502001 Woda | F13: Wynikowe | G13: 928.32 | H13: 1511.16 | I13: 1199.06 | J13: 1726 | K13: 844.52 | L13: 966.37 | M13: -148.66 | N13: 1216.82 | O13: 1255.33 | P13: 1280.2 | Q13: 814.72 | R13: 1139.18
A14: =IF(ISNUMBER(SEARCH("przychody",C14)),"Przychody","Koszty") -> Koszty | B14: B. Koszty działalności operacyjnej | C14: =C13 -> II. Zużycie materiałów i energii | D14: 58502002 | E14: 58502002 Energia elektryczna | F14: Wynikowe | G14: 872.32 | H14: 5284.06 | I14: 2746.11 | J14: 10086.23 | K14: 4947.58 | L14: 1981.79 | M14: 7500.2 | N14: 4769.2 | O14: 5214.36 | P14: 4125.63 | Q14: 5412.44 | R14: 4570.41
A15: =IF(ISNUMBER(SEARCH("przychody",C15)),"Przychody","Koszty") -> Koszty | B15: B. Koszty działalności operacyjnej | C15: =C14 -> II. Zużycie materiałów i energii | D15: 58508000 | E15: 58508000 Materiały biurowe | F15: Wynikowe | G15: 3888.21 | H15: 8046.53 | I15: 5925.51 | J15: 10591.79 | K15: 3481.33 | L15: 5980.06 | M15: 5804.8 | N15: 2975.62 | O15: 28115.14 | P15: 3405.81 | Q15: 26075.62 | R15: 5416.46
A16: =IF(ISNUMBER(SEARCH("przychody",C16)),"Przychody","Koszty") -> Koszty | B16: B. Koszty działalności operacyjnej | C16: =C15 -> II. Zużycie materiałów i energii | D16: 58552002 | E16: 58552002 Samochody - paliwo 75% | F16: Wynikowe | G16: 0 | H16: 13424.82 | I16: 13326.33 | J16: 7673.38 | K16: 3423.14 | L16: 6973.6 | M16: 9473.02 | N16: 6485.65 | O16: 11046.43 | P16: 8643.36 | Q16: 13399.64 | R16: 6568.65
A17: =IF(ISNUMBER(SEARCH("przychody",C17)),"Przychody","Koszty") -> Koszty | B17: B. Koszty działalności operacyjnej | C17: =C16 -> II. Zużycie materiałów i energii | D17: 58552003 | E17: 58552003 Samochody - paliwo 25% | F17: Wynikowe | G17: 0 | H17: 4474.94 | I17: 4442.11 | J17: 2557.79 | K17: 1141.04 | L17: 2324.52 | M17: 3157.65 | N17: 2161.89 | O17: 3701.64 | P17: 2861.56 | Q17: 4466.53 | R17: 2189.54
A18: =IF(ISNUMBER(SEARCH("przychody",C18)),"Przychody","Koszty") -> Koszty | B18: B. Koszty działalności operacyjnej | C18: =C17 -> II. Zużycie materiałów i energii | D18: 58552005 | E18: 58552005 Samochody - eksploatacja 75% | F18: Wynikowe | G18: 6578.88 | H18: 7894.13 | I18: 4979.25 | J18: 5105.19 | K18: 7660.35 | L18: 7622.12 | M18: 6784.33 | N18: 3820.27 | O18: 4466.23 | P18: 13632.85 | Q18: 6401.26 | R18: 9230.72
A19: =IF(ISNUMBER(SEARCH("przychody",C19)),"Przychody","Koszty") -> Koszty | B19: B. Koszty działalności operacyjnej | C19: =C18 -> II. Zużycie materiałów i energii | D19: 58552025 | E19: 58552025 Samochody - eksploatacja 25% | F19: Wynikowe | G19: 2138.84 | H19: 2975.96 | I19: 1659.72 | J19: 1701.74 | K19: 2563.43 | L19: 2740.7 | M19: 2261.41 | N19: 1273.41 | O19: 1554.23 | P19: 4895.93 | Q19: 2133.71 | R19: 3138.34
A20: =IF(ISNUMBER(SEARCH("przychody",C20)),"Przychody","Koszty") -> Koszty | B20: B. Koszty działalności operacyjnej | C20: III. Usługi obce | D20: 53080000 | E20: 53080000 Koszt operacyjny - pozostałe koszty na termin mors | F20: Wynikowe | G20: 22.83 | H20: 0 | I20: 0 | J20: 0 | K20: 0 | L20: 0 | M20: 0 | N20: 0 | O20: 0 | P20: 0 | Q20: 0 | R20: 0
A21: =IF(ISNUMBER(SEARCH("przychody",C21)),"Przychody","Koszty") -> Koszty | B21: B. Koszty działalności operacyjnej | C21: =C20 -> III. Usługi obce | D21: 58500000 | E21: 58500000 Wynajęcie biura | F21: Wynikowe | G21: 43618.17 | H21: 6220.09 | I21: 65139.98 | J21: 37383.83 | K21: 37738.79 | L21: 36686.81 | M21: 36794.1 | N21: 36392.29 | O21: 36321.9 | P21: 37209.57 | Q21: 37838.26 | R21: 36875.41
A22: =IF(ISNUMBER(SEARCH("przychody",C22)),"Przychody","Koszty") -> Koszty | B22: B. Koszty działalności operacyjnej | C22: =C21 -> III. Usługi obce | D22: 58500010 | E22: 58500010 Wynajecie parkingu | F22: Wynikowe | G22: 8194.97 | H22: 2573.17 | I22: 11589.29 | J22: 9158.13 | K22: 9058.49 | L22: 7898.77 | M22: 8730.43 | N22: 8932.14 | O22: 8810.97 | P22: 8314.82 | Q22: 9074.49 | R22: 8581.96
A23: =IF(ISNUMBER(SEARCH("przychody",C23)),"Przychody","Koszty") -> Koszty | B23: B. Koszty działalności operacyjnej | C23: =C22 -> III. Usługi obce | D23: 58502003 | E23: 58502003 Ubezpieczenie biura | F23: Wynikowe | G23: 1876.68 | H23: 1894.43 | I23: 1894.43 | J23: 2340.5 | K23: 2102.49 | L23: 2102.49 | M23: 2102.49 | N23: 2102.49 | O23: 2102.49 | P23: 2102.49 | Q23: 2102.49 | R23: 2102.49
A24: =IF(ISNUMBER(SEARCH("przychody",C24)),"Przychody","Koszty") -> Koszty | B24: B. Koszty działalności operacyjnej | C24: =C23 -> III. Usługi obce | D24: 58504000 | E24: 58504000 Naprawa biura | F24: Wynikowe | G24: 2588.68 | H24: 1438.68 | I24: 1438.68 | J24: 1984.98 | K24: 2770.21 | L24: 3070.21 | M24: 1570.21 | N24: 1570.21 | O24: 1570.21 | P24: 1570.21 | Q24: 1570.21 | R24: 1570.21
A25: =IF(ISNUMBER(SEARCH("przychody",C25)),"Przychody","Koszty") -> Koszty | B25: B. Koszty działalności operacyjnej | C25: =C24 -> III. Usługi obce | D25: 58504001 | E25: 58504001 Eksploatacja biura | F25: Wynikowe | G25: 14370.53 | H25: 3620.96 | I25: 18678.36 | J25: 11848.6 | K25: 20305.13 | L25: 10875.58 | M25: 14371.05 | N25: 10492.94 | O25: 13155.2 | P25: 14632.73 | Q25: 12723.92 | R25: 12812.35
A26: =IF(ISNUMBER(SEARCH("przychody",C26)),"Przychody","Koszty") -> Koszty | B26: B. Koszty działalności operacyjnej | C26: =C25 -> III. Usługi obce | D26: 58504002 | E26: 58504002 Sprzątanie biura | F26: Wynikowe | G26: 8520.75 | H26: 1218.86 | I26: 8818.86 | J26: 8292.7 | K26: 6702.42 | L26: 8542.42 | M26: 9100.53 | N26: 8504.31 | O26: 9100.53 | P26: 8504.31 | Q26: 8802.42 | R26: 16700.53
A27: =IF(ISNUMBER(SEARCH("przychody",C27)),"Przychody","Koszty") -> Koszty | B27: B. Koszty działalności operacyjnej | C27: IV. Podatki i opłaty | D27: 58506000 | E27: 58506000 Opłaty prawne | F27: Wynikowe | G27: 0 | H27: 33385 | I27: 1 | J27: 0 | K27: 0 | L27: 3 | M27: 350 | N27: 1 | O27: 192 | P27: 900 | Q27: -900 | R27: 0
A28: =IF(ISNUMBER(SEARCH("przychody",C28)),"Przychody","Koszty") -> Koszty | B28: B. Koszty działalności operacyjnej | C28: III. Usługi obce | D28: 58506001 | E28: 58506001 Usługi prawnicze | F28: Wynikowe | G28: 28945.74 | H28: 4580 | I28: 9520 | J28: 4100 | K28: 3500 | L28: 3500 | M28: 3980 | N28: 3500 | O28: 3500 | P28: 3500 | Q28: 4160 | R28: 3740
A29: =IF(ISNUMBER(SEARCH("przychody",C29)),"Przychody","Koszty") -> Koszty | B29: B. Koszty działalności operacyjnej | C29: =C28 -> III. Usługi obce | D29: 58506003 | E29: 58506003 Usługi audytorskie | F29: Wynikowe | G29: 0 | H29: 12267.4 | I29: 12302.38 | J29: 0 | K29: 0 | L29: 0 | M29: 0 | N29: 0 | O29: 5020 | P29: 0 | Q29: 0 | R29: 24800
A30: =IF(ISNUMBER(SEARCH("przychody",C30)),"Przychody","Koszty") -> Koszty | B30: B. Koszty działalności operacyjnej | C30: =C29 -> III. Usługi obce | D30: 58506004 | E30: 58506004 Usługi doradztwa podatkowego | F30: Wynikowe | G30: 0 | H30: 0 | I30: 0 | J30: 41544.95 | K30: 0 | L30: 0 | M30: 80044.84 | N30: 0 | O30: 24470.6 | P30: 0 | Q30: 22658.13 | R30: 15496.6
A31: =IF(ISNUMBER(SEARCH("przychody",C31)),"Przychody","Koszty") -> Koszty | B31: B. Koszty działalności operacyjnej | C31: =C30 -> III. Usługi obce | D31: 58506006 | E31: 58506006 Usługi rekrutacyjne | F31: Wynikowe | G31: 6232.2 | H31: 0 | I31: 0 | J31: 0 | K31: 0 | L31: 0 | M31: 0 | N31: 499 | O31: 0 | P31: 0 | Q31: 0 | R31: 0
A32: =IF(ISNUMBER(SEARCH("przychody",C32)),"Przychody","Koszty") -> Koszty | B32: B. Koszty działalności operacyjnej | C32: =C31 -> III. Usługi obce | D32: 58507000 | E32: 58507000 Pozostałe usługi | F32: Wynikowe | G32: 2011 | H32: 1985.88 | I32: 1529.17 | J32: 1038.8 | K32: 6022.8 | L32: 4702.4 | M32: 25.95 | N32: 866.4 | O32: 3533.8 | P32: 1863.85 | Q32: 312.46 | R32: 2305.9
A33: =IF(ISNUMBER(SEARCH("przychody",C33)),"Przychody","Koszty") -> Koszty | B33: B. Koszty działalności operacyjnej | C33: =C32 -> III. Usługi obce | D33: 58507001 | E33: 58507001 Archiwizacja | F33: Wynikowe | G33: 0 | H33: 0 | I33: 1755 | J33: 0 | K33: 0 | L33: 0 | M33: 0 | N33: 0 | O33: 0 | P33: 147 | Q33: 0 | R33: 0
A34: =IF(ISNUMBER(SEARCH("przychody",C34)),"Przychody","Koszty") -> Koszty | B34: B. Koszty działalności operacyjnej | C34: =C33 -> III. Usługi obce | D34: 58521000 | E34: 58521000 Telefony stacjonarne | F34: Wynikowe | G34: 5551.22 | H34: 4237.84 | I34: 4189.37 | J34: 4301.69 | K34: 4306.5 | L34: 4199.25 | M34: 4188.08 | N34: 4320.84 | O34: 4167.29 | P34: 4213.27 | Q34: 4302.22 | R34: 4548.96
A35: =IF(ISNUMBER(SEARCH("przychody",C35)),"Przychody","Koszty") -> Koszty | B35: B. Koszty działalności operacyjnej | C35: =C34 -> III. Usługi obce | D35: 58522000 | E35: 58522000 Telefony komórkowe | F35: Wynikowe | G35: 1882.58 | H35: 3244.02 | I35: 1787.78 | J35: 1568.18 | K35: 1232.58 | L35: 1224.02 | M35: 360.22 | N35: 2063.55 | O35: 1459.83 | P35: 1478.4 | Q35: 1142.82 | R35: 1147.79
A36: =IF(ISNUMBER(SEARCH("przychody",C36)),"Przychody","Koszty") -> Koszty | B36: B. Koszty działalności operacyjnej | C36: =C35 -> III. Usługi obce | D36: 58525000 | E36: 58525000 Internet | F36: Wynikowe | G36: 1950 | H36: 0 | I36: 4519.99 | J36: 2329.99 | K36: 2329.99 | L36: 2190 | M36: 2190 | N36: 2190 | O36: 2190 | P36: 2190 | Q36: 2190 | R36: 2430
A37: =IF(ISNUMBER(SEARCH("przychody",C37)),"Przychody","Koszty") -> Koszty | B37: B. Koszty działalności operacyjnej | C37: =C36 -> III. Usługi obce | D37: 58527000 | E37: 58527000 Usługi pocztowe i kurierskie | F37: Wynikowe | G37: 1483.23 | H37: 2603.43 | I37: -1191.97 | J37: 1153.83 | K37: 1127.33 | L37: 1485.05 | M37: 2146.4 | N37: 1513.85 | O37: 1259.56 | P37: 1010.22 | Q37: 1281.68 | R37: 5077.31
A38: =IF(ISNUMBER(SEARCH("przychody",C38)),"Przychody","Koszty") -> Koszty | B38: B. Koszty działalności operacyjnej | C38: =C37 -> III. Usługi obce | D38: 58530200 | E38: 58530200 Koszty oprogramowania | F38: Wynikowe | G38: 11019.62 | H38: 8006.1 | I38: 7596.1 | J38: 13813.1 | K38: 7546.1 | L38: 7776.1 | M38: 7643.1 | N38: 6511.1 | O38: 6971.1 | P38: 10946.1 | Q38: 8639.1 | R38: 3006
A39: =IF(ISNUMBER(SEARCH("przychody",C39)),"Przychody","Koszty") -> Koszty | B39: B. Koszty działalności operacyjnej | C39: =C38 -> III. Usługi obce | D39: 58530500 | E39: 58530500 Usługi konsultingowe IT | F39: Wynikowe | G39: 3390 | H39: 4580 | I39: 4050 | J39: 5530 | K39: 4170 | L39: 3690 | M39: 4340 | N39: 2140 | O39: 4060 | P39: 5730 | Q39: 10320.2 | R39: 5600
A40: =IF(ISNUMBER(SEARCH("przychody",C40)),"Przychody","Koszty") -> Koszty | B40: B. Koszty działalności operacyjnej | C40: =C39 -> III. Usługi obce | D40: 58530700 | E40: 58530700 Pozostałe koszty IT | F40: Wynikowe | G40: 207.45 | H40: 0 | I40: 0 | J40: 1179.2 | K40: 14.7 | L40: 3210.27 | M40: 1121.43 | N40: 0 | O40: 0 | P40: 868.34 | Q40: 926.86 | R40: 0
... A49: =IF(ISNUMBER(SEARCH("przychody",C49)),"Przychody","Koszty") -> Koszty | B49: B. Koszty działalności operacyjnej | C49: =C48 -> III. Usługi obce | D49: 58590000 | E49: 58590000 Rafaktura kosztów | F49: Wynikowe | G49: 0 | H49: 0 | I49: 0 | J49: 0 | K49: 0 | L49: 0 | M49: 0 | N49: 975 | O49: 567.16 | P49: 2944.31 | Q49: 489.04 | R49: 1846.81
A50: =IF(ISNUMBER(SEARCH("przychody",C50)),"Przychody","Koszty") -> Koszty | B50: B. Koszty działalności operacyjnej | C50: VII. Pozostałe koszty rodzajowe | D50: 59080000 | E50: 59080000 Pozostałe koszty pracownicze | F50: Wynikowe | G50: 0 | H50: 9505.77 | I50: 9304.18 | J50: 6741.03 | K50: 3010.6 | L50: 3789.66 | M50: 10725.92 | N50: 4167.48 | O50: 5261.78 | P50: 5056.64 | Q50: 5493.08 | R50: 10405.06
A51: =IF(ISNUMBER(SEARCH("przychody",C51)),"Przychody","Koszty") -> Koszty | B51: B. Koszty działalności operacyjnej | C51: III. Usługi obce | D51: 59504050 | E51: 59504050 Różne koszty operacyjne | F51: Wynikowe | G51: 0 | H51: 0 | I51: 0 | J51: 0 | K51: 0 | L51: 0 | M51: 0 | N51: 0 | O51: 0 | P51: 0 | Q51: 0 | R51: 0
A52: =IF(ISNUMBER(SEARCH("przychody",C52)),"Przychody","Koszty") -> Koszty | B52: B. Koszty działalności operacyjnej | C52: III. Usługi obce | D52: 65518000 | E52: 65518000 Opłaty i prowizje bankowe | F52: Wynikowe | G52: 1839.17 | H52: 1610.73 | I52: 1491.76 | J52: 1092.5 | K52: 1059.64 | L52: 2080.95 | M52: 2692.84 | N52: 940.01 | O52: 1459.24 | P52: 1356.76 | Q52: 2192.38 | R52: 895.49
A53: =IF(ISNUMBER(SEARCH("przychody",C53)),"Przychody","Koszty") -> Koszty | B53: B. Koszty działalności operacyjnej | C53: IV. Podatki i opłaty | D53: 59080040 | E53: 59080040 PFRON | F53: Wynikowe | G53: 11977 | H53: 11654 | I53: 0 | J53: 24681 | K53: 12213 | L53: 0 | M53: 24954 | N53: 12672 | O53: 9702 | P53: 9640 | Q53: 9660 | R53: 10065
A54: =IF(ISNUMBER(SEARCH("przychody",C54)),"Przychody","Koszty") -> Koszty | B54: B. Koszty działalności operacyjnej | C54: IV. Podatki i opłaty | D54: 59500040 | E54: 59500040 Podatek od nieruchomości | F54: Wynikowe | G54: 2191.55 | H54: 2191.55 | I54: 2191.55 | J54: 2267.68 | K54: 2224.43 | L54: 2224.43 | M54: 2224.43 | N54: 2224.43 | O54: 2224.43 | P54: 2224.43 | Q54: 2224.43 | R54: 2227.43
A55: =IF(ISNUMBER(SEARCH("przychody",C55)),"Przychody","Koszty") -> Koszty | B55: B. Koszty działalności operacyjnej | C55: IV. Podatki i opłaty | D55: 59500050 | E55: 59500050 VAT nie do odliczenia KUP | F55: Wynikowe | G55: 5209.71 | H55: 5352.19 | I55: 4832.47 | J55: 4774.46 | K55: 4283.24 | L55: 4688.01 | M55: 4874.48 | N55: 3914.94 | O55: 4540.83 | P55: 5433.43 | Q55: 5472.95 | R55: 4650.4
A56: =IF(ISNUMBER(SEARCH("przychody",C56)),"Przychody","Koszty") -> Koszty | B56: B. Koszty działalności operacyjnej | C56: IV. Podatki i opłaty | D56: 59500051 | E56: 59500051 VAT nie do odliczenia NKUP | F56: Wynikowe | G56: 1510.99 | H56: 756.59 | I56: 936.37 | J56: 1281.04 | K56: 925.61 | L56: 1060.22 | M56: 1118.93 | N56: 454.86 | O56: 1094.08 | P56: 1297.81 | Q56: 1471.41 | R56: 885.33
A57: =IF(ISNUMBER(SEARCH("przychody",C57)),"Przychody","Koszty") -> Koszty | B57: B. Koszty działalności operacyjnej | C57: V. Wynagrodzenia | D57: 59000000 | E57: 59000000 Wynagrodzenia osobowe | F57: Wynikowe | G57: 1107101.9 | H57: 1089088.7 | I57: 1091297.8 | J57: 1092961.2 | K57: 1071577.3 | L57: 1060328.3 | M57: 1058152.5 | N57: 1086590.2 | O57: 1078871.1 | P57: 1085071.1 | Q57: 1091726.7 | R57: 1102354.8
A58: =IF(ISNUMBER(SEARCH("przychody",C58)),"Przychody","Koszty") -> Koszty | B58: B. Koszty działalności operacyjnej | C58: V. Wynagrodzenia | D58: 59002000 | E58: 59002000 Premia roczna | F58: Wynikowe | G58: 0 | H58: 0 | I58: 0 | J58: -44723 | K58: 0 | L58: 214871.88 | M58: 0 | N58: 0 | O58: 0 | P58: 0 | Q58: 0 | R58: 1212000
A59: =IF(ISNUMBER(SEARCH("przychody",C59)),"Przychody","Koszty") -> Koszty | B59: B. Koszty działalności operacyjnej | C59: V. Wynagrodzenia | D59: 59002200 | E59: 59002200 Nadgodziny | F59: Wynikowe | G59: 0 | H59: 0 | I59: 0 | J59: 1471.54 | K59: 0 | L59: 0 | M59: 579.46 | N59: 118.33 | O59: 201.01 | P59: 589.17 | Q59: 0 | R59: 1120.69
A60: =IF(ISNUMBER(SEARCH("przychody",C60)),"Przychody","Koszty") -> Koszty | B60: B. Koszty działalności operacyjnej | C60: V. Wynagrodzenia | D60: 59018300 | E60: 59018300 Rezerwa na odprawę emerytalną | F60: Wynikowe | G60: 0 | H60: -2375 | I60: 30575 | J60: 0 | K60: 45000 | L60: 0 | M60: 0 | N60: 0 | O60: 0 | P60: 0 | Q60: 7639.17 | R60: -9219.07
A61: =IF(ISNUMBER(SEARCH("przychody",C61)),"Przychody","Koszty") -> Koszty | B61: B. Koszty działalności operacyjnej | C61: V. Wynagrodzenia | D61: 59040000 | E61: 59040000 Pozostałe świadczenia pracownicze | F61: Wynikowe | G61: 17114.62 | H61: -5987.01 | I61: -15628.31 | J61: 0 | K61: 0 | L61: 2232.42 | M61: 2678.72 | N61: 2776.87 | O61: 2985.4 | P61: 3493.57 | Q61: 863.52 | R61: 1028.34
... A104: =IF(ISNUMBER(SEARCH("przychody",C104)),"Przychody","Koszty") -> Koszty | B104: H. Koszty finansowe | C104: IV. Inne | D104: 65528110 | E104: 65528110 Zrealiz ujemne różnice kursowe od należ | F104: Wynikowe | G104: 15.15 | H104: 0 | I104: 0 | J104: 0 | K104: 0 | L104: 0 | M104: 0 | N104: 0 | O104: 0 | P104: 0 | Q104: 0 | R104: 0
A105: Podatek | B105: J. Podatek dochodowy | D105: 70000000 | E105: 70000000 Podatek dochodowy - bieżacy okres | F105: Wynikowe | G105: 0 | H105: 44113.25 | I105: 43210.75 | J105: 320688.27 | K105: 43662 | L105: 43662 | M105: 43662 | N105: 43662 | O105: 287538.99 | P105: 43662 | Q105: 43662 | R105: -798771.91
A106: =IF(ISNUMBER(SEARCH("przychody",C106)),"Przychody","Koszty") -> Koszty | B106: H. Koszty finansowe | C106: IV. Inne | D106: 60500000 | E106: 60500000 Niezrealiz dodatnie róż kurs od zabezp należ (TFx) | F106: Wynikowe | G106: 0 | H106: 0 | I106: 0 | J106: 0 | K106: 0 | L106: 0 | M106: 0 | N106: 0 | O106: 0 | P106: 0 | Q106: 0 | R106: -416.67
A107: =IF(ISNUMBER(SEARCH("przychody",C107)),"Przychody","Koszty") -> Koszty | B107: H. Koszty finansowe | C107: IV. Inne | D107: 60501000 | E107: 60501000 Niezrealiz ujemne róż kurs od zabezp należ (TFx) | F107: Wynikowe | G107: 0 | H107: 0 | I107: 0 | J107: 0 | K107: 0 | L107: 0 | M107: 0 | N107: 0 | O107: 0 | P107: 0 | Q107: 0 | R107: 130.12

Sheet 24 RziS Mapowanie
G1: =SUM(G3:G102) -> 3335057.1 | H1: =SUM(H3:H102) -> 3441549.9 | I1: =SUM(I3:I102) -> 3448161.1 | J1: =SUM(J3:J102) -> 926695.11 | K1: =SUM(K3:K102) -> 4829875.9 | L1: =SUM(L3:L102) -> 3832613.7 | M1: =SUM(M3:M102) -> 4066828.6 | N1: =SUM(N3:N102) -> 2154561 | ... P1: =SUM(P3:P102) -> 3790996.4 | Q1: =SUM(Q3:Q107) -> 3374417.5 | R1: =SUM(R3:R107) -> 7053888.5 | T1: -1
A2: Rodzaj1 | B2: Rodzaj2 | C2: Rodzaj3 | D2: Numer konta | E2: Nazwa konta | F2: Rodzaj konta (bilansowe/wynikowe) | G2: 2024-01 | H2: 2024-02 | I2: 2024-03 | J2: 2024-04 | K2: 2024-05 | L2: 2024-06 | M2: 2024-07 | N2: 2024-08 | O2: 2024-09 | P2: 2024-10 | Q2: 2024-11 | R2: 2024-12 | S2: 2024
A3: =IF(ISNUMBER(SEARCH("przychody",B3)),"Przychody","Koszty") -> Przychody | B3: A. Przychody netto ze sprzedaży i zrównane z nimi, w tym: | C3: =_xlfn.XLOOKUP(E3,'25 RZiS Zmapowane P+'!$E$2:$E$111,'25 RZiS Zmapowane P+'!$C$2:$C$111,0) -> I. Przychody netto ze sprzedaży produktów | D3: 44000000 | E3: 44000000 Przychód operacyjny - opłata za konosament | F3: Wynikowe | G3: 0 | H3: 0 | I3: 0 | J3: 0 | K3: 0 | L3: 0 | M3: 0 | N3: 0 | O3: 0 | P3: 0 | Q3: -112.36 | R3: 0 | S3: =SUM(_24[[#This Row],[2024-01]:[2024-12]]) -> -112.36
A4: =IF(ISNUMBER(SEARCH("przychody",B4)),"Przychody","Koszty") -> Przychody | B4: A. Przychody netto ze sprzedaży i zrównane z nimi, w tym: | C4: =_xlfn.XLOOKUP(E4,'25 RZiS Zmapowane P+'!$E$2:$E$111,'25 RZiS Zmapowane P+'!$C$2:$C$111,0) -> I. Przychody netto ze sprzedaży produktów | D4: 44000005 | E4: 44000005 Przychód operacyjny - opłata dokumentacyjna EXP | F4: Wynikowe | G4: 0 | H4: 0 | I4: 0 | J4: 0 | K4: 0 | L4: 0 | M4: 0 | N4: 0 | O4: 0 | P4: 0 | Q4: -153.29 | R4: 0 | S4: =SUM(_24[[#This Row],[2024-01]:[2024-12]]) -> -153.29
A5: =IF(ISNUMBER(SEARCH("przychody",B5)),"Przychody","Koszty") -> Przychody | B5: A. Przychody netto ze sprzedaży i zrównane z nimi, w tym: | C5: =_xlfn.XLOOKUP(E5,'25 RZiS Zmapowane P+'!$E$2:$E$111,'25 RZiS Zmapowane P+'!$C$2:$C$111,0) -> I. Przychody netto ze sprzedaży produktów | D5: 45510000 | E5: 45510000 Prowizja Cost+ | F5: Wynikowe | G5: 1850899 | H5: 1937526 | I5: 1838554 | J5: 453584 | K5: 1520140 | L5: 1520140 | M5: 2331123 | N5: 1636000 | O5: 1636000 | P5: 1635000 | Q5: 1635000 | R5: 3364855 | S5: =SUM(_24[[#This Row],[2024-01]:[2024-12]]) -> 21358821
A6: =IF(ISNUMBER(SEARCH("przychody",B6)),"Przychody","Koszty") -> Przychody | B6: D. Pozostałe przychody operacyjne | C6: =_xlfn.XLOOKUP(E6,'25 RZiS Zmapowane P+'!$E$2:$E$111,'25 RZiS Zmapowane P+'!$C$2:$C$111,0) -> IV. Inne przychody operacyjne | D6: 46012000 | E6: 46012000 Przychód operacyjny - nadpłaty | F6: Wynikowe | G6: 0 | H6: -4 | I6: -0.49 | J6: 0 | K6: 0 | L6: 0 | M6: 0 | N6: 0 | O6: 0 | P6: -10.34 | Q6: 0 | R6: -20.51 | S6: =SUM(_24[[#This Row],[2024-01]:[2024-12]]) -> -35.34
A7: =IF(ISNUMBER(SEARCH("przychody",B7)),"Przychody","Koszty") -> Przychody | B7: D. Pozostałe przychody operacyjne | C7: =_xlfn.XLOOKUP(E7,'25 RZiS Zmapowane P+'!$E$2:$E$111,'25 RZiS Zmapowane P+'!$C$2:$C$111,0) -> IV. Inne przychody operacyjne | D7: 46050000 | E7: 46050000 Przychód operacyjny - pozostałe | F7: Wynikowe | G7: 6616.25 | H7: 3474.05 | I7: 274 | J7: 6412.1 | K7: 1093 | L7: 207524.53 | M7: 364 | N7: 9190.58 | O7: 3890.97 | P7: 3517.94 | Q7: 3606.16 | R7: 3656.6 | S7: =SUM(_24[[#This Row],[2024-01]:[2024-12]]) -> 249620.18
A8: =IF(ISNUMBER(SEARCH("przychody",B8)),"Przychody","Koszty") -> Koszty | B8: B. Koszty działalności operacyjnej | C8: =_xlfn.XLOOKUP(E8,'25 RZiS Zmapowane P+'!$E$2:$E$111,'25 RZiS Zmapowane P+'!$C$2:$C$111,0) -> III. Usługi obce | D8: 53080000 | E8: 53080000 Koszt operacyjny - pozostałe koszty na termin mors | F8: Wynikowe | G8: 0 | H8: 0 | I8: 0 | J8: 0 | K8: 55401 | L8: 0 | M8: 0 | N8: 0 | O8: 0 | P8: 0 | Q8: 0 | R8: 0 | S8: =SUM(_24[[#This Row],[2024-01]:[2024-12]]) -> 55401
A9: =IF(ISNUMBER(SEARCH("przychody",B9)),"Przychody","Koszty") -> Koszty | B9: B. Koszty działalności operacyjnej | C9: =_xlfn.XLOOKUP(E9,'25 RZiS Zmapowane P+'!$E$2:$E$111,'25 RZiS Zmapowane P+'!$C$2:$C$111,0) -> III. Usługi obce | D9: 58500000 | E9: 58500000 Wynajęcie biura | F9: Wynikowe | G9: 21406.78 | H9: 5626.48 | I9: 21751.66 | J9: 21750.82 | K9: 3801.69 | L9: 4420.13 | M9: 28762.07 | N9: 7652.26 | O9: 7683.67 | P9: 7680.03 | Q9: 26297.01 | R9: 26647.1 | S9: =SUM(_24[[#This Row],[2024-01]:[2024-12]]) -> 183479.7
A10: =IF(ISNUMBER(SEARCH("przychody",B10)),"Przychody","Koszty") -> Koszty | B10: B. Koszty działalności operacyjnej | C10: =_xlfn.XLOOKUP(E10,'25 RZiS Zmapowane P+'!$E$2:$E$111,'25 RZiS Zmapowane P+'!$C$2:$C$111,0) -> III. Usługi obce | D10: 58500010 | E10: 58500010 Wynajecie parkingu | F10: Wynikowe | G10: 8307.36 | H10: 4965.21 | I10: 8420.35 | J10: 8757.84 | K10: 3524.39 | L10: 7557.76 | M10: 15464.41 | N10: 8034.57 | O10: 8125.68 | P10: 9291.91 | Q10: 8402.33 | R10: 10303.66 | S10: =SUM(_24[[#This Row],[2024-01]:[2024-12]]) -> 101155.47
A11: =IF(ISNUMBER(SEARCH("przychody",B11)),"Przychody","Koszty") -> Koszty | B11: B. Koszty działalności operacyjnej | C11: =_xlfn.XLOOKUP(E11,'25 RZiS Zmapowane P+'!$E$2:$E$111,'25 RZiS Zmapowane P+'!$C$2:$C$111,0) -> II. Zużycie materiałów i energii | D11: 58502000 | E11: 58502000 Energia cieplna | F11: Wynikowe | G11: 4208.23 | H11: 4306.92 | I11: 4073.16 | J11: 2428.72 | K11: 3835.33 | L11: 3948.43 | M11: 5932.9 | N11: 4848.09 | O11: 3860.73 | P11: 5514.71 | Q11: 3978.47 | R11: 4531.39 | S11: =SUM(_24[[#This Row],[2024-01]:[2024-12]]) -> 51467.08
A12: =IF(ISNUMBER(SEARCH("przychody",B12)),"Przychody","Koszty") -> Koszty | B12: B. Koszty działalności operacyjnej | C12: =_xlfn.XLOOKUP(E12,'25 RZiS Zmapowane P+'!$E$2:$E$111,'25 RZiS Zmapowane P+'!$C$2:$C$111,0) -> II. Zużycie materiałów i energii | D12: 58502001 | E12: 58502001 Woda | F12: Wynikowe | G12: 1388.54 | H12: 1792.07 | I12: 915.64 | J12: 1569.03 | K12: 1028.14 | L12: 1995.74 | M12: 1561.36 | N12: 695.43 | O12: 1698.22 | P12: 2170.34 | Q12: 1855.96 | R12: 2455.9 | S12: =SUM(_24[[#This Row],[2024-01]:[2024-12]]) -> 19126.37
A13: =IF(ISNUMBER(SEARCH("przychody",B13)),"Przychody","Koszty") -> Koszty | B13: B. Koszty działalności operacyjnej | C13: =_xlfn.XLOOKUP(E13,'25 RZiS Zmapowane P+'!$E$2:$E$111,'25 RZiS Zmapowane P+'!$C$2:$C$111,0) -> II. Zużycie materiałów i energii | D13: 58502002 | E13: 58502002 Energia elektryczna | F13: Wynikowe | G13: 1390.06 | H13: 7690.81 | I13: 4594.53 | J13: 3320.83 | K13: 3873.31 | L13: 3981.54 | M13: 5362.43 | N13: 1794.21 | O13: 7569.72 | P13: 5345.24 | Q13: 4732.72 | R13: 8656.65 | S13: =SUM(_24[[#This Row],[2024-01]:[2024-12]]) -> 58312.05
A14: =IF(ISNUMBER(SEARCH("przychody",B14)),"Przychody","Koszty") -> Koszty | B14: B. Koszty działalności operacyjnej | C14: =_xlfn.XLOOKUP(E14,'25 RZiS Zmapowane P+'!$E$2:$E$111,'25 RZiS Zmapowane P+'!$C$2:$C$111,0) -> III. Usługi obce | D14: 58502003 | E14: 58502003 Ubezpieczenie biura | F14: Wynikowe | G14: 1794.99 | H14: 1796.99 | I14: 1796.99 | J14: 2185.03 | K14: 1876.68 | L14: 1876.68 | M14: 1876.68 | N14: 1876.68 | O14: 1876.68 | P14: 1876.68 | Q14: 1876.68 | R14: 1876.68 | S14: =SUM(_24[[#This Row],[2024-01]:[2024-12]]) -> 22587.44
... A101: =IF(ISNUMBER(SEARCH("przychody",B101)),"Przychody","Koszty") -> Koszty | B101: H. Koszty finansowe | C101: =_xlfn.XLOOKUP(E101,'25 RZiS Zmapowane P+'!$E$2:$E$111,'25 RZiS Zmapowane P+'!$C$2:$C$111,0) -> IV. Inne | D101: 65528110 | E101: 65528110 Zrealiz ujemne różnice kursowe od należ | F101: Wynikowe | G101: 0 | H101: 0 | I101: 0 | J101: 0 | K101: 0 | L101: 0 | M101: 0 | N101: 0 | O101: 0 | P101: 0 | Q101: 0 | R101: 0 | S101: =SUM(_24[[#This Row],[2024-01]:[2024-12]]) -> 0
A102: =IF(ISNUMBER(SEARCH("przychody",B102)),"Przychody","Koszty") -> Koszty | B102: J. Podatek dochodowy | D102: 70000000 | E102: 70000000 Podatek dochodowy - bieżacy okres | F102: Wynikowe | G102: 0 | H102: 83990 | I102: 83990 | J102: 83990 | K102: 413010.75 | L102: 83990 | M102: 83990 | N102: 83990 | O102: 83990 | P102: 374175.12 | Q102: 83990 | R102: -1081873.3 | S102: =SUM(_24[[#This Row],[2024-01]:[2024-12]]) -> 377232.61
A103: =IF(ISNUMBER(SEARCH("przychody",B103)),"Przychody","Koszty") -> Przychody | B103: A. Przychody netto ze sprzedaży i zrównane z nimi, w tym: | C103: =_xlfn.XLOOKUP(E103,'25 RZiS Zmapowane P+'!$E$2:$E$111,'25 RZiS Zmapowane P+'!$C$2:$C$111,0) -> I. Przychody netto ze sprzedaży produktów | D103: 44006000 | E103: 44006000 Przychód operacyjny - korekta manifestu | F103: Wynikowe | Q103: -340.23 | R103: 0 | S103: =SUM(_24[[#This Row],[2024-01]:[2024-12]]) -> -340.23
B104: C. Zysk/ (strata) ze sprzedaży | G104: =SUMIF($B$3:$B$107,"A. Przychody netto ze sprzedaży i zrównane z nimi, w tym:",G3:G107) - SUMIF($B$3:$B$107,"B. Koszty działalności operacyjnej",G3:G107) -> 376375.95 | H104: =SUMIF($B$3:$B$107,"A. Przychody netto ze sprzedaży i zrównane z nimi, w tym:",H3:H107) - SUMIF($B$3:$B$107,"B. Koszty działalności operacyjnej",H3:H107) -> 520778.51 | I104: =SUMIF($B$3:$B$107,"A. Przychody netto ze sprzedaży i zrównane z nimi, w tym:",I3:I107) - SUMIF($B$3:$B$107,"B. Koszty działalności operacyjnej",I3:I107) -> 314197.75 | J104: =SUMIF($B$3:$B$107,"A. Przychody netto ze sprzedaży i zrównane z nimi, w tym:",J3:J107) - SUMIF($B$3:$B$107,"B. Koszty działalności operacyjnej",J3:J107) -> 71175.8 | K104: =SUMIF($B$3:$B$107,"A. Przychody netto ze sprzedaży i zrównane z nimi, w tym:",K3:K107) - SUMIF($B$3:$B$107,"B. Koszty działalności operacyjnej",K3:K107) -> -1376572.4 | L104: =SUMIF($B$3:$B$107,"A. Przychody netto ze sprzedaży i zrównane z nimi, w tym:",L3:L107) - SUMIF($B$3:$B$107,"B. Koszty działalności operacyjnej",L3:L107) -> -499558.88 | M104: =SUMIF($B$3:$B$107,"A. Przychody netto ze sprzedaży i zrównane z nimi, w tym:",M3:M107) - SUMIF($B$3:$B$107,"B. Koszty działalności operacyjnej",M3:M107) -> 740299.73 | N104: =SUMIF($B$3:$B$107,"A. Przychody netto ze sprzedaży i zrównane z nimi, w tym:",N3:N107) - SUMIF($B$3:$B$107,"B. Koszty działalności operacyjnej",N3:N107) -> 1210295.5 | ... R104: =SUMIF($B$3:$B$107,"A. Przychody netto ze sprzedaży i zrównane z nimi, w tym:",R3:R107) - SUMIF($B$3:$B$107,"B. Koszty działalności operacyjnej",R3:R107) -> 88619.84 | S104: =SUM(_24[[#This Row],[2024-01]:[2024-12]]) -> 250976.11
B105: F. Zysk/ (strata) z działalności operacyjnej | G105: =G104 + SUMIF($B$3:$B$107,"D. Pozostałe przychody operacyjne",G3:G107) - SUMIF($B$3:$B$107,"E. Pozostałe koszty operacyjne",G3:G107) -> 379992.2 | H105: =H104 + SUMIF($B$3:$B$107,"D. Pozostałe przychody operacyjne",H3:H107) - SUMIF($B$3:$B$107,"E. Pozostałe koszty operacyjne",H3:H107) -> 524248.56 | I105: =I104 + SUMIF($B$3:$B$107,"D. Pozostałe przychody operacyjne",I3:I107) - SUMIF($B$3:$B$107,"E. Pozostałe koszty operacyjne",I3:I107) -> 314475.32 | J105: =J104 + SUMIF($B$3:$B$107,"D. Pozostałe przychody operacyjne",J3:J107) - SUMIF($B$3:$B$107,"E. Pozostałe koszty operacyjne",J3:J107) -> 77587.9 | K105: =K104 + SUMIF($B$3:$B$107,"D. Pozostałe przychody operacyjne",K3:K107) - SUMIF($B$3:$B$107,"E. Pozostałe koszty operacyjne",K3:K107) -> -1380468.1 | L105: =L104 + SUMIF($B$3:$B$107,"D. Pozostałe przychody operacyjne",L3:L107) - SUMIF($B$3:$B$107,"E. Pozostałe koszty operacyjne",L3:L107) -> -290792.9 | M105: =M104 + SUMIF($B$3:$B$107,"D. Pozostałe przychody operacyjne",M3:M107) - SUMIF($B$3:$B$107,"E. Pozostałe koszty operacyjne",M3:M107) -> 787323.86 | N105: =N104 + SUMIF($B$3:$B$107,"D. Pozostałe przychody operacyjne",N3:N107) - SUMIF($B$3:$B$107,"E. Pozostałe koszty operacyjne",N3:N107) -> 1219868.3 | ... R105: =R104 + SUMIF($B$3:$B$107,"D. Pozostałe przychody operacyjne",R3:R107) - SUMIF($B$3:$B$107,"E. Pozostałe koszty operacyjne",R3:R107) -> 100759.51 | S105: =SUM(_24[[#This Row],[2024-01]:[2024-12]]) -> 714003.81
B106: I. Zysk/ (strata) brutto | G106: =G105 + SUMIF($B$3:$B$107,"G. Przychody finansowe",G3:G107) - SUMIF($B$3:$B$107,"H. Koszty finansowe",G3:G107) -> 379978.41 | H106: =H105 + SUMIF($B$3:$B$107,"G. Przychody finansowe",H3:H107) - SUMIF($B$3:$B$107,"H. Koszty finansowe",H3:H107) -> 524432.24 | I106: =I105 + SUMIF($B$3:$B$107,"G. Przychody finansowe",I3:I107) - SUMIF($B$3:$B$107,"H. Koszty finansowe",I3:I107) -> 313492.04 | J106: =J105 + SUMIF($B$3:$B$107,"G. Przychody finansowe",J3:J107) - SUMIF($B$3:$B$107,"H. Koszty finansowe",J3:J107) -> 77414.99 | K106: =K105 + SUMIF($B$3:$B$107,"G. Przychody finansowe",K3:K107) - SUMIF($B$3:$B$107,"H. Koszty finansowe",K3:K107) -> -1374106.3 | L106: =L105 + SUMIF($B$3:$B$107,"G. Przychody finansowe",L3:L107) - SUMIF($B$3:$B$107,"H. Koszty finansowe",L3:L107) -> -290811.78 | M106: =M105 + SUMIF($B$3:$B$107,"G. Przychody finansowe",M3:M107) - SUMIF($B$3:$B$107,"H. Koszty finansowe",M3:M107) -> 784525.63 | N106: =N105 + SUMIF($B$3:$B$107,"G. Przychody finansowe",N3:N107) - SUMIF($B$3:$B$107,"H. Koszty finansowe",N3:N107) -> 1220574.7 | ... R106: =R105 + SUMIF($B$3:$B$107,"G. Przychody finansowe",R3:R107) - SUMIF($B$3:$B$107,"H. Koszty finansowe",R3:R107) -> 104937.31 | S106: =SUM(_24[[#This Row],[2024-01]:[2024-12]]) -> 719521.55
B107: L. Zysk/ (strata) netto | G107: =G113 -> 379978.41 | H107: =H113 -> 440442.24 | I107: =I113 -> 229502.04 | J107: =J113 -> -6575.01 | K107: =K113 -> -1787117.1 | L107: =L113 -> -374801.78 | M107: =M113 -> 700535.63 | N107: =N113 -> 1136584.7 | ... R107: =R113 -> 1186810.6 | S107: =SUM(_24[[#This Row],[2024-01]:[2024-12]]) -> 342288.94
F111: P | G111: =SUMIF($A$3:$A$103,"Przychody",G3:G103) -> 1857517.7 | H111: =SUMIF($A$3:$A$103,"Przychody",H3:H103) -> 1940996.1 | I111: =SUMIF($A$3:$A$103,"Przychody",I3:I103) -> 1838831.6 | J111: =SUMIF($A$3:$A$103,"Przychody",J3:J103) -> 460060.05 | K111: =SUMIF($A$3:$A$103,"Przychody",K3:K103) -> 1521379.4 | L111: =SUMIF($A$3:$A$103,"Przychody",L3:L103) -> 1728906 | M111: =SUMIF($A$3:$A$103,"Przychody",M3:M103) -> 2383682.1 | N111: =SUMIF($A$3:$A$103,"Przychody",N3:N103) -> 1645572.9 | ... R111: =SUMIF($A$3:$A$103,"Przychody",R3:R103) -> 3379785.9
F112: K | G112: =SUMIF($A$3:$A$103,"Koszty",G3:G103) -> 1477539.3 | H112: =SUMIF($A$3:$A$103,"Koszty",H3:H103) -> 1500553.8 | I112: =SUMIF($A$3:$A$103,"Koszty",I3:I103) -> 1609329.5 | J112: =SUMIF($A$3:$A$103,"Koszty",J3:J103) -> 466635.06 | K112: =SUMIF($A$3:$A$103,"Koszty",K3:K103) -> 3308496.5 | L112: =SUMIF($A$3:$A$103,"Koszty",L3:L103) -> 2103707.8 | M112: =SUMIF($A$3:$A$103,"Koszty",M3:M103) -> 1683146.5 | N112: =SUMIF($A$3:$A$103,"Koszty",N3:N103) -> 508988.15 | ... R112: =SUMIF($A$3:$A$103,"Koszty",R3:R103) -> 2192975.4
F113: Z | G113: =G111-G112 -> 379978.41 | H113: =H111-H112 -> 440442.24 | I113: =I111-I112 -> 229502.04 | J113: =J111-J112 -> -6575.01 | K113: =K111-K112 -> -1787117.1 | L113: =L111-L112 -> -374801.78 | M113: =M111-M112 -> 700535.63 | N113: =N111-N112 -> 1136584.7 | ... R113: =R111-R112 -> 1186810.6 | S113: =SUM(G113:R113) -> 342288.94
G115: 2024-01 | H115: 2024-02 | I115: 2024-03 | J115: 2024-04 | K115: 2024-05 | L115: 2024-06 | M115: 2024-07 | N115: 2024-08 | O115: 2024-09 | P115: 2024-10 | Q115: 2024-11 | R115: 2024-12

Sheet Bilans ->>>
A1: B

Sheet Check Bilansu 25
A2: Etykiety wierszy | B2: Suma z BZ | E2: Etykiety wierszy | F2: Suma z BZ
A3: A. Aktywa trwałe | B3: 7537505.9 | E3: A. Aktywa trwałe | F3: 7537505.9
A4: I. Wartości niematerialne i prawne | B4: 7412 | E4: I. Wartości niematerialne i prawne | F4: 7412
A5: II. Rzeczowe aktywa trwałe | B5: 6727838.4 | E5: II. Rzeczowe aktywa trwałe | F5: 6727838.4
A6: V. Długoterminowe rozliczenia międzyokresowe | B6: 802255.52 | E6: V. Długoterminowe rozliczenia międzyokresowe | F6: 802255.52
A7: B. Aktywa obrotowe | B7: 95670395 | E7: B. Aktywa obrotowe | F7: 95670395
A8: II. Należności krótkoterminowe | B8: 95542030 | E8: II. Należności krótkoterminowe | F8: 95542030
A9: III. Inwestycje krótkoterminowe | B9: 102893.47 | E9: III. Inwestycje krótkoterminowe | F9: 102893.47
A10: IV. Krótkoterminowe rozliczenia międzyokresowe | B10: 25470.62 | E10: IV. Krótkoterminowe rozliczenia międzyokresowe | F10: 25470.62
A11: A. Kapitał (fundusz) własny | B11: 2604310.9 | E11: A. Kapitał (fundusz) własny | F11: -2604310.9
A12: I. Kapitał (fundusz) podstawowy | B12: 50000 | E12: I. Kapitał (fundusz) podstawowy | F12: -50000
B13: 50000 | E13: V. Zysk/ (strata) z lat ubiegłych | F13: -2229674.6
A14: (puste) | B14: 50000 | E14: VI. Zysk/ (strata) netto | F14: -324636.34
A15: (puste) | B15: 50000 | E15: B. Zobowiązania i rezerwy na zobowiązania | F15: -1.0060359e+08
A16: V. Zysk/ (strata) z lat ubiegłych | B16: 2229674.6 | E16: I. Rezerwy na zobowiązania | F16: -3005996.9
A17: VI. Zysk/ (strata) netto | B17: 324636.34 | E17: III. Zobowiązania krótkoterminowe | F17: -97597593
A18: B. Zobowiązania i rezerwy na zobowiązania | B18: 1.0060359e+08 | E18: Suma końcowa | F18: 0
A19: I. Rezerwy na zobowiązania | B19: 3005996.9
A20: 1. Rezerwa z tytułu odroczonego podatku dochodowego | B20: 79.17
A21: b) krótkoterminowe | B21: 79.17
A22: (puste) | B22: 79.17
A23: 2. Rezerwa na świadczenia emerytalne i podobne | B23: 498323
A24: a) długoterminowe | B24: 498323
A25: (puste) | B25: 498323
A26: 3. Pozostałe rezerwy | B26: 2507594.7
A27: a) długoterminowe | B27: 1055133.9
A28: (puste) | B28: 1055133.9
A29: b) krótkoterminowe | B29: 1452460.8
A30: (puste) | B30: 1452460.8 | D30: =B7-(B31+B30) -> -3379658.9 | E30: =B7/(B30+B31) -> 0.96587928
A31: III. Zobowiązania krótkoterminowe | B31: 97597593 | E31: =B7/B31 -> 0.98025363
A32: 3. Należności od pozostałych jednostek | B32: 0 | E32: =B7/(B31+B7) -> 0.49501418
A33: (puste) | B33: 0
A34: (puste) | B34: 0
A35: 3. Zobowiązania wobec pozostałych jednostek | B35: 0
A36: h) z tytułu wynagrodzeń | B36: 0
A37: (puste) | B37: 0
A38: 3. Zobowiązania wobec pozostałych jednostek | B38: 97597593
A39: d) z tytułu dostaw i usług, o okresie wymagalności: | B39: 106600.2
A40: - do 12 miesięcy | B40: 106600.2
A41: g) z tytułu podatków, ceł, ubezpieczeń społecznych i zdrowotnych oraz innych tytułów publicznoprawnych | B41: 1131853.4
A42: (puste) | B42: 1131853.4
A43: i) inne | B43: 96359139
A44: (puste) | B44: 96359139
A45: Suma końcowa | B45: 2.064158e+08

Sheet 25 Mapowanie Bilans P+
A1: Rodzaj1 | B1: Rodzaj2 | C1: Rodzaj3 | D1: Rodzaj4 | E1: Rodzaj5 | F1: Rodzaj6 | G1: Numer konta | H1: Nazwa konta | I1: Rodzaj konta (bilansowe/wynikowe) | J1: 2025-01 | K1: 2025-02 | L1: 2025-03 | M1: 2025-04 | N1: 2025-05 | O1: 2025-06 | P1: 2025-07 | Q1: 2025-08 | R1: 2025-09 | S1: 2025-10 | T1: 2025-11 | U1: 2025-12 | V1: BZ | W1: BZ 2025 | X1: Check:
A2: =IF(ISNUMBER(SEARCH("aktywa",B2)),"Aktywa","Pasywa") -> Aktywa | B2: A. Aktywa trwałe | C2: I. Wartości niematerialne i prawne | D2: 3. Inne wartości niematerialne i prawne | G2: 11000100 | H2: 11000100 Oprogramowanie i licencje IT - Wartość nabycia | I2: Bilansowe | J2: 77463.01 | K2: 0 | L2: 0 | M2: 0 | N2: 0 | O2: 0 | P2: 0 | Q2: 0 | R2: 0 | S2: 0 | T2: 0 | U2: 0 | V2: 77463.01 | W2: 77463.01 | X2: 0 | Z2: Aktywa/Pasywa
A3: =IF(ISNUMBER(SEARCH("aktywa",B3)),"Aktywa","Pasywa") -> Aktywa | B3: A. Aktywa trwałe | C3: I. Wartości niematerialne i prawne | D3: 3. Inne wartości niematerialne i prawne | G3: 11000400 | H3: 11000400 Oprogramowanie i licencje IT - Umorzenie | I3: Bilansowe | J3: -59859.51 | K3: -926.5 | L3: -926.5 | M3: -926.5 | N3: -926.5 | O3: -926.5 | P3: -926.5 | Q3: -926.5 | R3: -926.5 | S3: -926.5 | T3: -926.5 | U3: -926.5 | V3: -70051.01 | W3: -70051.01 | X3: 0 | Z3: A
A4: =IF(ISNUMBER(SEARCH("aktywa",B4)),"Aktywa","Pasywa") -> Aktywa | B4: A. Aktywa trwałe | C4: II. Rzeczowe aktywa trwałe | D4: 1. Środki trwałe | E4: b) budynki, lokale, prawa do lokali i obiekty inżynierii lądowej i wodnej | G4: 11502100 | H4: 11502100 Budynki - Wartość nabycia | I4: Bilansowe | J4: 8316577 | K4: 0 | L4: 0 | M4: 0 | N4: 0 | O4: 0 | P4: 0 | Q4: 0 | R4: 0 | S4: 0 | T4: 0 | U4: 0 | V4: 8316577 | W4: 8316577 | X4: 0 | Z4: I
A5: =IF(ISNUMBER(SEARCH("aktywa",B5)),"Aktywa","Pasywa") -> Aktywa | B5: A. Aktywa trwałe | C5: II. Rzeczowe aktywa trwałe | D5: 1. Środki trwałe | E5: b) budynki, lokale, prawa do lokali i obiekty inżynierii lądowej i wodnej | G5: 11502400 | H5: 11502400 Budynki - Umorzenie | I5: Bilansowe | J5: -1679956.6 | K5: -17326.2 | L5: -17326.21 | M5: -17326.2 | N5: -17326.2 | O5: -17326.2 | P5: -17326.2 | Q5: -17326.2 | R5: -17326.21 | S5: -17326.2 | T5: -17326.2 | U5: -17326.2 | V5: -1870544.8 | W5: -1870544.8 | X5: 0 | Z5: 1.
A6: =IF(ISNUMBER(SEARCH("aktywa",B6)),"Aktywa","Pasywa") -> Aktywa | B6: A. Aktywa trwałe | C6: II. Rzeczowe aktywa trwałe | D6: 2. Środki trwałe w budowie | G6: 11504100 | H6: 11504100 Nakłady w obcych środkach trwał - Wartość nabycia | I6: Bilansowe | J6: 204102.98 | K6: 0 | L6: 0 | M6: 0 | N6: 0 | O6: 0 | P6: 0 | Q6: 0 | R6: 0 | S6: 0 | T6: 0 | U6: 0 | V6: 204102.98 | W6: 204102.98 | X6: 0 | Z6: a)
A7: =IF(ISNUMBER(SEARCH("aktywa",B7)),"Aktywa","Pasywa") -> Aktywa | B7: A. Aktywa trwałe | C7: II. Rzeczowe aktywa trwałe | D7: 2. Środki trwałe w budowie | G7: 11504400 | H7: 11504400 Nakłady w obcych środkach trwał - Umorzenie | I7: Bilansowe | J7: -43327.35 | K7: -313.45 | L7: -313.46 | M7: -313.46 | N7: -6769.34 | O7: -1604.64 | P7: -1604.64 | Q7: -1604.63 | R7: -1604.64 | S7: -1604.63 | T7: -1604.63 | U7: -1604.64 | V7: -62269.51 | W7: -62269.51 | X7: 0 | Z7: -
A8: =IF(ISNUMBER(SEARCH("aktywa",B8)),"Aktywa","Pasywa") -> Aktywa | B8: A. Aktywa trwałe | C8: II. Rzeczowe aktywa trwałe | D8: 1. Środki trwałe | E8: c) urządzenia techniczne i maszyny | G8: 11508100 | H8: 11508100 Komputery i sprzęt IT - Wartość nabycia | I8: Bilansowe | J8: 1021948.2 | K8: 6806.51 | L8: -2240.07 | M8: 22451.59 | N8: 459 | O8: 0 | P8: 13387.33 | Q8: -1499.06 | R8: 157.44 | S8: 9879.54 | T8: 2065.04 | U8: 6725.93 | V8: 1080141.5 | W8: 1080141.5 | X8: 0
A9: =IF(ISNUMBER(SEARCH("aktywa",B9)),"Aktywa","Pasywa") -> Aktywa | B9: A. Aktywa trwałe | C9: II. Rzeczowe aktywa trwałe | D9: 1. Środki trwałe | E9: c) urządzenia techniczne i maszyny | G9: 11508400 | H9: 11508400 Komputery i sprzęt IT - Umorzenie | I9: Bilansowe | J9: -1009268.7 | K9: -3437.15 | L9: -3035.42 | M9: -22451.59 | N9: -459 | O9: 0 | P9: -13387.33 | Q9: 920.06 | R9: 421.56 | S9: -9879.54 | T9: -2065.04 | U9: -6725.93 | V9: -1069368.1 | W9: -1069368.1 | X9: 0
A10: =IF(ISNUMBER(SEARCH("aktywa",B10)),"Aktywa","Pasywa") -> Aktywa | B10: A. Aktywa trwałe | C10: II. Rzeczowe aktywa trwałe | D10: 1. Środki trwałe | E10: e) inne środki trwałe | G10: 11514100 | H10: 11514100 Meble i wyposażenie - Wartość nabycia | I10: Bilansowe | J10: 1071105.1 | K10: 343.9 | L10: 0 | M10: 16465.4 | N10: 0 | O10: 0 | P10: 1998.72 | Q10: 0 | R10: 0 | S10: 2900 | T10: 0 | U10: 0 | V10: 1092813.1 | W10: 1092813.1 | X10: 0
A11: =IF(ISNUMBER(SEARCH("aktywa",B11)),"Aktywa","Pasywa") -> Aktywa | B11: A. Aktywa trwałe | C11: II. Rzeczowe aktywa trwałe | D11: 1. Środki trwałe | E11: e) inne środki trwałe | G11: 11514400 | H11: 11514400 Meble i wyposażenie - Umorzenie | I11: Bilansowe | J11: -985003.34 | K11: -579 | L11: -3421.14 | M11: -18409.02 | N11: -1749.81 | O11: -1749.8 | P11: -3748.51 | Q11: -1749.81 | R11: -1749.8 | S11: -4649.8 | T11: -1749.8 | U11: -816.98 | V11: -1025376.8 | W11: -1025376.8 | X11: 0
A12: =IF(ISNUMBER(SEARCH("aktywa",B12)),"Aktywa","Pasywa") -> Aktywa | B12: A. Aktywa trwałe | C12: II. Rzeczowe aktywa trwałe | D12: 1. Środki trwałe | E12: d) środki transportu | G12: 11518100 | H12: 11518100 Samochody - Wartość nabycia | I12: Bilansowe | J12: 1042482.4 | K12: 0 | L12: -152490.19 | M12: 0 | N12: 0 | O12: 0 | P12: 0 | Q12: 0 | R12: 0 | S12: 0 | T12: 0 | U12: 0 | V12: 889992.25 | W12: 889992.25 | X12: 0
A13: =IF(ISNUMBER(SEARCH("aktywa",B13)),"Aktywa","Pasywa") -> Aktywa | B13: A. Aktywa trwałe | C13: II. Rzeczowe aktywa trwałe | D13: 1. Środki trwałe | E13: d) środki transportu | G13: 11518400 | H13: 11518400 Samochody - Umorzenie | I13: Bilansowe | J13: -881165.3 | K13: -16101 | L13: 133847.71 | M13: -13559.44 | N13: -8113.52 | O13: -6162.77 | P13: -6162.45 | Q13: -6162.46 | R13: -6162.48 | S13: -6162.47 | T13: -6162.46 | U13: -6162.46 | V13: -828229.1 | W13: -828229.1 | X13: 0
A14: =IF(ISNUMBER(SEARCH("aktywa",B14)),"Aktywa","Pasywa") -> Aktywa | B14: A. Aktywa trwałe | C14: V. Długoterminowe rozliczenia międzyokresowe | D14: 2. Inne rozliczenia międzyokresowe | G14: 13500000 | H14: 13500000 Kaucje i depozyty | I14: Bilansowe | J14: 159228 | K14: 0 | L14: 0 | M14: 0 | N14: 0 | O14: 0 | P14: 0 | Q14: 0 | R14: 0 | S14: 0 | T14: 0 | U14: 0 | V14: 159228 | W14: 159228 | X14: 0
A15: =IF(ISNUMBER(SEARCH("aktywa",B15)),"Aktywa","Pasywa") -> Aktywa | B15: B. Aktywa obrotowe | C15: II. Należności krótkoterminowe | D15: 3. Należności od pozostałych jednostek | E15: a) z tytułu dostaw i usług, o okresie spłaty: | F15: - do 12 miesięcy | G15: 15500000 | H15: 15500000 Należności handlowe - podmioty niepowiązane | I15: Bilansowe | J15: 15147.43 | K15: 769.25 | L15: -2600 | M15: -2600 | N15: -2600 | O15: -2600 | P15: -516.68 | Q15: 173.75 | R15: 36.9 | S15: 19365.65 | T15: -5000 | U15: 26568.67 | V15: 46144.97 | W15: 46144.97 | X15: 0
A16: =IF(ISNUMBER(SEARCH("aktywa",B16)),"Aktywa","Pasywa") -> Aktywa | B16: B. Aktywa obrotowe | C16: II. Należności krótkoterminowe | D16: 3. Należności od pozostałych jednostek | E16: c) inne | G16: 15500800 | H16: 15500800 Odpisy na należności handlowe - podm niepowiązane | I16: Bilansowe | J16: 0 | K16: 0 | L16: 0 | M16: 0 | N16: 0 | O16: 0 | P16: 0 | Q16: 0 | R16: 0 | S16: 0 | T16: 0 | U16: 0 | V16: 0 | W16: 0 | X16: 0
A17: =IF(ISNUMBER(SEARCH("aktywa",B17)),"Aktywa","Pasywa") -> Aktywa | B17: B. Aktywa obrotowe | C17: II. Należności krótkoterminowe | D17: 3. Należności od pozostałych jednostek | E17: a) z tytułu dostaw i usług, o okresie spłaty: | F17: - do 12 miesięcy | G17: 15500999 | H17: 15500999 Należności handlowe podm niepow - wycena bilansowa | I17: Bilansowe | J17: 0 | K17: 0 | L17: 0 | M17: 0 | N17: 0 | O17: 0 | P17: 0 | Q17: 0 | R17: 0 | S17: 0 | T17: 0 | U17: 319.97 | V17: 319.97 | W17: 319.97 | X17: 0
A18: =IF(ISNUMBER(SEARCH("aktywa",B18)),"Aktywa","Pasywa") -> Aktywa | B18: B. Aktywa obrotowe | C18: II. Należności krótkoterminowe | D18: 1. Należności od jednostek powiązanych | E18: a) z tytułu dostaw i usług, o okresie spłaty: | F18: - do 12 miesięcy | G18: 15540000 | H18: 15540000 Należności handlowe - podmioty powiązane | I18: Bilansowe | J18: 1206.04 | K18: -5000 | L18: 799.5 | M18: 676.5 | N18: 753.5 | O18: 676.5 | P18: 676.5 | Q18: 1722 | R18: 1275.11 | S18: 4097.37 | T18: -7162.98 | U18: 3344.88 | V18: 3064.92 | W18: 3064.92 | X18: 0
A19: =IF(ISNUMBER(SEARCH("aktywa",B19)),"Aktywa","Pasywa") -> Aktywa | B19: B. Aktywa obrotowe | C19: II. Należności krótkoterminowe | D19: 1. Należności od jednostek powiązanych | E19: a) z tytułu dostaw i usług, o okresie spłaty: | F19: - do 12 miesięcy | G19: 15540999 | H19: 15540999 Należności handlowe podm powiąz - wycena bilansowa | I19: Bilansowe | J19: 0 | K19: 0 | L19: 0 | M19: 0 | N19: 0 | O19: 0 | P19: 0 | Q19: 0 | R19: 0 | S19: 0 | T19: 0 | U19: -33.42 | V19: -33.42 | W19: -33.42 | X19: 0
A20: =IF(ISNUMBER(SEARCH("aktywa",B20)),"Aktywa","Pasywa") -> Aktywa | B20: B. Aktywa obrotowe | C20: II. Należności krótkoterminowe | D20: 3. Należności od pozostałych jednostek | E20: c) inne | G20: 15550368 | H20: 15550368 Bieżące rozrachunki z XYZ Principal | I20: Bilansowe | J20: 91020851 | K20: 0 | L20: 0 | M20: 0 | N20: 0 | O20: 0 | P20: -4.32 | Q20: 0 | R20: 0 | S20: 0 | T20: 0 | U20: 0 | V20: 91020847 | W20: 91020847 | X20: 0
A21: =IF(ISNUMBER(SEARCH("aktywa",B21)),"Aktywa","Pasywa") -> Pasywa | B21: B. Zobowiązania i rezerwy na zobowiązania | C21: III. Zobowiązania krótkoterminowe | D21: 3. Zobowiązania wobec pozostałych jednostek | E21: i) inne | G21: 15552000 | H21: 15552000 Bieżące rozrachunki z XYZ S.A. Genewa | I21: Bilansowe | J21: 96008976 | K21: -1861827 | L21: 1795000 | M21: 407621 | N21: 955819 | O21: -170817 | P21: -633951.26 | Q21: -88363 | R21: -70812 | S21: -129897.99 | T21: -23495.1 | U21: 170886.93 | V21: 96359139 | W21: 96359139 | X21: 0
A22: =IF(ISNUMBER(SEARCH("aktywa",B22)),"Aktywa","Pasywa") -> Aktywa | B22: B. Aktywa obrotowe | C22: II. Należności krótkoterminowe | D22: 2. Należności od jednostek powiązanych | E22: b) inne | G22: 15562000 | H22: 15562000 Faktury do wystawienia do właściciela | I22: Bilansowe | J22: 7065.52 | K22: 4799.41 | L22: 875.12 | M22: 988.93 | N22: -324.46 | O22: 435.83 | P22: 1608.09 | Q22: -246 | R22: 9758.4 | S22: -19799.13 | T22: 13981.35 | U22: -12687.91 | V22: 6455.15 | W22: 6455.15 | X22: 0
A23: =IF(ISNUMBER(SEARCH("aktywa",B23)),"Aktywa","Pasywa") -> Pasywa | B23: B. Zobowiązania i rezerwy na zobowiązania | C23: III. Zobowiązania krótkoterminowe | D23: 3. Zobowiązania wobec pozostałych jednostek | E23: g) z tytułu podatków, ceł, ubezpieczeń społecznych i zdrowotnych oraz innych tytułów publicznoprawnych | G23: 16004000 | H23: 16004000 Należności od US - VAT | I23: Bilansowe | J23: 368039 | K23: 35064 | L23: 86089 | M23: 42215 | N23: 27515 | O23: 34074 | P23: 52694 | Q23: 30222 | R23: 29072 | S23: 53572 | T23: 28170 | U23: 32801 | V23: 819527 | W23: 819527 | X23: 0
A24: =IF(ISNUMBER(SEARCH("aktywa",B24)),"Aktywa","Pasywa") -> Aktywa | B24: B. Aktywa obrotowe | C24: II. Należności krótkoterminowe | D24: 3. Należności od pozostałych jednostek | E24: b) z tytułu podatków, dotacji, ceł, ubezpieczeń społecznych i zdrowotnych oraz innych tytułów publicznoprawnych | G24: 16004010 | H24: 16004010 VAT Naliczony | I24: Bilansowe | J24: 621569.04 | K24: 25400.77 | L24: 46832.22 | M24: 52825.97 | N24: 30515.75 | O24: 30174.69 | P24: 55004.17 | Q24: 26251.76 | R24: 36588.37 | S24: 35269.57 | T24: 37089.09 | U24: 36210.02 | V24: 1033731.4 | W24: 1033731.4 | X24: 0
A25: =IF(ISNUMBER(SEARCH("aktywa",B25)),"Aktywa","Pasywa") -> Aktywa | B25: B. Aktywa obrotowe | C25: II. Należności krótkoterminowe | D25: 3. Należności od pozostałych jednostek | E25: b) z tytułu podatków, dotacji, ceł, ubezpieczeń społecznych i zdrowotnych oraz innych tytułów publicznoprawnych | G25: 16004080 | H25: 16004080 Input tax | I25: Bilansowe | J25: 2135.36 | K25: -678.77 | L25: 0 | M25: -703.1 | N25: 0 | O25: -97.54 | P25: 25.86 | Q25: 0 | R25: -56.58 | S25: -100.61 | T25: -66.7 | U25: 2814.63 | V25: 3272.55 | W25: 3272.55 | X25: 0
A26: =IF(ISNUMBER(SEARCH("aktywa",B26)),"Aktywa","Pasywa") -> Aktywa | B26: B. Aktywa obrotowe | C26: II. Należności krótkoterminowe | D26: 3. Należności od pozostałych jednostek | E26: c) inne | G26: 16008000 | H26: 16008000 Należności od pracowników | I26: Bilansowe | J26: -11714.43 | K26: 15089.74 | L26: 29514.71 | M26: 797.46 | N26: 634.96 | O26: -11740.31 | P26: -4282.4 | Q26: -1439.33 | R26: 3647.59 | S26: -9211.8 | T26: 8169.75 | U26: -12518.92 | V26: 6947.02 | W26: 6947.02 | X26: 0
A27: =IF(ISNUMBER(SEARCH("aktywa",B27)),"Aktywa","Pasywa") -> Aktywa | B27: B. Aktywa obrotowe | C27: II. Należności krótkoterminowe | D27: 3. Należności od pozostałych jednostek | E27: c) inne | G27: 16008030 | H27: 16008030 Zaliczki na wynagrodzenia | I27: Bilansowe | J27: 0 | K27: 10000 | L27: 0 | M27: 0 | N27: -10000 | O27: 0 | P27: 0 | Q27: 0 | R27: 0 | S27: 0 | T27: 0 | U27: 0 | V27: 0 | W27: 0 | X27: 0
A28: =IF(ISNUMBER(SEARCH("aktywa",B28)),"Aktywa","Pasywa") -> Aktywa | B28: B. Aktywa obrotowe | C28: IV. Krótkoterminowe rozliczenia międzyokresowe | G28: 17000000 | H28: 17000000 Rozliczenia międzyokresowe kosztów | I28: Bilansowe | J28: 62811.57 | K28: -6281.1 | L28: -6281.1 | M28: -6281.1 | N28: -6281.1 | O28: -6281.1 | P28: -6281.1 | Q28: -6281.1 | R28: -6281.1 | S28: -6281.1 | T28: -6281.67 | U28: 0 | V28: 0 | W28: 0 | X28: 0
A29: =IF(ISNUMBER(SEARCH("aktywa",B29)),"Aktywa","Pasywa") -> Aktywa | B29: B. Aktywa obrotowe | C29: IV. Krótkoterminowe rozliczenia międzyokresowe | G29: 17000030 | H29: 17000030 Rozliczenia międzyokresowe kosztów - ubezpiecz | I29: Bilansowe | J29: 17661.79 | K29: -2812.43 | L29: 1370.29 | M29: 24187.9 | N29: -5296.11 | O29: 8255.83 | P29: 2916.45 | Q29: -5329.63 | R29: -3381.09 | S29: -5329.09 | T29: -5329.09 | U29: -1444.2 | V29: 25470.62 | W29: 25470.62 | X29: 0
A30: =IF(ISNUMBER(SEARCH("aktywa",B30)),"Aktywa","Pasywa") -> Aktywa | B30: B. Aktywa obrotowe | C30: III. Inwestycje krótkoterminowe | D30: 1. Krótkoterminowe aktywa finansowe | E30: c) środki pieniężne i inne aktywa pieniężne | F30: - środki pieniężne w kasie i na rachunkach | G30: 18579900 | H30: 18579900 mBank PLN | I30: Bilansowe | J30: 73896.98 | K30: 179485.22 | L30: 116172.51 | M30: -342155.16 | N30: 140378.92 | O30: 589860.22 | P30: -655795.89 | Q30: 67057.49 | R30: -68231.48 | S30: 15997.28 | T30: 69099.47 | U30: -91363.78 | V30: 94401.78 | W30: 94401.78 | X30: 0
A31: =IF(ISNUMBER(SEARCH("aktywa",B31)),"Aktywa","Pasywa") -> Aktywa | B31: B. Aktywa obrotowe | C31: III. Inwestycje krótkoterminowe | D31: 1. Krótkoterminowe aktywa finansowe | E31: c) środki pieniężne i inne aktywa pieniężne | F31: - środki pieniężne w kasie i na rachunkach | G31: 18580000 | H31: 18580000 mBank USD | I31: Bilansowe | J31: 7177.18 | K31: -121.44 | L31: 34678.03 | M31: -37467.63 | N31: 0 | O31: 2883.3 | P31: 265.61 | Q31: 88.96 | R31: -972.06 | S31: -7325.44 | T31: -964.54 | U31: 1758.03 | V31: 0 | W31: 0 | X31: 0
A32: =IF(ISNUMBER(SEARCH("aktywa",B32)),"Aktywa","Pasywa") -> Aktywa | B32: B. Aktywa obrotowe | C32: III. Inwestycje krótkoterminowe | D32: 1. Krótkoterminowe aktywa finansowe | E32: c) środki pieniężne i inne aktywa pieniężne | F32: - środki pieniężne w kasie i na rachunkach | G32: 18580100 | H32: 18580100 mBank EUR | I32: Bilansowe | J32: 20275.14 | K32: -1344.03 | L32: -8823.61 | M32: 0 | N32: 0 | O32: -145.95 | P32: 3288.45 | Q32: -0.19 | R32: 0 | S32: 2496.6 | T32: 13199.93 | U32: -28946.34 | V32: 0 | W32: 0 | X32: 0
A33: =IF(ISNUMBER(SEARCH("aktywa",B33)),"Aktywa","Pasywa") -> Aktywa | B33: B. Aktywa obrotowe | C33: III. Inwestycje krótkoterminowe | D33: 1. Krótkoterminowe aktywa finansowe | E33: c) środki pieniężne i inne aktywa pieniężne | F33: - środki pieniężne w kasie i na rachunkach | G33: 18580200 | H33: 18580200 mBank PLN karty debetowe | I33: Bilansowe | J33: 1038.47 | K33: -525 | L33: 4487 | M33: -10 | N33: -10 | O33: -10 | P33: -16 | Q33: -10 | R33: -1019 | S33: 973.36 | T33: -10 | U33: -10 | V33: 4878.83 | W33: 4878.83 | X33: 0
A34: =IF(ISNUMBER(SEARCH("aktywa",B34)),"Aktywa","Pasywa") -> Aktywa | B34: B. Aktywa obrotowe | C34: III. Inwestycje krótkoterminowe | D34: 1. Krótkoterminowe aktywa finansowe | E34: c) środki pieniężne i inne aktywa pieniężne | F34: - środki pieniężne w kasie i na rachunkach | G34: 19000000 | H34: 19000000 Środki pienięzne w kasie | I34: Bilansowe | J34: 4724.93 | K34: -132.92 | L34: 322.97 | M34: 0 | N34: -1134 | O34: -500 | P34: 1032 | Q34: 0 | R34: -1258.06 | S34: 1056.64 | T34: -998.7 | U34: 500 | V34: 3612.86 | W34: 3612.86 | X34: 0
A35: =IF(ISNUMBER(SEARCH("aktywa",B35)),"Aktywa","Pasywa") -> Aktywa | B35: B. Aktywa obrotowe | C35: III. Inwestycje krótkoterminowe | D35: 1. Krótkoterminowe aktywa finansowe | E35: c) środki pieniężne i inne aktywa pieniężne | F35: - środki pieniężne w kasie i na rachunkach | G35: 19002000 | H35: 19002000 Inne środki pieniężne | I35: Bilansowe | J35: 19532.08 | K35: 0 | L35: 0 | M35: 0 | N35: 0 | O35: 0 | P35: 0 | Q35: 2000 | R35: 0 | S35: -2000 | T35: -20642.43 | U35: 1110.35 | V35: 0 | W35: 0 | X35: 0
A36: =IF(ISNUMBER(SEARCH("aktywa",B36)),"Aktywa","Pasywa") -> Pasywa | B36: A. Kapitał (fundusz) własny | C36: I. Kapitał (fundusz) podstawowy | G36: 20000000 | H36: 20000000 Kapitał zakładowy | I36: Bilansowe | J36: 50000 | K36: 0 | L36: 0 | M36: 0 | N36: 0 | O36: 0 | P36: 0 | Q36: 0 | R36: 0 | S36: 0 | T36: 0 | U36: 0 | V36: 50000 | W36: 50000 | X36: 0
A37: =IF(ISNUMBER(SEARCH("aktywa",B37)),"Aktywa","Pasywa") -> Pasywa | B37: A. Kapitał (fundusz) własny | C37: V. Zysk/ (strata) z lat ubiegłych | G37: 21000000 | H37: 21000000 Zysk zatrzymany | I37: Bilansowe | J37: 1892451 | K37: 0 | L37: 0 | M37: 0 | N37: 0 | O37: 0 | P37: 0 | Q37: 0 | R37: 321922.69 | S37: 0 | T37: 0 | U37: 0 | V37: 2214373.7 | W37: 2214373.7 | X37: 0
A38: =IF(ISNUMBER(SEARCH("aktywa",B38)),"Aktywa","Pasywa") -> Pasywa | B38: A. Kapitał (fundusz) własny | C38: V. Zysk/ (strata) z lat ubiegłych | G38: 21500000 | H38: 21500000 Profit of the period | I38: Bilansowe | J38: 337223.54 | K38: 0 | L38: 0 | M38: 0 | N38: 0 | O38: 0 | P38: 0 | Q38: 0 | R38: -321922.69 | S38: 0 | T38: 0 | U38: 0 | V38: 15300.85 | W38: 15300.85 | X38: -2.3646862e-11
A39: =IF(ISNUMBER(SEARCH("aktywa",B39)),"Aktywa","Pasywa") -> Pasywa | B39: B. Zobowiązania i rezerwy na zobowiązania | C39: I. Rezerwy na zobowiązania | D39: 2. Rezerwa na świadczenia emerytalne i podobne | E39: a) długoterminowe | G39: 30500000 | H39: 30500000 Rezerwa na odprawę emerytalną | I39: Bilansowe | J39: 515308 | K39: -2375 | L39: 2375 | M39: 0 | N39: 0 | O39: 0 | P39: 0 | Q39: 0 | R39: 0 | S39: 0 | T39: 0 | U39: -16985 | V39: 498323 | W39: 498323 | X39: 0
A40: =IF(ISNUMBER(SEARCH("aktywa",B40)),"Aktywa","Pasywa") -> Pasywa | B40: B. Zobowiązania i rezerwy na zobowiązania | C40: I. Rezerwy na zobowiązania | D40: 3. Pozostałe rezerwy | E40: b) krótkoterminowe | G40: 33506033 | H40: 33506033 Rezerwa na premię roczną | I40: Bilansowe | J40: 1458033 | K40: 0 | L40: 0 | M40: -1458033 | N40: 0 | O40: 0 | P40: 0 | Q40: 0 | R40: 0 | S40: 0 | T40: 0 | U40: 1452460.8 | V40: 1452460.8 | W40: 1452460.8 | X40: 0
A41: =IF(ISNUMBER(SEARCH("aktywa",B41)),"Aktywa","Pasywa") -> Pasywa | B41: B. Zobowiązania i rezerwy na zobowiązania | C41: I. Rezerwy na zobowiązania | D41: 3. Pozostałe rezerwy | E41: a) długoterminowe | G41: 33506050 | H41: 33506050 Rezerwa urlopowa | I41: Bilansowe | J41: 740835.59 | K41: 0 | L41: 0 | M41: 0 | N41: 0 | O41: 0 | P41: 0 | Q41: 0 | R41: 0 | S41: 0 | T41: 0 | U41: 262148.3 | V41: 1002983.9 | W41: 1002983.9 | X41: 0
A42: =IF(ISNUMBER(SEARCH("aktywa",B42)),"Aktywa","Pasywa") -> Pasywa | B42: B. Zobowiązania i rezerwy na zobowiązania | C42: I. Rezerwy na zobowiązania | D42: 3. Pozostałe rezerwy | E42: a) długoterminowe | G42: 34014000 | H42: 34014000 Inne rezerwy | I42: Bilansowe | J42: 27350 | K42: 0 | L42: 0 | M42: 0 | N42: 0 | O42: 0 | P42: 0 | Q42: 0 | R42: 0 | S42: 0 | T42: 0 | U42: 24800 | V42: 52150 | W42: 52150 | X42: 0
A43: =IF(ISNUMBER(SEARCH("aktywa",B43)),"Aktywa","Pasywa") -> Pasywa | B43: B. Zobowiązania i rezerwy na zobowiązania | C43: III. Zobowiązania krótkoterminowe | D43: 3. Zobowiązania wobec pozostałych jednostek | E43: d) z tytułu dostaw i usług, o okresie wymagalności: | F43: - do 12 miesięcy | G43: 34500000 | H43: 34500000 Zobowiązania handlowe - podmioty niepowiązane | I43: Bilansowe | J43: 24764.08 | K43: -11201.76 | L43: -21140.87 | M43: 59545.15 | N43: -47164.52 | O43: 28226.39 | P43: 85949.16 | Q43: -23709.11 | R43: -61043.14 | S43: 38598.83 | T43: -8398.45 | U43: -18659.59 | V43: 45766.17 | W43: 45766.17 | X43: 0
A44: =IF(ISNUMBER(SEARCH("aktywa",B44)),"Aktywa","Pasywa") -> Aktywa | B44: B. Aktywa obrotowe | C44: II. Należności krótkoterminowe | D44: 1. Należności od jednostek powiązanych | E44: a) z tytułu dostaw i usług, o okresie spłaty: | F44: - do 12 miesięcy | G44: 34550000 | H44: 34550000 Zobowiązania handlowe - podmioty powiązane | I44: Bilansowe | J44: 1877205 | K44: -1876903.4 | L44: 1765359.9 | M44: -335134.18 | N44: 312205 | O44: -56041.17 | P44: 47587.17 | Q44: 246 | R44: 30.27 | S44: -23112.63 | T44: -38893.13 | U44: 1433122.3 | V44: 3105671 | W44: 3105671 | X44: 0
A45: =IF(ISNUMBER(SEARCH("aktywa",B45)),"Aktywa","Pasywa") -> Pasywa | B45: B. Zobowiązania i rezerwy na zobowiązania | C45: III. Zobowiązania krótkoterminowe | D45: 3. Zobowiązania wobec pozostałych jednostek | E45: d) z tytułu dostaw i usług, o okresie wymagalności: | F45: - do 12 miesięcy | G45: 34550999 | H45: 34550999 Zobowiąz handlowe podm powiąz - wycena bilansowa | I45: Bilansowe | J45: 0 | K45: 0 | L45: 0 | M45: 0 | N45: 0 | O45: 0 | P45: 0 | Q45: 0 | R45: 0 | S45: 0 | T45: 0 | U45: 0 | V45: 0 | W45: 0 | X45: 0
A46: =IF(ISNUMBER(SEARCH("aktywa",B46)),"Aktywa","Pasywa") -> Aktywa | B46: B. Aktywa obrotowe | C46: II. Należności krótkoterminowe | D46: 3. Należności od pozostałych jednostek | E46: b) z tytułu podatków, dotacji, ceł, ubezpieczeń społecznych i zdrowotnych oraz innych tytułów publicznoprawnych | G46: 35002000 | H46: 35002000 Zobowiązania wobec US - VAT | I46: Bilansowe | J46: 584 | K46: 0 | L46: 0 | M46: 0 | N46: 0 | O46: 0 | P46: 0 | Q46: 0 | R46: 0 | S46: 0 | T46: 0 | U46: 0 | V46: 584 | W46: 584 | X46: 0
A47: =IF(ISNUMBER(SEARCH("aktywa",B47)),"Aktywa","Pasywa") -> Pasywa | B47: B. Zobowiązania i rezerwy na zobowiązania | C47: III. Zobowiązania krótkoterminowe | D47: 3. Zobowiązania wobec pozostałych jednostek | E47: g) z tytułu podatków, ceł, ubezpieczeń społecznych i zdrowotnych oraz innych tytułów publicznoprawnych | G47: 35002010 | H47: 35002010 VAT Należny | I47: Bilansowe | J47: 87869.07 | K47: -412.01 | L47: 12757.91 | M47: -570.99 | N47: 174.91 | O47: 84.93 | P47: 246.74 | Q47: 465.57 | R47: 286.03 | S47: 815.6 | T47: 137.82 | U47: 3169.7 | V47: 105025.28 | W47: 105025.28 | X47: 0
A48: =IF(ISNUMBER(SEARCH("aktywa",B48)),"Aktywa","Pasywa") -> Pasywa | B48: B. Zobowiązania i rezerwy na zobowiązania | C48: III. Zobowiązania krótkoterminowe | D48: 3. Zobowiązania wobec pozostałych jednostek | E48: g) z tytułu podatków, ceł, ubezpieczeń społecznych i zdrowotnych oraz innych tytułów publicznoprawnych | G48: 35002100 | H48: 35002100 VAT należny EU | I48: Bilansowe | J48: 236.89 | K48: 0 | L48: 0 | M48: 0 | N48: 0 | O48: 33.33 | P48: 25.86 | Q48: 0 | R48: 0 | S48: 0 | T48: 0 | U48: 0 | V48: 296.08 | W48: 296.08 | X48: 0
A49: =IF(ISNUMBER(SEARCH("aktywa",B49)),"Aktywa","Pasywa") -> Pasywa | B49: B. Zobowiązania i rezerwy na zobowiązania | C49: III. Zobowiązania krótkoterminowe | D49: 3. Zobowiązania wobec pozostałych jednostek | E49: g) z tytułu podatków, ceł, ubezpieczeń społecznych i zdrowotnych oraz innych tytułów publicznoprawnych | G49: 35004001 | H49: 35004001 Zobowiązania wobec US - PIT | I49: Bilansowe | J49: 87880 | K49: -1028 | L49: 9404 | M49: 118272 | N49: -100726 | O49: 14087 | P49: -6210 | Q49: 9539 | R49: 3053 | S49: 8988 | T49: 13231 | U49: 6853 | V49: 163343 | W49: 163343 | X49: 0
A50: =IF(ISNUMBER(SEARCH("aktywa",B50)),"Aktywa","Pasywa") -> Pasywa | B50: B. Zobowiązania i rezerwy na zobowiązania | C50: III. Zobowiązania krótkoterminowe | D50: 3. Zobowiązania wobec pozostałych jednostek | E50: g) z tytułu podatków, ceł, ubezpieczeń społecznych i zdrowotnych oraz innych tytułów publicznoprawnych | G50: 35006000 | H50: 35006000 Zobowiazania z tytułu ubezpieczeń społecznych | I50: Bilansowe | J50: 433622.1 | K50: -10204.51 | L50: -1536.14 | M50: 450774.19 | N50: -492565.76 | O50: 76065.37 | P50: -90599.89 | Q50: 3886.94 | R50: -7531.4 | S50: -2597.19 | T50: -1151.18 | U50: -358162.53 | V50: 0 | W50: 0 | X50: 0
A51: =IF(ISNUMBER(SEARCH("aktywa",B51)),"Aktywa","Pasywa") -> Aktywa | B51: A. Aktywa trwałe | C51: V. Długoterminowe rozliczenia międzyokresowe | D51: 2. Inne rozliczenia międzyokresowe | G51: 36500010 | H51: 36500010 Przychody z frachtu powyżej lub ponizej manifestu | I51: Bilansowe | J51: 121.1 | K51: 0.03 | L51: 0 | M51: -0.01 | N51: 0 | O51: 0.03 | P51: -0.02 | Q51: -0.01 | R51: 0.01 | S51: 0 | T51: 1 | U51: 2.31 | V51: 124.44 | W51: 124.44 | X51: 0
A52: =IF(ISNUMBER(SEARCH("aktywa",B52)),"Aktywa","Pasywa") -> Aktywa | B52: A. Aktywa trwałe | C52: V. Długoterminowe rozliczenia międzyokresowe | D52: 1. Aktywa z tytułu odroczonego podatku dochodowego | G52: 14502000 | H52: 14502000 Aktywa z tytułu podatku odroczonego | I52: Bilansowe | J52: 520903.26 | K52: -451.25 | L52: 451.25 | M52: -277026.27 | N52: 0 | O52: 0 | P52: 0 | Q52: 0 | R52: -243876.99 | S52: 0 | T52: 0 | U52: 571149.08 | V52: 571149.08 | W52: 571149.08 | X52: 0
A53: =IF(ISNUMBER(SEARCH("aktywa",B53)),"Aktywa","Pasywa") -> Aktywa | B53: B. Aktywa obrotowe | C53: II. Należności krótkoterminowe | D53: 3. Należności od pozostałych jednostek | E53: b) z tytułu podatków, dotacji, ceł, ubezpieczeń społecznych i zdrowotnych oraz innych tytułów publicznoprawnych | G53: 16500000 | H53: 16500000 Podatek dochodowy - zaliczki i nadpłata | I53: Bilansowe | J53: 717622 | K53: 0 | L53: 0 | M53: 0 | N53: 0 | O53: -728950 | P53: 11328 | Q53: 0 | R53: 0 | S53: 0 | T53: 0 | U53: 315026 | V53: 315026 | W53: 315026 | X53: 0
A54: =IF(ISNUMBER(SEARCH("aktywa",B54)),"Aktywa","Pasywa") -> Pasywa | B54: B. Zobowiązania i rezerwy na zobowiązania | C54: III. Zobowiązania krótkoterminowe | D54: 3. Zobowiązania wobec pozostałych jednostek | E54: h) z tytułu wynagrodzeń | G54: 33506000 | H54: 33506000 Krótkoterminowe zobowiązania wobec pracowników | I54: Bilansowe | J54: 0 | K54: 0 | L54: 0 | M54: 0 | N54: 0 | O54: 0 | P54: -730.43 | Q54: 730.43 | R54: -29.56 | S54: 29.56 | T54: 0 | U54: 0 | V54: 0 | W54: 0 | X54: 0
A55: =IF(ISNUMBER(SEARCH("aktywa",B55)),"Aktywa","Pasywa") -> Aktywa | B55: A. Aktywa trwałe | C55: II. Rzeczowe aktywa trwałe | D55: 3. Zaliczki na środki trwałe | G55: 17006000 | H55: 17006000 Zaliczki na środki trwałe | I55: Bilansowe | J55: 0 | K55: 0 | L55: 0 | M55: 0 | N55: 0 | O55: 0 | P55: 0 | Q55: 0 | R55: 0 | S55: 0 | T55: 0 | U55: 0 | V55: 0 | W55: 0 | X55: 0
A56: =IF(ISNUMBER(SEARCH("aktywa",B56)),"Aktywa","Pasywa") -> Aktywa | B56: B. Aktywa obrotowe | C56: II. Należności krótkoterminowe | D56: 3. Należności od pozostałych jednostek | E56: c) inne | G56: 15560000 | H56: 15560000 Faktury do wystawienia | I56: Bilansowe | J56: 0 | K56: 0 | L56: 0 | M56: 0 | N56: 0 | O56: 0 | P56: 0 | Q56: 0 | R56: 0 | S56: 0 | T56: 0 | U56: 0 | V56: 0 | W56: 0 | X56: 0
A57: =IF(ISNUMBER(SEARCH("aktywa",B57)),"Aktywa","Pasywa") -> Aktywa | B57: A. Aktywa trwałe | C57: V. Długoterminowe rozliczenia międzyokresowe | D57: 2. Inne rozliczenia międzyokresowe | G57: 15514000 | H57: 15514000 Przychody przyszłych okresów | I57: Bilansowe | J57: 0 | K57: 0 | L57: 0 | M57: 0 | N57: 0 | O57: 0 | P57: 0 | Q57: 0 | R57: 0 | S57: 0 | T57: 0 | U57: 71754 | V57: 71754 | W57: 71754 | X57: 0
A58: =IF(ISNUMBER(SEARCH("aktywa",B58)),"Aktywa","Pasywa") -> Pasywa | B58: B. Zobowiązania i rezerwy na zobowiązania | C58: III. Zobowiązania krótkoterminowe | D58: 3. Zobowiązania wobec pozostałych jednostek | E58: d) z tytułu dostaw i usług, o okresie wymagalności: | F58: - do 12 miesięcy | G58: 34504000 | H58: 34504000 Dostawy niefakturowane - podmioty niepowiązane | I58: Bilansowe | J58: 35.57 | K58: -35.57 | L58: 0 | M58: 0 | N58: 0 | O58: 0 | P58: 0 | Q58: 0 | R58: 0 | S58: 0 | T58: 0 | U58: 60834.03 | V58: 60834.03 | W58: 60834.03 | X58: 0
A59: =IF(ISNUMBER(SEARCH("aktywa",B59)),"Aktywa","Pasywa") -> Aktywa | B59: B. Aktywa obrotowe | C59: II. Należności krótkoterminowe | D59: 3. Należności od pozostałych jednostek | E59: c) inne | G59: 34515000 | H59: 34515000 Faktura do przypisania (SD) | I59: Bilansowe | J59: 0 | K59: 0 | L59: 0 | M59: 0 | N59: 0 | O59: 0 | P59: 0 | Q59: 0 | R59: 0 | S59: 0 | T59: 0 | U59: 0 | V59: 0 | W59: 0 | X59: 0
A60: =IF(ISNUMBER(SEARCH("aktywa",B60)),"Aktywa","Pasywa") -> Aktywa | B60: B. Aktywa obrotowe | C60: III. Inwestycje krótkoterminowe | D60: 3. Inne aktywa finansowe | G60: 65526100 | H60: 65526100 Niezrealiz ujemne różnice kursowe od należ (TFx) | I60: Bilansowe | J60: 0 | K60: 0 | L60: 0 | M60: 0 | N60: 0 | O60: 0 | P60: 0 | Q60: 0 | R60: 0 | S60: 0 | T60: 27079.76 | U60: -27079.76 | V60: 0 | W60: 0 | X60: 0
A61: =IF(ISNUMBER(SEARCH("aktywa",B61)),"Aktywa","Pasywa") -> Pasywa | B61: B. Zobowiązania i rezerwy na zobowiązania | C61: III. Zobowiązania krótkoterminowe | D61: 3. Należności od pozostałych jednostek | G61: 16000000 | H61: 16000000 Other receivables | I61: Bilansowe | J61: 0 | K61: 0 | L61: 0 | M61: 0 | N61: 0 | O61: 0 | P61: 0 | Q61: 0 | R61: 0 | S61: 0 | T61: 0 | U61: 0 | V61: 0 | W61: 0 | X61: 0
A62: =IF(ISNUMBER(SEARCH("aktywa",B62)),"Aktywa","Pasywa") -> Pasywa | B62: B. Zobowiązania i rezerwy na zobowiązania | C62: I. Rezerwy na zobowiązania | D62: 1. Rezerwa z tytułu odroczonego podatku dochodowego | E62: b) krótkoterminowe | G62: 31500000 | H62: 31500000 Rezerwa z tytułu podatku odroczonego | I62: Bilansowe | J62: 0 | K62: 0 | L62: 0 | M62: 0 | N62: 0 | O62: 0 | P62: 0 | Q62: 0 | R62: 0 | S62: 0 | T62: 0 | U62: 79.17 | V62: 79.17 | W62: 79.17 | X62: 0
A63: =IF(ISNUMBER(SEARCH("aktywa",B63)),"Aktywa","Pasywa") -> Pasywa | B63: B. Zobowiązania i rezerwy na zobowiązania | C63: III. Zobowiązania krótkoterminowe | D63: 3. Zobowiązania wobec pozostałych jednostek | E63: g) z tytułu podatków, ceł, ubezpieczeń społecznych i zdrowotnych oraz innych tytułów publicznoprawnych | G63: 36000000 | H63: 36000000 Podatek dochodowy - zobowiazania | I63: Bilansowe | J63: 0 | K63: 0 | L63: 0 | M63: 0 | N63: 0 | O63: 0 | P63: 0 | Q63: 0 | R63: 0 | S63: 0 | T63: 0 | U63: 43662 | V63: 43662 | W63: 43662 | X63: 0
A64: =IF(ISNUMBER(SEARCH("aktywa",B64)),"Aktywa","Pasywa") -> Pasywa | B64: A. Kapitał (fundusz) własny | C64: VI. Zysk/ (strata) netto | H64: Zysk netto bieżącego okresu | J64: 181516.08 | K64: 161780.99 | L64: 54304.57 | M64: -575793.26 | N64: 80904.46 | O64: -183603.6 | P64: 21642.13 | Q64: 123113.27 | R64: -193925.27 | S64: 8818.26 | T64: 47007.43 | U64: 598871.28 | V64: =((SUM(_25B[[#This Row],[2025-01]:[2025-12]]))) -> 324636.34 | W64: -324636.34 | X64: 0
J66: -1

Sheet 25 Mapowanie Bilans
A1: Rodzaj1 | B1: Rodzaj2 | C1: Rodzaj3 | D1: Rodzaj4 | E1: Rodzaj5 | F1: Rodzaj6 | G1: Numer konta | H1: Nazwa konta | I1: Rodzaj konta (bilansowe/wynikowe) | J1: 2025/Jan | K1: 2025/Feb | L1: 2025/Mar | M1: 2025/Apr | N1: 2025/May | O1: 2025/Jun | P1: 2025/Jul | Q1: 2025/Aug | R1: 2025/Sep | S1: 2025/Oct | T1: 2025/Nov | U1: 2025/Dec | V1: BZ | W1: BZ 2025 | X1: Check:
A2: =IF(ISNUMBER(SEARCH("aktywa",B2)),"Aktywa","Pasywa") -> Aktywa | B2: A. Aktywa trwałe | C2: I. Wartości niematerialne i prawne | D2: 3. Inne wartości niematerialne i prawne | G2: 11000100 | H2: 11000100 Oprogramowanie i licencje IT - Wartość nabycia | I2: Bilansowe | J2: 77463.01 | K2: 0 | L2: 0 | M2: 0 | N2: 0 | O2: 0 | P2: 0 | Q2: 0 | R2: 0 | S2: 0 | T2: 0 | U2: 0 | V2: 77463.01 | W2: 77463.01 | X2: 0 | Z2: Aktywa/Pasywa
A3: =IF(ISNUMBER(SEARCH("aktywa",B3)),"Aktywa","Pasywa") -> Aktywa | B3: A. Aktywa trwałe | C3: I. Wartości niematerialne i prawne | D3: 3. Inne wartości niematerialne i prawne | G3: 11000400 | H3: 11000400 Oprogramowanie i licencje IT - Umorzenie | I3: Bilansowe | J3: -59859.51 | K3: -926.5 | L3: -926.5 | M3: -926.5 | N3: -926.5 | O3: -926.5 | P3: -926.5 | Q3: -926.5 | R3: -926.5 | S3: -926.5 | T3: -926.5 | U3: -926.5 | V3: -70051.01 | W3: -70051.01 | X3: 0 | Z3: A
A4: =IF(ISNUMBER(SEARCH("aktywa",B4)),"Aktywa","Pasywa") -> Aktywa | B4: A. Aktywa trwałe | C4: II. Rzeczowe aktywa trwałe | D4: 1. Środki trwałe | E4: b) budynki, lokale, prawa do lokali i obiekty inżynierii lądowej i wodnej | G4: 11502100 | H4: 11502100 Budynki - Wartość nabycia | I4: Bilansowe | J4: 8316577 | K4: 0 | L4: 0 | M4: 0 | N4: 0 | O4: 0 | P4: 0 | Q4: 0 | R4: 0 | S4: 0 | T4: 0 | U4: 0 | V4: 8316577 | W4: 8316577 | X4: 0 | Z4: I
A5: =IF(ISNUMBER(SEARCH("aktywa",B5)),"Aktywa","Pasywa") -> Aktywa | B5: A. Aktywa trwałe | C5: II. Rzeczowe aktywa trwałe | D5: 1. Środki trwałe | E5: b) budynki, lokale, prawa do lokali i obiekty inżynierii lądowej i wodnej | G5: 11502400 | H5: 11502400 Budynki - Umorzenie | I5: Bilansowe | J5: -1679956.6 | K5: -17326.2 | L5: -17326.21 | M5: -17326.2 | N5: -17326.2 | O5: -17326.2 | P5: -17326.2 | Q5: -17326.2 | R5: -17326.21 | S5: -17326.2 | T5: -17326.2 | U5: -17326.2 | V5: -1870544.8 | W5: -1870544.8 | X5: 0 | Z5: 1.
A6: =IF(ISNUMBER(SEARCH("aktywa",B6)),"Aktywa","Pasywa") -> Aktywa | B6: A. Aktywa trwałe | C6: II. Rzeczowe aktywa trwałe | D6: 2. Środki trwałe w budowie | G6: 11504100 | H6: 11504100 Nakłady w obcych środkach trwał - Wartość nabycia | I6: Bilansowe | J6: 204102.98 | K6: 0 | L6: 0 | M6: 0 | N6: 0 | O6: 0 | P6: 0 | Q6: 0 | R6: 0 | S6: 0 | T6: 0 | U6: 0 | V6: 204102.98 | W6: 204102.98 | X6: 0 | Z6: a)
A7: =IF(ISNUMBER(SEARCH("aktywa",B7)),"Aktywa","Pasywa") -> Aktywa | B7: A. Aktywa trwałe | C7: II. Rzeczowe aktywa trwałe | D7: 2. Środki trwałe w budowie | G7: 11504400 | H7: 11504400 Nakłady w obcych środkach trwał - Umorzenie | I7: Bilansowe | J7: -43327.35 | K7: -313.45 | L7: -313.46 | M7: -313.46 | N7: -6769.34 | O7: -1604.64 | P7: -1604.64 | Q7: -1604.63 | R7: -1604.64 | S7: -1604.63 | T7: -1604.63 | U7: -1604.64 | V7: -62269.51 | W7: -62269.51 | X7: 0 | Z7: -
A8: =IF(ISNUMBER(SEARCH("aktywa",B8)),"Aktywa","Pasywa") -> Aktywa | B8: A. Aktywa trwałe | C8: II. Rzeczowe aktywa trwałe | D8: 1. Środki trwałe | E8: c) urządzenia techniczne i maszyny | G8: 11508100 | H8: 11508100 Komputery i sprzęt IT - Wartość nabycia | I8: Bilansowe | J8: 1021948.2 | K8: 6806.51 | L8: -2240.07 | M8: 22451.59 | N8: 459 | O8: 0 | P8: 13387.33 | Q8: -1499.06 | R8: 157.44 | S8: 9879.54 | T8: 2065.04 | U8: 6725.93 | V8: 1080141.5 | W8: 1080141.5 | X8: 0
A9: =IF(ISNUMBER(SEARCH("aktywa",B9)),"Aktywa","Pasywa") -> Aktywa | B9: A. Aktywa trwałe | C9: II. Rzeczowe aktywa trwałe | D9: 1. Środki trwałe | E9: c) urządzenia techniczne i maszyny | G9: 11508400 | H9: 11508400 Komputery i sprzęt IT - Umorzenie | I9: Bilansowe | J9: -1009268.7 | K9: -3437.15 | L9: -3035.42 | M9: -22451.59 | N9: -459 | O9: 0 | P9: -13387.33 | Q9: 920.06 | R9: 421.56 | S9: -9879.54 | T9: -2065.04 | U9: -6725.93 | V9: -1069368.1 | W9: -1069368.1 | X9: 0
A10: =IF(ISNUMBER(SEARCH("aktywa",B10)),"Aktywa","Pasywa") -> Aktywa | B10: A. Aktywa trwałe | C10: II. Rzeczowe aktywa trwałe | D10: 1. Środki trwałe | E10: e) inne środki trwałe | G10: 11514100 | H10: 11514100 Meble i wyposażenie - Wartość nabycia | I10: Bilansowe | J10: 1071105.1 | K10: 343.9 | L10: 0 | M10: 16465.4 | N10: 0 | O10: 0 | P10: 1998.72 | Q10: 0 | R10: 0 | S10: 2900 | T10: 0 | U10: 0 | V10: 1092813.1 | W10: 1092813.1 | X10: 0
A11: =IF(ISNUMBER(SEARCH("aktywa",B11)),"Aktywa","Pasywa") -> Aktywa | B11: A. Aktywa trwałe | C11: II. Rzeczowe aktywa trwałe | D11: 1. Środki trwałe | E11: e) inne środki trwałe | G11: 11514400 | H11: 11514400 Meble i wyposażenie - Umorzenie | I11: Bilansowe | J11: -985003.34 | K11: -579 | L11: -3421.14 | M11: -18409.02 | N11: -1749.81 | O11: -1749.8 | P11: -3748.51 | Q11: -1749.81 | R11: -1749.8 | S11: -4649.8 | T11: -1749.8 | U11: -816.98 | V11: -1025376.8 | W11: -1025376.8 | X11: 0
A12: =IF(ISNUMBER(SEARCH("aktywa",B12)),"Aktywa","Pasywa") -> Aktywa | B12: A. Aktywa trwałe | C12: II. Rzeczowe aktywa trwałe | D12: 1. Środki trwałe | E12: d) środki transportu | G12: 11518100 | H12: 11518100 Samochody - Wartość nabycia | I12: Bilansowe | J12: 1042482.4 | K12: 0 | L12: -152490.19 | M12: 0 | N12: 0 | O12: 0 | P12: 0 | Q12: 0 | R12: 0 | S12: 0 | T12: 0 | U12: 0 | V12: 889992.25 | W12: 889992.25 | X12: 0
A13: =IF(ISNUMBER(SEARCH("aktywa",B13)),"Aktywa","Pasywa") -> Aktywa | B13: A. Aktywa trwałe | C13: II. Rzeczowe aktywa trwałe | D13: 1. Środki trwałe | E13: d) środki transportu | G13: 11518400 | H13: 11518400 Samochody - Umorzenie | I13: Bilansowe | J13: -881165.3 | K13: -16101 | L13: 133847.71 | M13: -13559.44 | N13: -8113.52 | O13: -6162.77 | P13: -6162.45 | Q13: -6162.46 | R13: -6162.48 | S13: -6162.47 | T13: -6162.46 | U13: -6162.46 | V13: -828229.1 | W13: -828229.1 | X13: 0
A14: =IF(ISNUMBER(SEARCH("aktywa",B14)),"Aktywa","Pasywa") -> Aktywa | B14: A. Aktywa trwałe | C14: V. Długoterminowe rozliczenia międzyokresowe | D14: 2. Inne rozliczenia międzyokresowe | G14: 13500000 | H14: 13500000 Kaucje i depozyty | I14: Bilansowe | J14: 159228 | K14: 0 | L14: 0 | M14: 0 | N14: 0 | O14: 0 | P14: 0 | Q14: 0 | R14: 0 | S14: 0 | T14: 0 | U14: 0 | V14: 159228 | W14: 159228 | X14: 0
A15: =IF(ISNUMBER(SEARCH("aktywa",B15)),"Aktywa","Pasywa") -> Aktywa | B15: B. Aktywa obrotowe | C15: II. Należności krótkoterminowe | D15: 3. Należności od pozostałych jednostek | E15: a) z tytułu dostaw i usług, o okresie spłaty: | F15: - do 12 miesięcy | G15: 15500000 | H15: 15500000 Należności handlowe - podmioty niepowiązane | I15: Bilansowe | J15: 15147.43 | K15: 769.25 | L15: -2600 | M15: -2600 | N15: -2600 | O15: -2600 | P15: -516.68 | Q15: 173.75 | R15: 36.9 | S15: 19365.65 | T15: -5000 | U15: 26568.67 | V15: 46144.97 | W15: 46144.97 | X15: 0
A16: =IF(ISNUMBER(SEARCH("aktywa",B16)),"Aktywa","Pasywa") -> Aktywa | B16: B. Aktywa obrotowe | C16: II. Należności krótkoterminowe | D16: 3. Należności od pozostałych jednostek | E16: c) inne | G16: 15500800 | H16: 15500800 Odpisy na należności handlowe - podm niepowiązane | I16: Bilansowe | J16: 0 | K16: 0 | L16: 0 | M16: 0 | N16: 0 | O16: 0 | P16: 0 | Q16: 0 | R16: 0 | S16: 0 | T16: 0 | U16: 0 | V16: 0 | W16: 0 | X16: 0
A17: =IF(ISNUMBER(SEARCH("aktywa",B17)),"Aktywa","Pasywa") -> Aktywa | B17: B. Aktywa obrotowe | C17: II. Należności krótkoterminowe | D17: 3. Należności od pozostałych jednostek | E17: a) z tytułu dostaw i usług, o okresie spłaty: | F17: - do 12 miesięcy | G17: 15500999 | H17: 15500999 Należności handlowe podm niepow - wycena bilansowa | I17: Bilansowe | J17: 0 | K17: 0 | L17: 0 | M17: 0 | N17: 0 | O17: 0 | P17: 0 | Q17: 0 | R17: 0 | S17: 0 | T17: 0 | U17: 319.97 | V17: 319.97 | W17: 319.97 | X17: 0
A18: =IF(ISNUMBER(SEARCH("aktywa",B18)),"Aktywa","Pasywa") -> Aktywa | B18: B. Aktywa obrotowe | C18: II. Należności krótkoterminowe | D18: 1. Należności od jednostek powiązanych | E18: a) z tytułu dostaw i usług, o okresie spłaty: | F18: - do 12 miesięcy | G18: 15540000 | H18: 15540000 Należności handlowe - podmioty powiązane | I18: Bilansowe | J18: 1206.04 | K18: -5000 | L18: 799.5 | M18: 676.5 | N18: 753.5 | O18: 676.5 | P18: 676.5 | Q18: 1722 | R18: 1275.11 | S18: 4097.37 | T18: -7162.98 | U18: 3344.88 | V18: 3064.92 | W18: 3064.92 | X18: 0
A19: =IF(ISNUMBER(SEARCH("aktywa",B19)),"Aktywa","Pasywa") -> Aktywa | B19: B. Aktywa obrotowe | C19: II. Należności krótkoterminowe | D19: 1. Należności od jednostek powiązanych | E19: a) z tytułu dostaw i usług, o okresie spłaty: | F19: - do 12 miesięcy | G19: 15540999 | H19: 15540999 Należności handlowe podm powiąz - wycena bilansowa | I19: Bilansowe | J19: 0 | K19: 0 | L19: 0 | M19: 0 | N19: 0 | O19: 0 | P19: 0 | Q19: 0 | R19: 0 | S19: 0 | T19: 0 | U19: -33.42 | V19: -33.42 | W19: -33.42 | X19: 0
A20: =IF(ISNUMBER(SEARCH("aktywa",B20)),"Aktywa","Pasywa") -> Aktywa | B20: B. Aktywa obrotowe | C20: II. Należności krótkoterminowe | D20: 3. Należności od pozostałych jednostek | E20: c) inne | G20: 15550368 | H20: 15550368 Bieżące rozrachunki z XYZ Principal | I20: Bilansowe | J20: 91020851 | K20: 0 | L20: 0 | M20: 0 | N20: 0 | O20: 0 | P20: -4.32 | Q20: 0 | R20: 0 | S20: 0 | T20: 0 | U20: 0 | V20: 91020847 | W20: 91020847 | X20: 0
A21: =IF(ISNUMBER(SEARCH("aktywa",B21)),"Aktywa","Pasywa") -> Pasywa | B21: B. Zobowiązania i rezerwy na zobowiązania | C21: III. Zobowiązania krótkoterminowe | D21: 3. Zobowiązania wobec pozostałych jednostek | E21: i) inne | G21: 15552000 | H21: 15552000 Bieżące rozrachunki z XYZ S.A. Genewa | I21: Bilansowe | J21: -96008976 | K21: 1861827 | L21: -1795000 | M21: -407621 | N21: -955819 | O21: 170817 | P21: 633951.26 | Q21: 88363 | R21: 70812 | S21: 129897.99 | T21: 23495.1 | U21: -170886.93 | V21: -96359139 | W21: -96359139 | X21: 0
A22: =IF(ISNUMBER(SEARCH("aktywa",B22)),"Aktywa","Pasywa") -> Aktywa | B22: B. Aktywa obrotowe | C22: II. Należności krótkoterminowe | D22: 2. Należności od jednostek powiązanych | E22: b) inne | G22: 15562000 | H22: 15562000 Faktury do wystawienia do właściciela | I22: Bilansowe | J22: 7065.52 | K22: 4799.41 | L22: 875.12 | M22: 988.93 | N22: -324.46 | O22: 435.83 | P22: 1608.09 | Q22: -246 | R22: 9758.4 | S22: -19799.13 | T22: 13981.35 | U22: -12687.91 | V22: 6455.15 | W22: 6455.15 | X22: 0
A23: =IF(ISNUMBER(SEARCH("aktywa",B23)),"Aktywa","Pasywa") -> Pasywa | B23: B. Zobowiązania i rezerwy na zobowiązania | C23: III. Zobowiązania krótkoterminowe | D23: 3. Zobowiązania wobec pozostałych jednostek | E23: g) z tytułu podatków, ceł, ubezpieczeń społecznych i zdrowotnych oraz innych tytułów publicznoprawnych | G23: 16004000 | H23: 16004000 Należności od US - VAT | I23: Bilansowe | J23: -368039 | K23: -35064 | L23: -86089 | M23: -42215 | N23: -27515 | O23: -34074 | P23: -52694 | Q23: -30222 | R23: -29072 | S23: -53572 | T23: -28170 | U23: -32801 | V23: -819527 | W23: -819527 | X23: 0
A24: =IF(ISNUMBER(SEARCH("aktywa",B24)),"Aktywa","Pasywa") -> Aktywa | B24: B. Aktywa obrotowe | C24: II. Należności krótkoterminowe | D24: 3. Należności od pozostałych jednostek | E24: b) z tytułu podatków, dotacji, ceł, ubezpieczeń społecznych i zdrowotnych oraz innych tytułów publicznoprawnych | G24: 16004010 | H24: 16004010 VAT Naliczony | I24: Bilansowe | J24: 621569.04 | K24: 25400.77 | L24: 46832.22 | M24: 52825.97 | N24: 30515.75 | O24: 30174.69 | P24: 55004.17 | Q24: 26251.76 | R24: 36588.37 | S24: 35269.57 | T24: 37089.09 | U24: 36210.02 | V24: 1033731.4 | W24: 1033731.4 | X24: 0
A25: =IF(ISNUMBER(SEARCH("aktywa",B25)),"Aktywa","Pasywa") -> Aktywa | B25: B. Aktywa obrotowe | C25: II. Należności krótkoterminowe | D25: 3. Należności od pozostałych jednostek | E25: b) z tytułu podatków, dotacji, ceł, ubezpieczeń społecznych i zdrowotnych oraz innych tytułów publicznoprawnych | G25: 16004080 | H25: 16004080 Input tax | I25: Bilansowe | J25: 2135.36 | K25: -678.77 | L25: 0 | M25: -703.1 | N25: 0 | O25: -97.54 | P25: 25.86 | Q25: 0 | R25: -56.58 | S25: -100.61 | T25: -66.7 | U25: 2814.63 | V25: 3272.55 | W25: 3272.55 | X25: 0
A26: =IF(ISNUMBER(SEARCH("aktywa",B26)),"Aktywa","Pasywa") -> Aktywa | B26: B. Aktywa obrotowe | C26: II. Należności krótkoterminowe | D26: 3. Należności od pozostałych jednostek | E26: c) inne | G26: 16008000 | H26: 16008000 Należności od pracowników | I26: Bilansowe | J26: -11714.43 | K26: 15089.74 | L26: 29514.71 | M26: 797.46 | N26: 634.96 | O26: -11740.31 | P26: -4282.4 | Q26: -1439.33 | R26: 3647.59 | S26: -9211.8 | T26: 8169.75 | U26: -12518.92 | V26: 6947.02 | W26: 6947.02 | X26: 0
A27: =IF(ISNUMBER(SEARCH("aktywa",B27)),"Aktywa","Pasywa") -> Aktywa | B27: B. Aktywa obrotowe | C27: II. Należności krótkoterminowe | D27: 3. Należności od pozostałych jednostek | E27: c) inne | G27: 16008030 | H27: 16008030 Zaliczki na wynagrodzenia | I27: Bilansowe | J27: 0 | K27: 10000 | L27: 0 | M27: 0 | N27: -10000 | O27: 0 | P27: 0 | Q27: 0 | R27: 0 | S27: 0 | T27: 0 | U27: 0 | V27: 0 | W27: 0 | X27: 0
A28: =IF(ISNUMBER(SEARCH("aktywa",B28)),"Aktywa","Pasywa") -> Aktywa | B28: B. Aktywa obrotowe | C28: IV. Krótkoterminowe rozliczenia międzyokresowe | G28: 17000000 | H28: 17000000 Rozliczenia międzyokresowe kosztów | I28: Bilansowe | J28: 62811.57 | K28: -6281.1 | L28: -6281.1 | M28: -6281.1 | N28: -6281.1 | O28: -6281.1 | P28: -6281.1 | Q28: -6281.1 | R28: -6281.1 | S28: -6281.1 | T28: -6281.67 | U28: 0 | V28: 0 | W28: 0 | X28: 0
A29: =IF(ISNUMBER(SEARCH("aktywa",B29)),"Aktywa","Pasywa") -> Aktywa | B29: B. Aktywa obrotowe | C29: IV. Krótkoterminowe rozliczenia międzyokresowe | G29: 17000030 | H29: 17000030 Rozliczenia międzyokresowe kosztów - ubezpiecz | I29: Bilansowe | J29: 17661.79 | K29: -2812.43 | L29: 1370.29 | M29: 24187.9 | N29: -5296.11 | O29: 8255.83 | P29: 2916.45 | Q29: -5329.63 | R29: -3381.09 | S29: -5329.09 | T29: -5329.09 | U29: -1444.2 | V29: 25470.62 | W29: 25470.62 | X29: 0
A30: =IF(ISNUMBER(SEARCH("aktywa",B30)),"Aktywa","Pasywa") -> Aktywa | B30: B. Aktywa obrotowe | C30: III. Inwestycje krótkoterminowe | D30: 1. Krótkoterminowe aktywa finansowe | G30: 18579900 | H30: 18579900 mBank PLN | I30: Bilansowe | J30: 73896.98 | K30: 179485.22 | L30: 116172.51 | M30: -342155.16 | N30: 140378.92 | O30: 589860.22 | P30: -655795.89 | Q30: 67057.49 | R30: -68231.48 | S30: 15997.28 | T30: 69099.47 | U30: -91363.78 | V30: 94401.78 | W30: 94401.78 | X30: 0
A31: =IF(ISNUMBER(SEARCH("aktywa",B31)),"Aktywa","Pasywa") -> Aktywa | B31: B. Aktywa obrotowe | C31: III. Inwestycje krótkoterminowe | D31: 1. Krótkoterminowe aktywa finansowe | G31: 18580000 | H31: 18580000 mBank USD | I31: Bilansowe | J31: 7177.18 | K31: -121.44 | L31: 34678.03 | M31: -37467.63 | N31: 0 | O31: 2883.3 | P31: 265.61 | Q31: 88.96 | R31: -972.06 | S31: -7325.44 | T31: -964.54 | U31: 1758.03 | V31: 0 | W31: 0 | X31: 0
A32: =IF(ISNUMBER(SEARCH("aktywa",B32)),"Aktywa","Pasywa") -> Aktywa | B32: B. Aktywa obrotowe | C32: III. Inwestycje krótkoterminowe | D32: 1. Krótkoterminowe aktywa finansowe | G32: 18580100 | H32: 18580100 mBank EUR | I32: Bilansowe | J32: 20275.14 | K32: -1344.03 | L32: -8823.61 | M32: 0 | N32: 0 | O32: -145.95 | P32: 3288.45 | Q32: -0.19 | R32: 0 | S32: 2496.6 | T32: 13199.93 | U32: -28946.34 | V32: 0 | W32: 0 | X32: 0
A33: =IF(ISNUMBER(SEARCH("aktywa",B33)),"Aktywa","Pasywa") -> Aktywa | B33: B. Aktywa obrotowe | C33: III. Inwestycje krótkoterminowe | D33: 1. Krótkoterminowe aktywa finansowe | G33: 18580200 | H33: 18580200 mBank PLN karty debetowe | I33: Bilansowe | J33: 1038.47 | K33: -525 | L33: 4487 | M33: -10 | N33: -10 | O33: -10 | P33: -16 | Q33: -10 | R33: -1019 | S33: 973.36 | T33: -10 | U33: -10 | V33: 4878.83 | W33: 4878.83 | X33: 0
A34: =IF(ISNUMBER(SEARCH("aktywa",B34)),"Aktywa","Pasywa") -> Aktywa | B34: B. Aktywa obrotowe | C34: III. Inwestycje krótkoterminowe | D34: 1. Krótkoterminowe aktywa finansowe | G34: 19000000 | H34: 19000000 Środki pienięzne w kasie | I34: Bilansowe | J34: 4724.93 | K34: -132.92 | L34: 322.97 | M34: 0 | N34: -1134 | O34: -500 | P34: 1032 | Q34: 0 | R34: -1258.06 | S34: 1056.64 | T34: -998.7 | U34: 500 | V34: 3612.86 | W34: 3612.86 | X34: 0
A35: =IF(ISNUMBER(SEARCH("aktywa",B35)),"Aktywa","Pasywa") -> Aktywa | B35: B. Aktywa obrotowe | C35: III. Inwestycje krótkoterminowe | D35: 1. Krótkoterminowe aktywa finansowe | G35: 19002000 | H35: 19002000 Inne środki pieniężne | I35: Bilansowe | J35: 19532.08 | K35: 0 | L35: 0 | M35: 0 | N35: 0 | O35: 0 | P35: 0 | Q35: 2000 | R35: 0 | S35: -2000 | T35: -20642.43 | U35: 1110.35 | V35: 0 | W35: 0 | X35: 0
A36: =IF(ISNUMBER(SEARCH("aktywa",B36)),"Aktywa","Pasywa") -> Pasywa | B36: A. Kapitał (fundusz) własny | C36: I. Kapitał (fundusz) podstawowy | G36: 20000000 | H36: 20000000 Kapitał zakładowy | I36: Bilansowe | J36: -50000 | K36: 0 | L36: 0 | M36: 0 | N36: 0 | O36: 0 | P36: 0 | Q36: 0 | R36: 0 | S36: 0 | T36: 0 | U36: 0 | V36: -50000 | W36: -50000 | X36: 0
A37: =IF(ISNUMBER(SEARCH("aktywa",B37)),"Aktywa","Pasywa") -> Pasywa | B37: A. Kapitał (fundusz) własny | C37: V. Zysk/ (strata) z lat ubiegłych | G37: 21000000 | H37: 21000000 Zysk zatrzymany | I37: Bilansowe | J37: -1892451 | K37: 0 | L37: 0 | M37: 0 | N37: 0 | O37: 0 | P37: 0 | Q37: 0 | R37: -321922.69 | S37: 0 | T37: 0 | U37: 0 | V37: -2214373.7 | W37: -2214373.7 | X37: 0
A38: =IF(ISNUMBER(SEARCH("aktywa",B38)),"Aktywa","Pasywa") -> Pasywa | B38: A. Kapitał (fundusz) własny | C38: V. Zysk/ (strata) z lat ubiegłych | G38: 21500000 | H38: 21500000 Profit of the period | I38: Bilansowe | J38: -337223.54 | K38: 0 | L38: 0 | M38: 0 | N38: 0 | O38: 0 | P38: 0 | Q38: 0 | R38: 321922.69 | S38: 0 | T38: 0 | U38: 0 | V38: -15300.85 | W38: -15300.85 | X38: 2.3646862e-11
A39: =IF(ISNUMBER(SEARCH("aktywa",B39)),"Aktywa","Pasywa") -> Pasywa | B39: B. Zobowiązania i rezerwy na zobowiązania | C39: I. Rezerwy na zobowiązania | D39: 2. Rezerwa na świadczenia emerytalne i podobne | E39: a) długoterminowe | G39: 30500000 | H39: 30500000 Rezerwa na odprawę emerytalną | I39: Bilansowe | J39: -515308 | K39: 2375 | L39: -2375 | M39: 0 | N39: 0 | O39: 0 | P39: 0 | Q39: 0 | R39: 0 | S39: 0 | T39: 0 | U39: 16985 | V39: -498323 | W39: -498323 | X39: 0
A40: =IF(ISNUMBER(SEARCH("aktywa",B40)),"Aktywa","Pasywa") -> Pasywa | B40: B. Zobowiązania i rezerwy na zobowiązania | C40: I. Rezerwy na zobowiązania | D40: 3. Pozostałe rezerwy | E40: b) krótkoterminowe | G40: 33506033 | H40: 33506033 Rezerwa na premię roczną | I40: Bilansowe | J40: -1458033 | K40: 0 | L40: 0 | M40: 1458033 | N40: 0 | O40: 0 | P40: 0 | Q40: 0 | R40: 0 | S40: 0 | T40: 0 | U40: -1452460.8 | V40: -1452460.8 | W40: -1452460.8 | X40: 0
A41: =IF(ISNUMBER(SEARCH("aktywa",B41)),"Aktywa","Pasywa") -> Pasywa | B41: B. Zobowiązania i rezerwy na zobowiązania | C41: I. Rezerwy na zobowiązania | D41: 3. Pozostałe rezerwy | E41: a) długoterminowe | G41: 33506050 | H41: 33506050 Rezerwa urlopowa | I41: Bilansowe | J41: -740835.59 | K41: 0 | L41: 0 | M41: 0 | N41: 0 | O41: 0 | P41: 0 | Q41: 0 | R41: 0 | S41: 0 | T41: 0 | U41: -262148.3 | V41: -1002983.9 | W41: -1002983.9 | X41: 0
A42: =IF(ISNUMBER(SEARCH("aktywa",B42)),"Aktywa","Pasywa") -> Pasywa | B42: B. Zobowiązania i rezerwy na zobowiązania | C42: I. Rezerwy na zobowiązania | D42: 3. Pozostałe rezerwy | E42: a) długoterminowe | G42: 34014000 | H42: 34014000 Inne rezerwy | I42: Bilansowe | J42: -27350 | K42: 0 | L42: 0 | M42: 0 | N42: 0 | O42: 0 | P42: 0 | Q42: 0 | R42: 0 | S42: 0 | T42: 0 | U42: -24800 | V42: -52150 | W42: -52150 | X42: 0
A43: =IF(ISNUMBER(SEARCH("aktywa",B43)),"Aktywa","Pasywa") -> Pasywa | B43: B. Zobowiązania i rezerwy na zobowiązania | C43: III. Zobowiązania krótkoterminowe | D43: 3. Zobowiązania wobec pozostałych jednostek | E43: d) z tytułu dostaw i usług, o okresie wymagalności: | F43: - do 12 miesięcy | G43: 34500000 | H43: 34500000 Zobowiązania handlowe - podmioty niepowiązane | I43: Bilansowe | J43: -24764.08 | K43: 11201.76 | L43: 21140.87 | M43: -59545.15 | N43: 47164.52 | O43: -28226.39 | P43: -85949.16 | Q43: 23709.11 | R43: 61043.14 | S43: -38598.83 | T43: 8398.45 | U43: 18659.59 | V43: -45766.17 | W43: -45766.17 | X43: 0
A44: =IF(ISNUMBER(SEARCH("aktywa",B44)),"Aktywa","Pasywa") -> Aktywa | B44: B. Aktywa obrotowe | C44: II. Należności krótkoterminowe | D44: 1. Należności od jednostek powiązanych | E44: a) z tytułu dostaw i usług, o okresie spłaty: | F44: - do 12 miesięcy | G44: 34550000 | H44: 34550000 Zobowiązania handlowe - podmioty powiązane | I44: Bilansowe | J44: 1877205 | K44: -1876903.4 | L44: 1765359.9 | M44: -335134.18 | N44: 312205 | O44: -56041.17 | P44: 47587.17 | Q44: 246 | R44: 30.27 | S44: -23112.63 | T44: -38893.13 | U44: 1433122.3 | V44: 3105671 | W44: 3105671 | X44: 0
A45: =IF(ISNUMBER(SEARCH("aktywa",B45)),"Aktywa","Pasywa") -> Pasywa | B45: B. Zobowiązania i rezerwy na zobowiązania | C45: III. Zobowiązania krótkoterminowe | D45: 3. Zobowiązania wobec pozostałych jednostek | E45: d) z tytułu dostaw i usług, o okresie wymagalności: | F45: - do 12 miesięcy | G45: 34550999 | H45: 34550999 Zobowiąz handlowe podm powiąz - wycena bilansowa | I45: Bilansowe | J45: 0 | K45: 0 | L45: 0 | M45: 0 | N45: 0 | O45: 0 | P45: 0 | Q45: 0 | R45: 0 | S45: 0 | T45: 0 | U45: 0 | V45: 0 | W45: 0 | X45: 0
A46: =IF(ISNUMBER(SEARCH("aktywa",B46)),"Aktywa","Pasywa") -> Aktywa | B46: B. Aktywa obrotowe | C46: II. Należności krótkoterminowe | D46: 3. Należności od pozostałych jednostek | E46: b) z tytułu podatków, dotacji, ceł, ubezpieczeń społecznych i zdrowotnych oraz innych tytułów publicznoprawnych | G46: 35002000 | H46: 35002000 Zobowiązania wobec US - VAT | I46: Bilansowe | J46: 584 | K46: 0 | L46: 0 | M46: 0 | N46: 0 | O46: 0 | P46: 0 | Q46: 0 | R46: 0 | S46: 0 | T46: 0 | U46: 0 | V46: 584 | W46: 584 | X46: 0
A47: =IF(ISNUMBER(SEARCH("aktywa",B47)),"Aktywa","Pasywa") -> Pasywa | B47: B. Zobowiązania i rezerwy na zobowiązania | C47: III. Zobowiązania krótkoterminowe | D47: 3. Zobowiązania wobec pozostałych jednostek | E47: g) z tytułu podatków, ceł, ubezpieczeń społecznych i zdrowotnych oraz innych tytułów publicznoprawnych | G47: 35002010 | H47: 35002010 VAT Należny | I47: Bilansowe | J47: -87869.07 | K47: 412.01 | L47: -12757.91 | M47: 570.99 | N47: -174.91 | O47: -84.93 | P47: -246.74 | Q47: -465.57 | R47: -286.03 | S47: -815.6 | T47: -137.82 | U47: -3169.7 | V47: -105025.28 | W47: -105025.28 | X47: 0
A48: =IF(ISNUMBER(SEARCH("aktywa",B48)),"Aktywa","Pasywa") -> Pasywa | B48: B. Zobowiązania i rezerwy na zobowiązania | C48: III. Zobowiązania krótkoterminowe | D48: 3. Zobowiązania wobec pozostałych jednostek | E48: g) z tytułu podatków, ceł, ubezpieczeń społecznych i zdrowotnych oraz innych tytułów publicznoprawnych | G48: 35002100 | H48: 35002100 VAT należny EU | I48: Bilansowe | J48: -236.89 | K48: 0 | L48: 0 | M48: 0 | N48: 0 | O48: -33.33 | P48: -25.86 | Q48: 0 | R48: 0 | S48: 0 | T48: 0 | U48: 0 | V48: -296.08 | W48: -296.08 | X48: 0
A49: =IF(ISNUMBER(SEARCH("aktywa",B49)),"Aktywa","Pasywa") -> Pasywa | B49: B. Zobowiązania i rezerwy na zobowiązania | C49: III. Zobowiązania krótkoterminowe | D49: 3. Zobowiązania wobec pozostałych jednostek | E49: g) z tytułu podatków, ceł, ubezpieczeń społecznych i zdrowotnych oraz innych tytułów publicznoprawnych | G49: 35004001 | H49: 35004001 Zobowiązania wobec US - PIT | I49: Bilansowe | J49: -87880 | K49: 1028 | L49: -9404 | M49: -118272 | N49: 100726 | O49: -14087 | P49: 6210 | Q49: -9539 | R49: -3053 | S49: -8988 | T49: -13231 | U49: -6853 | V49: -163343 | W49: -163343 | X49: 0
A50: =IF(ISNUMBER(SEARCH("aktywa",B50)),"Aktywa","Pasywa") -> Pasywa | B50: B. Zobowiązania i rezerwy na zobowiązania | C50: III. Zobowiązania krótkoterminowe | D50: 3. Zobowiązania wobec pozostałych jednostek | E50: g) z tytułu podatków, ceł, ubezpieczeń społecznych i zdrowotnych oraz innych tytułów publicznoprawnych | G50: 35006000 | H50: 35006000 Zobowiazania z tytułu ubezpieczeń społecznych | I50: Bilansowe | J50: -433622.1 | K50: 10204.51 | L50: 1536.14 | M50: -450774.19 | N50: 492565.76 | O50: -76065.37 | P50: 90599.89 | Q50: -3886.94 | R50: 7531.4 | S50: 2597.19 | T50: 1151.18 | U50: 358162.53 | V50: 0 | W50: 0 | X50: 0
A51: =IF(ISNUMBER(SEARCH("aktywa",B51)),"Aktywa","Pasywa") -> Aktywa | B51: A. Aktywa trwałe | C51: V. Długoterminowe rozliczenia międzyokresowe | D51: 2. Inne rozliczenia międzyokresowe | G51: 36500010 | H51: 36500010 Przychody z frachtu powyżej lub ponizej manifestu | I51: Bilansowe | J51: 121.1 | K51: 0.03 | L51: 0 | M51: -0.01 | N51: 0 | O51: 0.03 | P51: -0.02 | Q51: -0.01 | R51: 0.01 | S51: 0 | T51: 1 | U51: 2.31 | V51: 124.44 | W51: 124.44 | X51: 0
A52: =IF(ISNUMBER(SEARCH("aktywa",B52)),"Aktywa","Pasywa") -> Aktywa | B52: A. Aktywa trwałe | C52: V. Długoterminowe rozliczenia międzyokresowe | D52: 1. Aktywa z tytułu odroczonego podatku dochodowego | G52: 14502000 | H52: 14502000 Aktywa z tytułu podatku odroczonego | I52: Bilansowe | J52: 520903.26 | K52: -451.25 | L52: 451.25 | M52: -277026.27 | N52: 0 | O52: 0 | P52: 0 | Q52: 0 | R52: -243876.99 | S52: 0 | T52: 0 | U52: 571149.08 | V52: 571149.08 | W52: 571149.08 | X52: 0
A53: =IF(ISNUMBER(SEARCH("aktywa",B53)),"Aktywa","Pasywa") -> Aktywa | B53: B. Aktywa obrotowe | C53: II. Należności krótkoterminowe | D53: 3. Należności od pozostałych jednostek | E53: b) z tytułu podatków, dotacji, ceł, ubezpieczeń społecznych i zdrowotnych oraz innych tytułów publicznoprawnych | G53: 16500000 | H53: 16500000 Podatek dochodowy - zaliczki i nadpłata | I53: Bilansowe | J53: 717622 | K53: 0 | L53: 0 | M53: 0 | N53: 0 | O53: -728950 | P53: 11328 | Q53: 0 | R53: 0 | S53: 0 | T53: 0 | U53: 315026 | V53: 315026 | W53: 315026 | X53: 0
A54: =IF(ISNUMBER(SEARCH("aktywa",B54)),"Aktywa","Pasywa") -> Pasywa | B54: B. Zobowiązania i rezerwy na zobowiązania | C54: III. Zobowiązania krótkoterminowe | D54: 3. Zobowiązania wobec pozostałych jednostek | E54: h) z tytułu wynagrodzeń | G54: 33506000 | H54: 33506000 Krótkoterminowe zobowiązania wobec pracowników | I54: Bilansowe | J54: 0 | K54: 0 | L54: 0 | M54: 0 | N54: 0 | O54: 0 | P54: 730.43 | Q54: -730.43 | R54: 29.56 | S54: -29.56 | T54: 0 | U54: 0 | V54: 0 | W54: 0 | X54: 0
A55: =IF(ISNUMBER(SEARCH("aktywa",B55)),"Aktywa","Pasywa") -> Aktywa | B55: A. Aktywa trwałe | C55: II. Rzeczowe aktywa trwałe | D55: 3. Zaliczki na środki trwałe | G55: 17006000 | H55: 17006000 Zaliczki na środki trwałe | I55: Bilansowe | J55: 0 | K55: 0 | L55: 0 | M55: 0 | N55: 0 | O55: 0 | P55: 0 | Q55: 0 | R55: 0 | S55: 0 | T55: 0 | U55: 0 | V55: 0 | W55: 0 | X55: 0
A56: =IF(ISNUMBER(SEARCH("aktywa",B56)),"Aktywa","Pasywa") -> Aktywa | B56: B. Aktywa obrotowe | C56: II. Należności krótkoterminowe | D56: 3. Należności od pozostałych jednostek | E56: c) inne | G56: 15560000 | H56: 15560000 Faktury do wystawienia | I56: Bilansowe | J56: 0 | K56: 0 | L56: 0 | M56: 0 | N56: 0 | O56: 0 | P56: 0 | Q56: 0 | R56: 0 | S56: 0 | T56: 0 | U56: 0 | V56: 0 | W56: 0 | X56: 0
A57: =IF(ISNUMBER(SEARCH("aktywa",B57)),"Aktywa","Pasywa") -> Aktywa | B57: A. Aktywa trwałe | C57: V. Długoterminowe rozliczenia międzyokresowe | D57: 2. Inne rozliczenia międzyokresowe | G57: 15514000 | H57: 15514000 Przychody przyszłych okresów | I57: Bilansowe | J57: 0 | K57: 0 | L57: 0 | M57: 0 | N57: 0 | O57: 0 | P57: 0 | Q57: 0 | R57: 0 | S57: 0 | T57: 0 | U57: 71754 | V57: 71754 | W57: 71754 | X57: 0
A58: =IF(ISNUMBER(SEARCH("aktywa",B58)),"Aktywa","Pasywa") -> Pasywa | B58: B. Zobowiązania i rezerwy na zobowiązania | C58: III. Zobowiązania krótkoterminowe | D58: 3. Zobowiązania wobec pozostałych jednostek | E58: d) z tytułu dostaw i usług, o okresie wymagalności: | F58: - do 12 miesięcy | G58: 34504000 | H58: 34504000 Dostawy niefakturowane - podmioty niepowiązane | I58: Bilansowe | J58: -35.57 | K58: 35.57 | L58: 0 | M58: 0 | N58: 0 | O58: 0 | P58: 0 | Q58: 0 | R58: 0 | S58: 0 | T58: 0 | U58: -60834.03 | V58: -60834.03 | W58: -60834.03 | X58: 0
A59: =IF(ISNUMBER(SEARCH("aktywa",B59)),"Aktywa","Pasywa") -> Aktywa | B59: B. Aktywa obrotowe | C59: II. Należności krótkoterminowe | D59: 3. Należności od pozostałych jednostek | E59: c) inne | G59: 34515000 | H59: 34515000 Faktura do przypisania (SD) | I59: Bilansowe | J59: 0 | K59: 0 | L59: 0 | M59: 0 | N59: 0 | O59: 0 | P59: 0 | Q59: 0 | R59: 0 | S59: 0 | T59: 0 | U59: 0 | V59: 0 | W59: 0 | X59: 0
A60: =IF(ISNUMBER(SEARCH("aktywa",B60)),"Aktywa","Pasywa") -> Aktywa | B60: B. Aktywa obrotowe | C60: III. Inwestycje krótkoterminowe | D60: 3. Inne aktywa finansowe | G60: 65526100 | H60: 65526100 Niezrealiz ujemne różnice kursowe od należ (TFx) | I60: Bilansowe | J60: 0 | K60: 0 | L60: 0 | M60: 0 | N60: 0 | O60: 0 | P60: 0 | Q60: 0 | R60: 0 | S60: 0 | T60: 27079.76 | U60: -27079.76 | V60: 0 | W60: 0 | X60: 0
A61: =IF(ISNUMBER(SEARCH("aktywa",B61)),"Aktywa","Pasywa") -> Pasywa | B61: B. Zobowiązania i rezerwy na zobowiązania | C61: III. Zobowiązania krótkoterminowe | D61: 3. Należności od pozostałych jednostek | G61: 16000000 | H61: 16000000 Other receivables | I61: Bilansowe | J61: 0 | K61: 0 | L61: 0 | M61: 0 | N61: 0 | O61: 0 | P61: 0 | Q61: 0 | R61: 0 | S61: 0 | T61: 0 | U61: 0 | V61: 0 | W61: 0 | X61: 0
A62: =IF(ISNUMBER(SEARCH("aktywa",B62)),"Aktywa","Pasywa") -> Pasywa | B62: B. Zobowiązania i rezerwy na zobowiązania | C62: I. Rezerwy na zobowiązania | D62: 1. Rezerwa z tytułu odroczonego podatku dochodowego | E62: b) krótkoterminowe | G62: 31500000 | H62: 31500000 Rezerwa z tytułu podatku odroczonego | I62: Bilansowe | J62: 0 | K62: 0 | L62: 0 | M62: 0 | N62: 0 | O62: 0 | P62: 0 | Q62: 0 | R62: 0 | S62: 0 | T62: 0 | U62: -79.17 | V62: -79.17 | W62: -79.17 | X62: 0
A63: =IF(ISNUMBER(SEARCH("aktywa",B63)),"Aktywa","Pasywa") -> Pasywa | B63: B. Zobowiązania i rezerwy na zobowiązania | C63: III. Zobowiązania krótkoterminowe | D63: 3. Zobowiązania wobec pozostałych jednostek | E63: g) z tytułu podatków, ceł, ubezpieczeń społecznych i zdrowotnych oraz innych tytułów publicznoprawnych | G63: 36000000 | H63: 36000000 Podatek dochodowy - zobowiazania | I63: Bilansowe | J63: 0 | K63: 0 | L63: 0 | M63: 0 | N63: 0 | O63: 0 | P63: 0 | Q63: 0 | R63: 0 | S63: 0 | T63: 0 | U63: -43662 | V63: -43662 | W63: -43662 | X63: 0
A64: =IF(ISNUMBER(SEARCH("aktywa",B64)),"Aktywa","Pasywa") -> Pasywa | B64: A. Kapitał (fundusz) własny | C64: VI. Zysk/ (strata) netto | H64: Zysk netto bieżącego okresu | J64: -181516.08 | K64: -161780.99 | L64: -54304.57 | M64: 575793.26 | N64: -80904.46 | O64: 183603.6 | P64: -21642.13 | Q64: -123113.27 | R64: 193925.27 | S64: -8818.26 | T64: -47007.43 | U64: -598871.28 | V64: =(SUM('25 Mapowanie Bilans'!$J64:$U64)) -> -324636.34 | W64: 324636.34 | X64: 0
J65: =SUM(J2:J64) -> -1.3387762e-09 | K65: =SUM(K2:K64) -> 0 | L65: =SUM(L2:L64) -> 4.9476512e-10 | M65: =SUM(M2:M64) -> 0 | N65: =SUM(N2:N64) -> 1.1641532e-10 | O65: =SUM(O2:O64) -> 0 | P65: =SUM(P2:P64) -> -3.1031959e-09 | Q65: =SUM(Q2:Q64) -> 9.4587449e-10 | ... V65: =SUM(V2:V64) -> 2.3865141e-09
J66: -1

Sheet Check Bilansu 24
A3: Etykiety wierszy | B3: Suma z BZ | E3: Etykiety wierszy | F3: Suma z BZ
A4: A. Aktywa trwałe | B4: -9534734.1 | E4: A. Aktywa trwałe | F4: 9534734.1
A5: I. Wartości niematerialne i prawne | B5: -18530 | E5: I. Wartości niematerialne i prawne | F5: 18530
A6: II. Rzeczowe aktywa trwałe | B6: -7106096.6 | E6: II. Rzeczowe aktywa trwałe | F6: 7106096.6
A7: V. Długoterminowe rozliczenia międzyokresowe | B7: -2410107.5 | E7: V. Długoterminowe rozliczenia międzyokresowe | F7: 2410107.5
A8: B. Aktywa obrotowe | B8: -92539868 | E8: B. Aktywa obrotowe | F8: 92539868
A9: II. Należności krótkoterminowe | B9: -92323882 | E9: II. Należności krótkoterminowe | F9: 92323882
A10: III. Inwestycje krótkoterminowe | B10: -125098.23 | E10: III. Inwestycje krótkoterminowe | F10: 125098.23
A11: IV. Krótkoterminowe rozliczenia międzyokresowe | B11: -90888.06 | E11: IV. Krótkoterminowe rozliczenia międzyokresowe | F11: 90888.06
A12: A. Kapitał (fundusz) własny | B12: 2300040.8 | E12: A. Kapitał (fundusz) własny | F12: 2300040.8
A13: I. Kapitał (fundusz) podstawowy | B13: 50000 | E13: I. Kapitał (fundusz) podstawowy | F13: 50000
A14: V. Zysk/ (strata) z lat ubiegłych | B14: 1907751.9 | E14: V. Zysk/ (strata) z lat ubiegłych | F14: 1907751.9
A15: VI. Zysk/ (strata) netto | B15: 342288.94 | E15: VI. Zysk/ (strata) netto | F15: 342288.94
... A19: Suma końcowa | B19: 0 | E19: Suma końcowa | F19: 2.041492e+08
F21: =F8+F4 -> 1.020746e+08
F22: =F16+F12 -> 1.020746e+08
F23: =F21-F22 -> 0

Sheet 24 Bilans Mapowanie A+
A1: Rodzaj1 | B1: Rodzaj2 | C1: Rodzaj3 | D1: Rodzaj4 | E1: Rodzaj5 | F1: Rodzaj6 | G1: Numer konta | H1: Nazwa konta | I1: Rodzaj konta (bilansowe/wynikowe) | J1: 2024-01 | K1: 2024-02 | L1: 2024-03 | M1: 2024-04 | N1: 2024-05 | O1: 2024-06 | P1: 2024-07 | Q1: 2024-08 | R1: 2024-09 | S1: 2024-10 | T1: 2024-11 | U1: 2024-12 | V1: BZ | W1: BZ 2024 | X1: Check:
A2: Aktywa | B2: A. Aktywa trwałe | C2: I. Wartości niematerialne i prawne | D2: 3. Inne wartości niematerialne i prawne | G2: 11000100 | H2: 11000100 Oprogramowanie i licencje IT - Wartość nabycia | I2: Bilansowe | J2: 49668.01 | K2: 0 | L2: 27795 | M2: 0 | N2: 0 | O2: 0 | P2: 0 | Q2: 0 | R2: 0 | S2: 0 | T2: 0 | U2: 0 | V2: 77463.01 | W2: 77463.01 | X2: 0
A3: Aktywa | B3: A. Aktywa trwałe | C3: I. Wartości niematerialne i prawne | D3: 3. Inne wartości niematerialne i prawne | G3: 11000400 | H3: 11000400 Oprogramowanie i licencje IT - Umorzenie | I3: Bilansowe | J3: -49668.01 | K3: 0 | L3: 0 | M3: 0 | N3: 0 | O3: 0 | P3: 0 | Q3: 0 | R3: 0 | S3: 0 | T3: -8338.5 | U3: -926.5 | V3: -58933.01 | W3: -58933.01 | X3: 0
A4: Aktywa | B4: A. Aktywa trwałe | C4: II. Rzeczowe aktywa trwałe | D4: 1. Środki trwałe | E4: b) budynki, lokale, prawa do lokali i obiekty inżynierii lądowej i wodnej | G4: 11502100 | H4: 11502100 Budynki - Wartość nabycia | I4: Bilansowe | J4: 8316577 | K4: 0 | L4: 0 | M4: 0 | N4: 0 | O4: 0 | P4: 0 | Q4: 0 | R4: 0 | S4: 0 | T4: 0 | U4: 0 | V4: 8316577 | W4: 8316577 | X4: 0
A5: Aktywa | B5: A. Aktywa trwałe | C5: II. Rzeczowe aktywa trwałe | D5: 1. Środki trwałe | E5: b) budynki, lokale, prawa do lokali i obiekty inżynierii lądowej i wodnej | G5: 11502400 | H5: 11502400 Budynki - Umorzenie | I5: Bilansowe | J5: -1472042.2 | K5: 0 | L5: -34652.41 | M5: -17326.2 | N5: -17326.2 | O5: -17326.21 | P5: 0 | Q5: -34652.41 | R5: 0 | S5: -34652.42 | T5: -17326.2 | U5: -17326.2 | V5: -1662630.4 | W5: -1662630.4 | X5: 0
A6: Aktywa | B6: A. Aktywa trwałe | C6: II. Rzeczowe aktywa trwałe | D6: 2. Środki trwałe w budowie | G6: 11504100 | H6: 11504100 Nakłady w obcych środkach trwał - Wartość nabycia | I6: Bilansowe | J6: 45961.56 | K6: 0 | L6: 0 | M6: 0 | N6: 154941.42 | O6: 0 | P6: 0 | Q6: 0 | R6: 0 | S6: 0 | T6: 0 | U6: 0 | V6: 200902.98 | W6: 200902.98 | X6: 0
A7: Aktywa | B7: A. Aktywa trwałe | C7: II. Rzeczowe aktywa trwałe | D7: 2. Środki trwałe w budowie | G7: 11504400 | H7: 11504400 Nakłady w obcych środkach trwał - Umorzenie | I7: Bilansowe | J7: -30527.62 | K7: 0 | L7: -626.91 | M7: -313.46 | N7: -313.45 | O7: -313.45 | P7: 0 | Q7: -626.92 | R7: 0 | S7: -626.92 | T7: -313.45 | U7: -313.46 | V7: -33975.64 | W7: -33975.64 | X7: 0
A8: Aktywa | B8: A. Aktywa trwałe | C8: II. Rzeczowe aktywa trwałe | D8: 1. Środki trwałe | E8: c) urządzenia techniczne i maszyny | G8: 11508100 | H8: 11508100 Komputery i sprzęt IT - Wartość nabycia | I8: Bilansowe | J8: 861732.19 | K8: 17038.54 | L8: 16111.25 | M8: 2357.72 | N8: 90426.23 | O8: 33306.22 | P8: 30969.95 | Q8: 11382.72 | R8: 5967.17 | S8: 43619.2 | T8: 3289 | U8: 54044.92 | V8: 1170245.1 | W8: 1170245.1 | X8: 0
A9: Aktywa | B9: A. Aktywa trwałe | C9: II. Rzeczowe aktywa trwałe | D9: 1. Środki trwałe | E9: c) urządzenia techniczne i maszyny | G9: 11508400 | H9: 11508400 Komputery i sprzęt IT - Umorzenie | I9: Bilansowe | J9: -839627.19 | K9: 0 | L9: -38074.31 | M9: -47300.48 | N9: -50435.97 | O9: -36086.98 | P9: 0 | Q9: -44473.07 | R9: 0 | S9: -52577.82 | T9: -4082.85 | U9: -36848.6 | V9: -1149507.3 | W9: -1149507.3 | X9: 0
A10: Aktywa | B10: A. Aktywa trwałe | C10: II. Rzeczowe aktywa trwałe | D10: 1. Środki trwałe | E10: e) inne środki trwałe | G10: 11514100 | H10: 11514100 Meble i wyposażenie - Wartość nabycia | I10: Bilansowe | J10: 1024800.8 | K10: 598 | L10: 26000 | M10: 0 | N10: 67007.26 | O10: 8354 | P10: 553.66 | Q10: 0 | R10: 0 | S10: 1137.4 | T10: 0 | U10: 0 | V10: 1128451.1 | W10: 1128451.1 | X10: 0
A11: Aktywa | B11: A. Aktywa trwałe | C11: II. Rzeczowe aktywa trwałe | D11: 1. Środki trwałe | E11: e) inne środki trwałe | G11: 11514400 | H11: 11514400 Meble i wyposażenie - Umorzenie | I11: Bilansowe | J11: -1014993.9 | K11: 0 | L11: -1663.78 | M11: -966.21 | N11: -704.71 | O11: -10375.18 | P11: 0 | Q11: -4595.97 | R11: 0 | S11: -4042.32 | T11: -2021.17 | U11: -2021.14 | V11: -1041384.3 | W11: -1041384.3 | X11: 0
A12: Aktywa | B12: A. Aktywa trwałe | C12: II. Rzeczowe aktywa trwałe | D12: 1. Środki trwałe | E12: d) środki transportu | G12: 11518100 | H12: 11518100 Samochody - Wartość nabycia | I12: Bilansowe | J12: 1391454.6 | K12: 0 | L12: 0 | M12: 0 | N12: 0 | O12: 0 | P12: 0 | Q12: 0 | R12: 0 | S12: 0 | T12: 0 | U12: -328972.15 | V12: 1062482.4 | W12: 1062482.4 | X12: 0
A13: Aktywa | B13: A. Aktywa trwałe | C13: II. Rzeczowe aktywa trwałe | D13: 1. Środki trwałe | E13: d) środki transportu | G13: 11518400 | H13: 11518400 Samochody - Umorzenie | I13: Bilansowe | J13: -990571.85 | K13: 0 | L13: -45714.6 | M13: -22857.26 | N13: -19036.95 | O13: -19036.95 | P13: 0 | Q13: -38073.86 | R13: 0 | S13: -36769.31 | T13: -16100.98 | U13: 303097.44 | V13: -885064.32 | W13: -885064.32 | X13: 0
A14: Aktywa | B14: A. Aktywa trwałe | C14: V. Długoterminowe rozliczenia międzyokresowe | D14: 2. Inne rozliczenia międzyokresowe | G14: 13500000 | H14: 13500000 Kaucje i depozyty | I14: Bilansowe | J14: 82626 | K14: 76602 | L14: 0 | M14: 0 | N14: 0 | O14: 0 | P14: 0 | Q14: 0 | R14: 0 | S14: 0 | T14: 0 | U14: 0 | V14: 159228 | W14: 159228 | X14: 0
A15: Aktywa | B15: A. Aktywa trwałe | C15: V. Długoterminowe rozliczenia międzyokresowe | D15: 1. Aktywa z tytułu odroczonego podatku dochodowego | G15: 14502000 | H15: 14502000 Aktywa z tytułu podatku odroczonego | I15: Bilansowe | J15: 619205.87 | K15: 0 | L15: 0 | M15: 0 | N15: -329020.75 | O15: 0 | P15: 0 | Q15: 0 | R15: 0 | S15: -290185.12 | T15: 0 | U15: 520903.26 | V15: 520903.26 | W15: 520903.26 | X15: 0
A16: Aktywa | B16: B. Aktywa obrotowe | C16: II. Należności krótkoterminowe | D16: 3. Należności od pozostałych jednostek | E16: a) z tytułu dostaw i usług, o okresie spłaty: | F16: - do 12 miesięcy | G16: 15500000 | H16: 15500000 Należności handlowe - podmioty niepowiązane | I16: Bilansowe | J16: 134792.96 | K16: -5493.88 | L16: 31565.17 | M16: 13038.96 | N16: -44630.13 | O16: 252417.23 | P16: -252461.23 | Q16: -17131.87 | R16: 0 | S16: -66732.63 | T16: -27018.58 | U16: -3246 | V16: 15100 | W16: 15100 | X16: 0
A17: Aktywa | B17: B. Aktywa obrotowe | C17: II. Należności krótkoterminowe | D17: 3. Należności od pozostałych jednostek | E17: c) inne | G17: 15500800 | H17: 15500800 Odpisy na należności handlowe - podm niepowiązane | I17: Bilansowe | J17: -228599.86 | K17: 0 | L17: 0 | M17: 0 | N17: 0 | O17: 0 | P17: 0 | Q17: 0 | R17: 0 | S17: 204362.28 | T17: 0 | U17: 24237.58 | V17: 0 | W17: 0 | X17: 0
A18: Aktywa | B18: B. Aktywa obrotowe | C18: II. Należności krótkoterminowe | D18: 3. Należności od pozostałych jednostek | E18: a) z tytułu dostaw i usług, o okresie spłaty: | F18: - do 12 miesięcy | G18: 15500999 | H18: 15500999 Należności handlowe podm niepow - wycena bilansowa | I18: Bilansowe | J18: -4003.23 | K18: 0 | L18: 0 | M18: 0 | N18: 0 | O18: 0 | P18: 0 | Q18: 0 | R18: 0 | S18: 0 | T18: 0 | U18: 3933.72 | V18: -69.51 | W18: -69.51 | X18: 0
A19: Aktywa | B19: B. Aktywa obrotowe | C19: II. Należności krótkoterminowe | D19: 3. Należności od pozostałych jednostek | E19: c) inne | G19: 15560000 | H19: 15560000 Faktury do wystawienia | I19: Bilansowe | J19: 0 | K19: 0 | L19: 0 | M19: 0 | N19: 4.32 | O19: -4.32 | P19: 0 | Q19: 0 | R19: 0 | S19: 0 | T19: 0 | U19: 0 | V19: 0 | W19: 0 | X19: 0
A20: Aktywa | B20: A. Aktywa trwałe | C20: V. Długoterminowe rozliczenia międzyokresowe | D20: 2. Inne rozliczenia międzyokresowe | G20: 15514000 | H20: 15514000 Przychody przyszłych okresów | I20: Bilansowe | J20: 1850899 | K20: -1850899 | L20: 0 | M20: 0 | N20: 0 | O20: 0 | P20: 0 | Q20: 0 | R20: 0 | S20: 0 | T20: 0 | U20: 1729855 | V20: 1729855 | W20: 1729855 | X20: 0
A21: Aktywa | B21: B. Aktywa obrotowe | C21: II. Należności krótkoterminowe | D21: 1. Należności od jednostek powiązanych | E21: a) z tytułu dostaw i usług, o okresie spłaty: | F21: - do 12 miesięcy | G21: 15540000 | H21: 15540000 Należności handlowe - podmioty powiązane | I21: Bilansowe | J21: 929.04 | K21: 0 | L21: 0 | M21: 0 | N21: 191641.94 | O21: -35780.23 | P21: -137525.04 | Q21: -18336.67 | R21: 0 | S21: 0 | T21: 0 | U21: 0 | V21: 929.04 | W21: 929.04 | X21: 0
A22: Aktywa | B22: B. Aktywa obrotowe | C22: II. Należności krótkoterminowe | D22: 1. Należności od jednostek powiązanych | E22: a) z tytułu dostaw i usług, o okresie spłaty: | F22: - do 12 miesięcy | G22: 15540999 | H22: 15540999 Należności handlowe podm powiąz - wycena bilansowa | I22: Bilansowe | J22: -26.04 | K22: 0 | L22: 0 | M22: 0 | N22: 0 | O22: 0 | P22: 0 | Q22: 0 | R22: 0 | S22: 0 | T22: 0 | U22: 26.04 | V22: 0 | W22: 0 | X22: 0
A23: Aktywa | B23: B. Aktywa obrotowe | C23: II. Należności krótkoterminowe | D23: 3. Należności od pozostałych jednostek | E23: c) inne | G23: 15550368 | H23: 15550368 Bieżące rozrachunki z XYZ Principal | I23: Bilansowe | J23: 90991394 | K23: 25146.98 | L23: 1131.32 | M23: 0 | N23: -1131.32 | O23: 4.32 | P23: 0 | Q23: 0 | R23: 0 | S23: 0 | T23: 4305.57 | U23: 0 | V23: 91020851 | W23: 91020851 | X23: 0
A24: Pasywa | B24: B. Zobowiązania i rezerwy na zobowiązania | C24: III. Zobowiązania krótkoterminowe | D24: 3. Zobowiązania wobec pozostałych jednostek | E24: i) inne | G24: 15552000 | H24: 15552000 Bieżące rozrachunki z XYZ S.A. Genewa | I24: Bilansowe | J24: 96164743 | K24: -2200425 | L24: -353554 | M24: 954250 | N24: 1621954.9 | O24: 1344860 | P24: -1138638.6 | Q24: -11000 | R24: 15000 | S24: 59640 | T24: -57000 | U24: 29000 | V24: 96428831 | W24: 96428831 | X24: 0
A25: Aktywa | B25: B. Aktywa obrotowe | C25: II. Należności krótkoterminowe | D25: 2. Należności od jednostek powiązanych | E25: b) inne | G25: 15562000 | H25: 15562000 Faktury do wystawienia do właściciela | I25: Bilansowe | J25: 40034.51 | K25: 12603.71 | L25: -21394.88 | M25: -18430.37 | N25: -21966.66 | O25: 35763.97 | P25: -152.18 | Q25: -118.94 | R25: -35000 | S25: -12415.61 | T25: 7200 | U25: 0 | V25: -13876.45 | W25: -13876.45 | X25: 0
A26: Pasywa | B26: B. Zobowiązania i rezerwy na zobowiązania | C26: III. Zobowiązania krótkoterminowe | D26: 3. Zobowiązania wobec pozostałych jednostek | E26: g) z tytułu podatków, ceł, ubezpieczeń społecznych i zdrowotnych oraz innych tytułów publicznoprawnych | G26: 16004000 | H26: 16004000 Należności od US - VAT | I26: Bilansowe | J26: -76353 | K26: 36368 | L26: 76547 | M26: 66663 | N26: 28240 | O26: 33646 | P26: 33173 | Q26: 54185 | R26: 0 | S26: 27847 | T26: 31079 | U26: 56644 | V26: 368039 | W26: 368039 | X26: 0
A27: Aktywa | B27: B. Aktywa obrotowe | C27: II. Należności krótkoterminowe | D27: 3. Należności od pozostałych jednostek | E27: b) z tytułu podatków, dotacji, ceł, ubezpieczeń społecznych i zdrowotnych oraz innych tytułów publicznoprawnych | G27: 16004010 | H27: 16004010 VAT Naliczony | I27: Bilansowe | J27: 106017.54 | K27: 28754.15 | L27: 40045.56 | M27: 33012.76 | N27: 101028.86 | O27: 32405.71 | P27: 40330.16 | Q27: 25834.45 | R27: 46879.29 | S27: 49477.24 | T27: 31843.95 | U27: 43551.13 | V27: 579180.8 | W27: 579180.8 | X27: 0
A28: Aktywa | B28: B. Aktywa obrotowe | C28: II. Należności krótkoterminowe | D28: 3. Należności od pozostałych jednostek | E28: b) z tytułu podatków, dotacji, ceł, ubezpieczeń społecznych i zdrowotnych oraz innych tytułów publicznoprawnych | G28: 16004080 | H28: 16004080 Input tax | I28: Bilansowe | J28: 325.05 | K28: 0 | L28: 0 | M28: 0 | N28: -95.81 | O28: 0 | P28: 1673.61 | Q28: 0 | R28: -4.38 | S28: 65.2 | T28: 103.69 | U28: 68 | V28: 2135.36 | W28: 2135.36 | X28: 0
A29: Aktywa | B29: B. Aktywa obrotowe | C29: II. Należności krótkoterminowe | D29: 3. Należności od pozostałych jednostek | E29: c) inne | G29: 16008000 | H29: 16008000 Należności od pracowników | I29: Bilansowe | J29: -17309.58 | K29: 12901.17 | L29: -13104.29 | M29: 8588.4 | N29: -727.52 | O29: 16950.95 | P29: -6415.3 | Q29: -9894.46 | R29: -2480.85 | S29: 9920.74 | T29: -1472.93 | U29: -6858.87 | V29: -9902.54 | W29: -9902.54 | X29: 0
A30: Aktywa | B30: B. Aktywa obrotowe | C30: II. Należności krótkoterminowe | D30: 3. Należności od pozostałych jednostek | E30: c) inne | G30: 16008030 | H30: 16008030 Zaliczki na wynagrodzenia | I30: Bilansowe | J30: 33680 | K30: -8370 | L30: -6470 | M30: 19100 | N30: -22940 | O30: 20500 | P30: -12331.09 | Q30: 5100 | R30: 2131.09 | S30: -26400 | T30: -2000 | U30: -2000 | V30: 0 | W30: 0 | X30: 0
A31: Aktywa | B31: B. Aktywa obrotowe | C31: II. Należności krótkoterminowe | D31: 3. Należności od pozostałych jednostek | E31: b) z tytułu podatków, dotacji, ceł, ubezpieczeń społecznych i zdrowotnych oraz innych tytułów publicznoprawnych | G31: 16500000 | H31: 16500000 Podatek dochodowy - zaliczki i nadpłata | I31: Bilansowe | J31: 557949 | K31: 0 | L31: 0 | M31: 0 | N31: 0 | O31: -557948 | P31: 0 | Q31: 0 | R31: 0 | S31: -1 | T31: 0 | U31: 728950 | V31: 728950 | W31: 728950 | X31: 0
A32: Aktywa | B32: B. Aktywa obrotowe | C32: IV. Krótkoterminowe rozliczenia międzyokresowe | G32: 17000000 | H32: 17000000 Rozliczenia międzyokresowe kosztów | I32: Bilansowe | J32: 159844.67 | K32: -27941.1 | L32: 17248.9 | M32: -6281.1 | N32: -29811.1 | O32: -6281 | P32: -26991.1 | Q32: -6281.1 | R32: -49601.1 | S32: 57748.9 | T32: -6281.1 | U32: -6281.1 | V32: 69092.67 | W32: 69092.67 | X32: 0
A33: Aktywa | B33: B. Aktywa obrotowe | C33: IV. Krótkoterminowe rozliczenia międzyokresowe | G33: 17000030 | H33: 17000030 Rozliczenia międzyokresowe kosztów - ubezpiecz | I33: Bilansowe | J33: 23080.09 | K33: 3252.34 | L33: -6768.4 | M33: -127.94 | N33: 28478.58 | O33: 9115.79 | P33: -612.68 | Q33: -4514.43 | R33: -6659.68 | S33: -12008.92 | T33: -5719.68 | U33: -5719.68 | V33: 21795.39 | W33: 21795.39 | X33: 0
A34: Aktywa | B34: A. Aktywa trwałe | C34: II. Rzeczowe aktywa trwałe | D34: 3. Zaliczki na środki trwałe | G34: 17006000 | H34: 17006000 Zaliczki na środki trwałe | I34: Bilansowe | J34: 0 | K34: 0 | L34: 0 | M34: 10000 | N34: 0 | O34: 0 | P34: 0 | Q34: -10000 | R34: 0 | S34: 0 | T34: 0 | U34: 0 | V34: 0 | W34: 0 | X34: 0
A35: Aktywa | B35: B. Aktywa obrotowe | C35: III. Inwestycje krótkoterminowe | D35: 1. Krótkoterminowe aktywa finansowe | E35: c) środki pieniężne i inne aktywa pieniężne | F35: - środki pieniężne w kasie i na rachunkach | G35: 18579900 | H35: 18579900 mBank PLN | I35: Bilansowe | J35: 118969.27 | K35: -22664.33 | L35: -8491.62 | M35: 1200077 | N35: -1187917.9 | O35: 574892.54 | P35: -420467.34 | Q35: 74535.7 | R35: 84251.6 | S35: 33433.01 | T35: -109214.94 | U35: -219483.51 | V35: 117919.48 | W35: 117919.48 | X35: 0
A36: Aktywa | B36: B. Aktywa obrotowe | C36: III. Inwestycje krótkoterminowe | D36: 1. Krótkoterminowe aktywa finansowe | E36: c) środki pieniężne i inne aktywa pieniężne | F36: - środki pieniężne w kasie i na rachunkach | G36: 18580000 | H36: 18580000 mBank USD | I36: Bilansowe | J36: 0 | K36: 0 | L36: 0 | M36: 415.7 | N36: 4620.34 | O36: 0 | P36: 15074.92 | Q36: -4171.42 | R36: -1225.45 | S36: -580.75 | T36: -106.19 | U36: -14027.15 | V36: 0 | W36: 0 | X36: 0
A37: Aktywa | B37: B. Aktywa obrotowe | C37: III. Inwestycje krótkoterminowe | D37: 1. Krótkoterminowe aktywa finansowe | E37: c) środki pieniężne i inne aktywa pieniężne | F37: - środki pieniężne w kasie i na rachunkach | G37: 18580100 | H37: 18580100 mBank EUR | I37: Bilansowe | J37: 38867.72 | K37: -19608.05 | L37: 102444.52 | M37: -94122.38 | N37: 19672.2 | O37: -26029.72 | P37: 238837.21 | Q37: 17259.72 | R37: -5321.46 | S37: -16924.71 | T37: 2774.91 | U37: -257849.96 | V37: 0 | W37: 0 | X37: 0
A38: Aktywa | B38: B. Aktywa obrotowe | C38: III. Inwestycje krótkoterminowe | D38: 1. Krótkoterminowe aktywa finansowe | E38: c) środki pieniężne i inne aktywa pieniężne | F38: - środki pieniężne w kasie i na rachunkach | G38: 18580200 | H38: 18580200 mBank PLN karty debetowe | I38: Bilansowe | J38: 10393.47 | K38: -3016 | L38: 4981 | M38: -6022 | N38: -10 | O38: -3019 | P38: 4960 | Q38: -2016 | R38: -3019 | S38: -110 | T38: 469 | U38: -537 | V38: 3054.47 | W38: 3054.47 | X38: 0
A39: Aktywa | B39: B. Aktywa obrotowe | C39: III. Inwestycje krótkoterminowe | D39: 1. Krótkoterminowe aktywa finansowe | E39: c) środki pieniężne i inne aktywa pieniężne | F39: - środki pieniężne w kasie i na rachunkach | G39: 19000000 | H39: 19000000 Środki pienięzne w kasie | I39: Bilansowe | J39: 5799.08 | K39: -2574.92 | L39: 916.41 | M39: 2583 | N39: -2932.8 | O39: -3000 | P39: 3834.67 | Q39: -815.12 | R39: 3112.45 | S39: -6665.71 | T39: 389.78 | U39: 3477.44 | V39: 4124.28 | W39: 4124.28 | X39: 0
A40: Aktywa | B40: B. Aktywa obrotowe | C40: III. Inwestycje krótkoterminowe | D40: 1. Krótkoterminowe aktywa finansowe | E40: c) środki pieniężne i inne aktywa pieniężne | F40: - środki pieniężne w kasie i na rachunkach | G40: 19002000 | H40: 19002000 Inne środki pieniężne | I40: Bilansowe | J40: 5000 | K40: 21476 | L40: -9187.68 | M40: 6165.22 | N40: 21527.5 | O40: 532.73 | P40: -6828.28 | Q40: 0 | R40: 2261.47 | S40: -26046.24 | T40: -6917.82 | U40: -7982.9 | V40: 9.5387804e-09 | W40: 9.5387804e-09 | X40: 0
A41: Pasywa | B41: A. Kapitał (fundusz) własny | C41: I. Kapitał (fundusz) podstawowy | G41: 20000000 | H41: 20000000 Kapitał zakładowy | I41: Bilansowe | J41: 50000 | K41: 0 | L41: 0 | M41: 0 | N41: 0 | O41: 0 | P41: 0 | Q41: 0 | R41: 0 | S41: 0 | T41: 0 | U41: 0 | V41: 50000 | W41: 50000 | X41: 0
A42: Pasywa | B42: A. Kapitał (fundusz) własny | C42: V. Zysk/ (strata) z lat ubiegłych | G42: 21000000 | H42: 21000000 Zysk zatrzymany | I42: Bilansowe | J42: 1256953.8 | K42: 0 | L42: 0 | M42: 0 | N42: 0 | O42: 0 | P42: 635497.26 | Q42: 0 | R42: 0 | S42: 0 | T42: 0 | U42: 0 | V42: 1892451 | W42: 1892451 | X42: 0
A43: Pasywa | B43: A. Kapitał (fundusz) własny | C43: V. Zysk/ (strata) z lat ubiegłych | G43: 21500000 | H43: 21500000 Profit of the period | I43: Bilansowe | J43: 650798.11 | K43: 0 | L43: 0 | M43: 0 | N43: 0 | O43: 0 | P43: -635497.26 | Q43: 0 | R43: 0 | S43: 0 | T43: 0 | U43: 0 | V43: 15300.85 | W43: 15300.85 | X43: 0
A44: Pasywa | B44: B. Zobowiązania i rezerwy na zobowiązania | C44: I. Rezerwy na zobowiązania | D44: 2. Rezerwa na świadczenia emerytalne i podobne | E44: a) długoterminowe | G44: 30500000 | H44: 30500000 Rezerwa na odprawę emerytalną | I44: Bilansowe | J44: 431910 | K44: 0 | L44: 0 | M44: 0 | N44: 0 | O44: 0 | P44: 0 | Q44: 0 | R44: 0 | S44: 0 | T44: 0 | U44: 83398 | V44: 515308 | W44: 515308 | X44: 0
A45: Pasywa | B45: B. Zobowiązania i rezerwy na zobowiązania | C45: I. Rezerwy na zobowiązania | D45: 3. Pozostałe rezerwy | E45: b) krótkoterminowe | G45: 33506033 | H45: 33506033 Rezerwa na premię roczną | I45: Bilansowe | J45: 1731688 | K45: 0 | L45: 0 | M45: 0 | N45: -1693374 | O45: 0 | P45: 0 | Q45: 0 | R45: 0 | S45: 0 | T45: 0 | U45: 1419719 | V45: 1458033 | W45: 1458033 | X45: 0
A46: Pasywa | B46: B. Zobowiązania i rezerwy na zobowiązania | C46: I. Rezerwy na zobowiązania | D46: 3. Pozostałe rezerwy | E46: a) długoterminowe | G46: 33506050 | H46: 33506050 Rezerwa urlopowa | I46: Bilansowe | J46: 767709 | K46: 0 | L46: 0 | M46: 0 | N46: 0 | O46: 0 | P46: 0 | Q46: 0 | R46: 0 | S46: 0 | T46: 0 | U46: -26873.41 | V46: 740835.59 | W46: 740835.59 | X46: 0
A47: Pasywa | B47: B. Zobowiązania i rezerwy na zobowiązania | C47: III. Zobowiązania krótkoterminowe | D47: 3. Zobowiązania wobec pozostałych jednostek | E47: h) z tytułu wynagrodzeń | G47: 33506000 | H47: 33506000 Krótkoterminowe zobowiązania wobec pracowników | I47: Bilansowe | J47: 53 | K47: 3382.66 | L47: 106 | M47: -682197.48 | N47: 682234.18 | O47: 123.42 | P47: -2706.67 | Q47: -754052.84 | R47: 748405.94 | S47: 4651.79 | T47: -12.41 | U47: 12.41 | V47: -3.3412562e-10 | W47: -3.3412562e-10 | X47: 0
A48: Pasywa | B48: B. Zobowiązania i rezerwy na zobowiązania | C48: I. Rezerwy na zobowiązania | D48: 3. Pozostałe rezerwy | E48: a) długoterminowe | G48: 34014000 | H48: 34014000 Inne rezerwy | I48: Bilansowe | J48: 17750 | K48: 0 | L48: 0 | M48: 0 | N48: 0 | O48: 0 | P48: 0 | Q48: 0 | R48: 0 | S48: 0 | T48: 0 | U48: 9600 | V48: 27350 | W48: 27350 | X48: 0
A49: Pasywa | B49: B. Zobowiązania i rezerwy na zobowiązania | C49: III. Zobowiązania krótkoterminowe | D49: 3. Zobowiązania wobec pozostałych jednostek | E49: d) z tytułu dostaw i usług, o okresie wymagalności: | F49: - do 12 miesięcy | G49: 34500000 | H49: 34500000 Zobowiązania handlowe - podmioty niepowiązane | I49: Bilansowe | J49: 58587.33 | K49: -75500.95 | L49: 27423.46 | M49: -47190.7 | N49: 276719.25 | O49: -158920.88 | P49: -60292.43 | Q49: -33969.5 | R49: 29761.68 | S49: -12177.21 | T49: -24530.4 | U49: 107090.49 | V49: 87000.14 | W49: 87000.14 | X49: 0
A50: Pasywa | B50: B. Zobowiązania i rezerwy na zobowiązania | C50: III. Zobowiązania krótkoterminowe | D50: 3. Zobowiązania wobec pozostałych jednostek | E50: d) z tytułu dostaw i usług, o okresie wymagalności: | F50: - do 12 miesięcy | G50: 34504000 | H50: 34504000 Dostawy niefakturowane - podmioty niepowiązane | I50: Bilansowe | J50: 38051.43 | K50: -38051.43 | L50: 0 | M50: 0 | N50: 0 | O50: 0 | P50: 0 | Q50: 0 | R50: 0 | S50: 0 | T50: 0 | U50: 56387.4 | V50: 56387.4 | W50: 56387.4 | X50: 0
A51: Aktywa | B51: B. Aktywa obrotowe | C51: II. Należności krótkoterminowe | D51: 3. Należności od pozostałych jednostek | E51: c) inne | G51: 34515000 | H51: 34515000 Faktura do przypisania (SD) | I51: Bilansowe | J51: 93807.9 | K51: -93807.9 | L51: 0 | M51: 0 | N51: 0 | O51: 0 | P51: 0 | Q51: 0 | R51: 0 | S51: 0 | T51: 0 | U51: 0 | V51: 0 | W51: 0 | X51: 0
A52: Aktywa | B52: B. Aktywa obrotowe | C52: II. Należności krótkoterminowe | D52: 1. Należności od jednostek powiązanych | E52: a) z tytułu dostaw i usług, o okresie spłaty: | F52: - do 12 miesięcy | G52: 34550000 | H52: 34550000 Zobowiązania handlowe - podmioty powiązane | I52: Bilansowe | J52: 0 | K52: 0 | L52: -107503.79 | M52: -1231453 | N52: 1338956.8 | O52: 0 | P52: -23375.94 | Q52: 13421.14 | R52: 9954.8 | S52: -66921.68 | T52: 64469.85 | U52: 2451.83 | V52: -6.9121597e-11 | W52: -6.9121597e-11 | X52: 0
A53: Pasywa | B53: B. Zobowiązania i rezerwy na zobowiązania | C53: III. Zobowiązania krótkoterminowe | D53: 3. Zobowiązania wobec pozostałych jednostek | E53: d) z tytułu dostaw i usług, o okresie wymagalności: | F53: - do 12 miesięcy | G53: 34550999 | H53: 34550999 Zobowiąz handlowe podm powiąz - wycena bilansowa | I53: Bilansowe | J53: 29.08 | K53: 0 | L53: 0 | M53: 0 | N53: 0 | O53: 0 | P53: 0 | Q53: 0 | R53: 0 | S53: 0 | T53: 0 | U53: -29.08 | V53: 0 | W53: 0 | X53: 0
A54: Pasywa | B54: B. Zobowiązania i rezerwy na zobowiązania | C54: III. Zobowiązania krótkoterminowe | D54: 3. Zobowiązania wobec pozostałych jednostek | E54: g) z tytułu podatków, ceł, ubezpieczeń społecznych i zdrowotnych oraz innych tytułów publicznoprawnych | G54: 35002010 | H54: 35002010 VAT Należny | I54: Bilansowe | J54: 1102.78 | K54: 256.48 | L54: 325.18 | M54: 512.96 | N54: -93.18 | O54: 47461.02 | P54: 13678.48 | Q54: 822.97 | R54: 22266.73 | S54: 258.28 | T54: 258.12 | U54: 272.02 | V54: 87121.84 | W54: 87121.84 | X54: 0
A55: Pasywa | B55: B. Zobowiązania i rezerwy na zobowiązania | C55: III. Zobowiązania krótkoterminowe | D55: 3. Zobowiązania wobec pozostałych jednostek | E55: g) z tytułu podatków, ceł, ubezpieczeń społecznych i zdrowotnych oraz innych tytułów publicznoprawnych | G55: 35002100 | H55: 35002100 VAT należny EU | I55: Bilansowe | J55: 0 | K55: 0 | L55: 0 | M55: 0 | N55: 0 | O55: 0 | P55: 0 | Q55: 0 | R55: 0 | S55: 65.2 | T55: 103.69 | U55: 68 | V55: 236.89 | W55: 236.89 | X55: 0
A56: Pasywa | B56: B. Zobowiązania i rezerwy na zobowiązania | C56: III. Zobowiązania krótkoterminowe | D56: 3. Zobowiązania wobec pozostałych jednostek | E56: g) z tytułu podatków, ceł, ubezpieczeń społecznych i zdrowotnych oraz innych tytułów publicznoprawnych | G56: 35004001 | H56: 35004001 Zobowiązania wobec US - PIT | I56: Bilansowe | J56: 90737 | K56: -1448 | L56: 1816 | M56: -91105 | N56: 267860 | O56: -131887 | P56: -15065 | Q56: -120908 | R56: 115651 | S56: -159 | T56: 13827 | U56: -129319 | V56: 0 | W56: 0 | X56: 0
A57: Pasywa | B57: B. Zobowiązania i rezerwy na zobowiązania | C57: III. Zobowiązania krótkoterminowe | D57: 3. Zobowiązania wobec pozostałych jednostek | E57: g) z tytułu podatków, ceł, ubezpieczeń społecznych i zdrowotnych oraz innych tytułów publicznoprawnych | G57: 35006000 | H57: 35006000 Zobowiazania z tytułu ubezpieczeń społecznych | I57: Bilansowe | J57: 352824.99 | K57: -1026.29 | L57: -7579.2 | M57: -344219.5 | N57: 892880.01 | O57: -491438.28 | P57: -81610.91 | Q57: -319830.82 | R57: 331739.46 | S57: -33984.48 | T57: -3757.68 | U57: -293997.3 | V57: -5.8207661e-10 | W57: -5.8207661e-10 | X57: 0
A58: Aktywa | B58: A. Aktywa trwałe | C58: V. Długoterminowe rozliczenia międzyokresowe | D58: 2. Inne rozliczenia międzyokresowe | G58: 36500010 | H58: 36500010 Przychody z frachtu powyżej lub ponizej manifestu | I58: Bilansowe | J58: 122.99 | K58: 0 | L58: 0.02 | M58: -0.15 | N58: 0 | O58: 0.08 | P58: -0.51 | Q58: 0.02 | R58: 0 | S58: -1.23 | T58: 0.03 | U58: -0.04 | V58: 121.21 | W58: 121.21 | X58: 0
A59: Pasywa | B59: B. Zobowiązania i rezerwy na zobowiązania | C59: III. Zobowiązania krótkoterminowe | D59: 3. Należności od pozostałych jednostek | G59: 16000000 | H59: 16000000 Other receivables | I59: Bilansowe | T59: 0 | U59: 5419 | V59: 5419 | W59: 5419 | X59: 0
A60: Aktywa | B60: B. Aktywa obrotowe | C60: II. Należności krótkoterminowe | D60: 3. Należności od pozostałych jednostek | E60: b) z tytułu podatków, dotacji, ceł, ubezpieczeń społecznych i zdrowotnych oraz innych tytułów publicznoprawnych | G60: 35002000 | H60: 35002000 Zobowiązania wobec US - VAT | I60: Bilansowe | J60: 0 | K60: 0 | L60: 0 | M60: 0 | N60: 0 | O60: 0 | P60: 0 | Q60: 0 | R60: 0 | S60: 0 | T60: 584 | U60: 0 | V60: 584 | W60: 584 | X60: 0
A61: =IF(ISNUMBER(SEARCH("aktywa",B61)),"Aktywa","Pasywa") -> Pasywa | B61: A. Kapitał (fundusz) własny | C61: VI. Zysk/ (strata) netto | H61: Zysk netto bieżącego okresu | J61: 379978.41 | K61: 440442.24 | L61: 229502.04 | M61: -6575.01 | N61: -1787117.1 | O61: -374801.78 | P61: 700535.63 | Q61: 1136584.7 | R61: -1211578.9 | S61: -300040 | T61: -51451.93 | U61: 1186810.6 | V61: 342288.94 | W61: 342288.94 | X61: 0
J63: -1

Sheet 24 Bilans Mapowanie
A1: Rodzaj1 | B1: Rodzaj2 | C1: Rodzaj3 | D1: Rodzaj4 | E1: Rodzaj5 | F1: Rodzaj6 | G1: Numer konta | H1: Nazwa konta | I1: Rodzaj konta (bilansowe/wynikowe) | J1: 2024/Jan | K1: 2024/Feb | L1: 2024/Mar | M1: 2024/Apr | N1: 2024/May | O1: 2024/Jun | P1: 2024/Jul | Q1: 2024/Aug | R1: 2024/Sep | S1: 2024/Oct | T1: 2024/Nov | U1: 2024/Dec | V1: BZ | W1: BZ 2024 | X1: Check:
A2: Aktywa | B2: A. Aktywa trwałe | C2: I. Wartości niematerialne i prawne | D2: 3. Inne wartości niematerialne i prawne | G2: 11000100 | H2: 11000100 Oprogramowanie i licencje IT - Wartość nabycia | I2: Bilansowe | J2: -49668.01 | K2: 0 | L2: -27795 | M2: 0 | N2: 0 | O2: 0 | P2: 0 | Q2: 0 | R2: 0 | S2: 0 | T2: 0 | U2: 0 | V2: -77463.01 | W2: -77463.01 | X2: 0 | Y2: =COUNTIF(_25B[Nazwa konta],'24 Bilans Mapowanie'!H2) -> 1
A3: Aktywa | B3: A. Aktywa trwałe | C3: I. Wartości niematerialne i prawne | D3: 3. Inne wartości niematerialne i prawne | G3: 11000400 | H3: 11000400 Oprogramowanie i licencje IT - Umorzenie | I3: Bilansowe | J3: 49668.01 | K3: 0 | L3: 0 | M3: 0 | N3: 0 | O3: 0 | P3: 0 | Q3: 0 | R3: 0 | S3: 0 | T3: 8338.5 | U3: 926.5 | V3: 58933.01 | W3: 58933.01 | X3: 0 | Y3: =COUNTIF(_25B[Nazwa konta],'24 Bilans Mapowanie'!H3) -> 1
A4: Aktywa | B4: A. Aktywa trwałe | C4: II. Rzeczowe aktywa trwałe | D4: 1. Środki trwałe | E4: b) budynki, lokale, prawa do lokali i obiekty inżynierii lądowej i wodnej | G4: 11502100 | H4: 11502100 Budynki - Wartość nabycia | I4: Bilansowe | J4: -8316577 | K4: 0 | L4: 0 | M4: 0 | N4: 0 | O4: 0 | P4: 0 | Q4: 0 | R4: 0 | S4: 0 | T4: 0 | U4: 0 | V4: -8316577 | W4: -8316577 | X4: 0 | Y4: =COUNTIF(_25B[Nazwa konta],'24 Bilans Mapowanie'!H4) -> 1
A5: Aktywa | B5: A. Aktywa trwałe | C5: II. Rzeczowe aktywa trwałe | D5: 1. Środki trwałe | E5: b) budynki, lokale, prawa do lokali i obiekty inżynierii lądowej i wodnej | G5: 11502400 | H5: 11502400 Budynki - Umorzenie | I5: Bilansowe | J5: 1472042.2 | K5: 0 | L5: 34652.41 | M5: 17326.2 | N5: 17326.2 | O5: 17326.21 | P5: 0 | Q5: 34652.41 | R5: 0 | S5: 34652.42 | T5: 17326.2 | U5: 17326.2 | V5: 1662630.4 | W5: 1662630.4 | X5: 0 | Y5: =COUNTIF(_25B[Nazwa konta],'24 Bilans Mapowanie'!H5) -> 1
A6: Aktywa | B6: A. Aktywa trwałe | C6: II. Rzeczowe aktywa trwałe | D6: 2. Środki trwałe w budowie | G6: 11504100 | H6: 11504100 Nakłady w obcych środkach trwał - Wartość nabycia | I6: Bilansowe | J6: -45961.56 | K6: 0 | L6: 0 | M6: 0 | N6: -154941.42 | O6: 0 | P6: 0 | Q6: 0 | R6: 0 | S6: 0 | T6: 0 | U6: 0 | V6: -200902.98 | W6: -200902.98 | X6: 0 | Y6: =COUNTIF(_25B[Nazwa konta],'24 Bilans Mapowanie'!H6) -> 1
A7: Aktywa | B7: A. Aktywa trwałe | C7: II. Rzeczowe aktywa trwałe | D7: 2. Środki trwałe w budowie | G7: 11504400 | H7: 11504400 Nakłady w obcych środkach trwał - Umorzenie | I7: Bilansowe | J7: 30527.62 | K7: 0 | L7: 626.91 | M7: 313.46 | N7: 313.45 | O7: 313.45 | P7: 0 | Q7: 626.92 | R7: 0 | S7: 626.92 | T7: 313.45 | U7: 313.46 | V7: 33975.64 | W7: 33975.64 | X7: 0 | Y7: =COUNTIF(_25B[Nazwa konta],'24 Bilans Mapowanie'!H7) -> 1
A8: Aktywa | B8: A. Aktywa trwałe | C8: II. Rzeczowe aktywa trwałe | D8: 1. Środki trwałe | E8: c) urządzenia techniczne i maszyny | G8: 11508100 | H8: 11508100 Komputery i sprzęt IT - Wartość nabycia | I8: Bilansowe | J8: -861732.19 | K8: -17038.54 | L8: -16111.25 | M8: -2357.72 | N8: -90426.23 | O8: -33306.22 | P8: -30969.95 | Q8: -11382.72 | R8: -5967.17 | S8: -43619.2 | T8: -3289 | U8: -54044.92 | V8: -1170245.1 | W8: -1170245.1 | X8: 0 | Y8: =COUNTIF(_25B[Nazwa konta],'24 Bilans Mapowanie'!H8) -> 1
A9: Aktywa | B9: A. Aktywa trwałe | C9: II. Rzeczowe aktywa trwałe | D9: 1. Środki trwałe | E9: c) urządzenia techniczne i maszyny | G9: 11508400 | H9: 11508400 Komputery i sprzęt IT - Umorzenie | I9: Bilansowe | J9: 839627.19 | K9: 0 | L9: 38074.31 | M9: 47300.48 | N9: 50435.97 | O9: 36086.98 | P9: 0 | Q9: 44473.07 | R9: 0 | S9: 52577.82 | T9: 4082.85 | U9: 36848.6 | V9: 1149507.3 | W9: 1149507.3 | X9: 0 | Y9: =COUNTIF(_25B[Nazwa konta],'24 Bilans Mapowanie'!H9) -> 1
A10: Aktywa | B10: A. Aktywa trwałe | C10: II. Rzeczowe aktywa trwałe | D10: 1. Środki trwałe | E10: e) inne środki trwałe | G10: 11514100 | H10: 11514100 Meble i wyposażenie - Wartość nabycia | I10: Bilansowe | J10: -1024800.8 | K10: -598 | L10: -26000 | M10: 0 | N10: -67007.26 | O10: -8354 | P10: -553.66 | Q10: 0 | R10: 0 | S10: -1137.4 | T10: 0 | U10: 0 | V10: -1128451.1 | W10: -1128451.1 | X10: 0 | Y10: =COUNTIF(_25B[Nazwa konta],'24 Bilans Mapowanie'!H10) -> 1
A11: Aktywa | B11: A. Aktywa trwałe | C11: II. Rzeczowe aktywa trwałe | D11: 1. Środki trwałe | E11: e) inne środki trwałe | G11: 11514400 | H11: 11514400 Meble i wyposażenie - Umorzenie | I11: Bilansowe | J11: 1014993.9 | K11: 0 | L11: 1663.78 | M11: 966.21 | N11: 704.71 | O11: 10375.18 | P11: 0 | Q11: 4595.97 | R11: 0 | S11: 4042.32 | T11: 2021.17 | U11: 2021.14 | V11: 1041384.3 | W11: 1041384.3 | X11: 0 | Y11: =COUNTIF(_25B[Nazwa konta],'24 Bilans Mapowanie'!H11) -> 1
A12: Aktywa | B12: A. Aktywa trwałe | C12: II. Rzeczowe aktywa trwałe | D12: 1. Środki trwałe | E12: d) środki transportu | G12: 11518100 | H12: 11518100 Samochody - Wartość nabycia | I12: Bilansowe | J12: -1391454.6 | K12: 0 | L12: 0 | M12: 0 | N12: 0 | O12: 0 | P12: 0 | Q12: 0 | R12: 0 | S12: 0 | T12: 0 | U12: 328972.15 | V12: -1062482.4 | W12: -1062482.4 | X12: 0 | Y12: =COUNTIF(_25B[Nazwa konta],'24 Bilans Mapowanie'!H12) -> 1
A13: Aktywa | B13: A. Aktywa trwałe | C13: II. Rzeczowe aktywa trwałe | D13: 1. Środki trwałe | E13: d) środki transportu | G13: 11518400 | H13: 11518400 Samochody - Umorzenie | I13: Bilansowe | J13: 990571.85 | K13: 0 | L13: 45714.6 | M13: 22857.26 | N13: 19036.95 | O13: 19036.95 | P13: 0 | Q13: 38073.86 | R13: 0 | S13: 36769.31 | T13: 16100.98 | U13: -303097.44 | V13: 885064.32 | W13: 885064.32 | X13: 0 | Y13: =COUNTIF(_25B[Nazwa konta],'24 Bilans Mapowanie'!H13) -> 1
A14: Aktywa | B14: A. Aktywa trwałe | C14: V. Długoterminowe rozliczenia międzyokresowe | D14: 2. Inne rozliczenia międzyokresowe | G14: 13500000 | H14: 13500000 Kaucje i depozyty | I14: Bilansowe | J14: -82626 | K14: -76602 | L14: 0 | M14: 0 | N14: 0 | O14: 0 | P14: 0 | Q14: 0 | R14: 0 | S14: 0 | T14: 0 | U14: 0 | V14: -159228 | W14: -159228 | X14: 0 | Y14: =COUNTIF(_25B[Nazwa konta],'24 Bilans Mapowanie'!H14) -> 1
A15: Aktywa | B15: A. Aktywa trwałe | C15: V. Długoterminowe rozliczenia międzyokresowe | D15: 1. Aktywa z tytułu odroczonego podatku dochodowego | G15: 14502000 | H15: 14502000 Aktywa z tytułu podatku odroczonego | I15: Bilansowe | J15: -619205.87 | K15: 0 | L15: 0 | M15: 0 | N15: 329020.75 | O15: 0 | P15: 0 | Q15: 0 | R15: 0 | S15: 290185.12 | T15: 0 | U15: -520903.26 | V15: -520903.26 | W15: -520903.26 | X15: 0 | Y15: =COUNTIF(_25B[Nazwa konta],'24 Bilans Mapowanie'!H15) -> 1
A16: Aktywa | B16: B. Aktywa obrotowe | C16: II. Należności krótkoterminowe | D16: 3. Należności od pozostałych jednostek | E16: a) z tytułu dostaw i usług, o okresie spłaty: | F16: - do 12 miesięcy | G16: 15500000 | H16: 15500000 Należności handlowe - podmioty niepowiązane | I16: Bilansowe | J16: -134792.96 | K16: 5493.88 | L16: -31565.17 | M16: -13038.96 | N16: 44630.13 | O16: -252417.23 | P16: 252461.23 | Q16: 17131.87 | R16: 0 | S16: 66732.63 | T16: 27018.58 | U16: 3246 | V16: -15100 | W16: -15100 | X16: 0 | Y16: =COUNTIF(_25B[Nazwa konta],'24 Bilans Mapowanie'!H16) -> 1
A17: Aktywa | B17: B. Aktywa obrotowe | C17: II. Należności krótkoterminowe | D17: 3. Należności od pozostałych jednostek | E17: c) inne | G17: 15500800 | H17: 15500800 Odpisy na należności handlowe - podm niepowiązane | I17: Bilansowe | J17: 228599.86 | K17: 0 | L17: 0 | M17: 0 | N17: 0 | O17: 0 | P17: 0 | Q17: 0 | R17: 0 | S17: -204362.28 | T17: 0 | U17: -24237.58 | V17: 0 | W17: 0 | X17: 0 | Y17: =COUNTIF(_25B[Nazwa konta],'24 Bilans Mapowanie'!H17) -> 1
A18: Aktywa | B18: B. Aktywa obrotowe | C18: II. Należności krótkoterminowe | D18: 3. Należności od pozostałych jednostek | E18: a) z tytułu dostaw i usług, o okresie spłaty: | F18: - do 12 miesięcy | G18: 15500999 | H18: 15500999 Należności handlowe podm niepow - wycena bilansowa | I18: Bilansowe | J18: 4003.23 | K18: 0 | L18: 0 | M18: 0 | N18: 0 | O18: 0 | P18: 0 | Q18: 0 | R18: 0 | S18: 0 | T18: 0 | U18: -3933.72 | V18: 69.51 | W18: 69.51 | X18: 0 | Y18: =COUNTIF(_25B[Nazwa konta],'24 Bilans Mapowanie'!H18) -> 1
A19: Aktywa | B19: B. Aktywa obrotowe | C19: II. Należności krótkoterminowe | D19: 3. Należności od pozostałych jednostek | E19: c) inne | G19: 15560000 | H19: 15560000 Faktury do wystawienia | I19: Bilansowe | J19: 0 | K19: 0 | L19: 0 | M19: 0 | N19: -4.32 | O19: 4.32 | P19: 0 | Q19: 0 | R19: 0 | S19: 0 | T19: 0 | U19: 0 | V19: 0 | W19: 0 | X19: 0 | Y19: =COUNTIF(_25B[Nazwa konta],'24 Bilans Mapowanie'!H19) -> 1
A20: Aktywa | B20: A. Aktywa trwałe | C20: V. Długoterminowe rozliczenia międzyokresowe | D20: 2. Inne rozliczenia międzyokresowe | G20: 15514000 | H20: 15514000 Przychody przyszłych okresów | I20: Bilansowe | J20: -1850899 | K20: 1850899 | L20: 0 | M20: 0 | N20: 0 | O20: 0 | P20: 0 | Q20: 0 | R20: 0 | S20: 0 | T20: 0 | U20: -1729855 | V20: -1729855 | W20: -1729855 | X20: 0 | Y20: =COUNTIF(_25B[Nazwa konta],'24 Bilans Mapowanie'!H20) -> 1
A21: Aktywa | B21: B. Aktywa obrotowe | C21: II. Należności krótkoterminowe | D21: 1. Należności od jednostek powiązanych | E21: a) z tytułu dostaw i usług, o okresie spłaty: | F21: - do 12 miesięcy | G21: 15540000 | H21: 15540000 Należności handlowe - podmioty powiązane | I21: Bilansowe | J21: -929.04 | K21: 0 | L21: 0 | M21: 0 | N21: -191641.94 | O21: 35780.23 | P21: 137525.04 | Q21: 18336.67 | R21: 0 | S21: 0 | T21: 0 | U21: 0 | V21: -929.04 | W21: -929.04 | X21: 0 | Y21: =COUNTIF(_25B[Nazwa konta],'24 Bilans Mapowanie'!H21) -> 1
A22: Aktywa | B22: B. Aktywa obrotowe | C22: II. Należności krótkoterminowe | D22: 1. Należności od jednostek powiązanych | E22: a) z tytułu dostaw i usług, o okresie spłaty: | F22: - do 12 miesięcy | G22: 15540999 | H22: 15540999 Należności handlowe podm powiąz - wycena bilansowa | I22: Bilansowe | J22: 26.04 | K22: 0 | L22: 0 | M22: 0 | N22: 0 | O22: 0 | P22: 0 | Q22: 0 | R22: 0 | S22: 0 | T22: 0 | U22: -26.04 | V22: 0 | W22: 0 | X22: 0 | Y22: =COUNTIF(_25B[Nazwa konta],'24 Bilans Mapowanie'!H22) -> 1
A23: Aktywa | B23: B. Aktywa obrotowe | C23: II. Należności krótkoterminowe | D23: 3. Należności od pozostałych jednostek | E23: c) inne | G23: 15550368 | H23: 15550368 Bieżące rozrachunki z XYZ Principal | I23: Bilansowe | J23: -90991394 | K23: -25146.98 | L23: -1131.32 | M23: 0 | N23: 1131.32 | O23: -4.32 | P23: 0 | Q23: 0 | R23: 0 | S23: 0 | T23: -4305.57 | U23: 0 | V23: -91020851 | W23: -91020851 | X23: 0 | Y23: =COUNTIF(_25B[Nazwa konta],'24 Bilans Mapowanie'!H23) -> 1
A24: Pasywa | B24: B. Zobowiązania i rezerwy na zobowiązania | C24: III. Zobowiązania krótkoterminowe | D24: 3. Zobowiązania wobec pozostałych jednostek | E24: i) inne | G24: 15552000 | H24: 15552000 Bieżące rozrachunki z XYZ S.A. Genewa | I24: Bilansowe | J24: 96164743 | K24: -2200425 | L24: -353554 | M24: 954250 | N24: 1621954.9 | O24: 1344860 | P24: -1138638.6 | Q24: -11000 | R24: 15000 | S24: 59640 | T24: -57000 | U24: 29000 | V24: 96428831 | W24: 96428831 | X24: 0 | Y24: =COUNTIF(_25B[Nazwa konta],'24 Bilans Mapowanie'!H24) -> 1
A25: Aktywa | B25: B. Aktywa obrotowe | C25: II. Należności krótkoterminowe | D25: 2. Należności od jednostek powiązanych | E25: b) inne | G25: 15562000 | H25: 15562000 Faktury do wystawienia do właściciela | I25: Bilansowe | J25: -40034.51 | K25: -12603.71 | L25: 21394.88 | M25: 18430.37 | N25: 21966.66 | O25: -35763.97 | P25: 152.18 | Q25: 118.94 | R25: 35000 | S25: 12415.61 | T25: -7200 | U25: 0 | V25: 13876.45 | W25: 13876.45 | X25: 0 | Y25: =COUNTIF(_25B[Nazwa konta],'24 Bilans Mapowanie'!H25) -> 1
A26: Pasywa | B26: B. Zobowiązania i rezerwy na zobowiązania | C26: III. Zobowiązania krótkoterminowe | D26: 3. Zobowiązania wobec pozostałych jednostek | E26: g) z tytułu podatków, ceł, ubezpieczeń społecznych i zdrowotnych oraz innych tytułów publicznoprawnych | G26: 16004000 | H26: 16004000 Należności od US - VAT | I26: Bilansowe | J26: -76353 | K26: 36368 | L26: 76547 | M26: 66663 | N26: 28240 | O26: 33646 | P26: 33173 | Q26: 54185 | R26: 0 | S26: 27847 | T26: 31079 | U26: 56644 | V26: 368039 | W26: 368039 | X26: 0 | Y26: =COUNTIF(_25B[Nazwa konta],'24 Bilans Mapowanie'!H26) -> 1
A27: Aktywa | B27: B. Aktywa obrotowe | C27: II. Należności krótkoterminowe | D27: 3. Należności od pozostałych jednostek | E27: b) z tytułu podatków, dotacji, ceł, ubezpieczeń społecznych i zdrowotnych oraz innych tytułów publicznoprawnych | G27: 16004010 | H27: 16004010 VAT Naliczony | I27: Bilansowe | J27: -106017.54 | K27: -28754.15 | L27: -40045.56 | M27: -33012.76 | N27: -101028.86 | O27: -32405.71 | P27: -40330.16 | Q27: -25834.45 | R27: -46879.29 | S27: -49477.24 | T27: -31843.95 | U27: -43551.13 | V27: -579180.8 | W27: -579180.8 | X27: 0 | Y27: =COUNTIF(_25B[Nazwa konta],'24 Bilans Mapowanie'!H27) -> 1
A28: Aktywa | B28: B. Aktywa obrotowe | C28: II. Należności krótkoterminowe | D28: 3. Należności od pozostałych jednostek | E28: b) z tytułu podatków, dotacji, ceł, ubezpieczeń społecznych i zdrowotnych oraz innych tytułów publicznoprawnych | G28: 16004080 | H28: 16004080 Input tax | I28: Bilansowe | J28: -325.05 | K28: 0 | L28: 0 | M28: 0 | N28: 95.81 | O28: 0 | P28: -1673.61 | Q28: 0 | R28: 4.38 | S28: -65.2 | T28: -103.69 | U28: -68 | V28: -2135.36 | W28: -2135.36 | X28: 0 | Y28: =COUNTIF(_25B[Nazwa konta],'24 Bilans Mapowanie'!H28) -> 1
A29: Aktywa | B29: B. Aktywa obrotowe | C29: II. Należności krótkoterminowe | D29: 3. Należności od pozostałych jednostek | E29: c) inne | G29: 16008000 | H29: 16008000 Należności od pracowników | I29: Bilansowe | J29: 17309.58 | K29: -12901.17 | L29: 13104.29 | M29: -8588.4 | N29: 727.52 | O29: -16950.95 | P29: 6415.3 | Q29: 9894.46 | R29: 2480.85 | S29: -9920.74 | T29: 1472.93 | U29: 6858.87 | V29: 9902.54 | W29: 9902.54 | X29: 0 | Y29: =COUNTIF(_25B[Nazwa konta],'24 Bilans Mapowanie'!H29) -> 1
A30: Aktywa | B30: B. Aktywa obrotowe | C30: II. Należności krótkoterminowe | D30: 3. Należności od pozostałych jednostek | E30: c) inne | G30: 16008030 | H30: 16008030 Zaliczki na wynagrodzenia | I30: Bilansowe | J30: -33680 | K30: 8370 | L30: 6470 | M30: -19100 | N30: 22940 | O30: -20500 | P30: 12331.09 | Q30: -5100 | R30: -2131.09 | S30: 26400 | T30: 2000 | U30: 2000 | V30: 0 | W30: 0 | X30: 0 | Y30: =COUNTIF(_25B[Nazwa konta],'24 Bilans Mapowanie'!H30) -> 1
A31: Aktywa | B31: B. Aktywa obrotowe | C31: II. Należności krótkoterminowe | D31: 3. Należności od pozostałych jednostek | E31: b) z tytułu podatków, dotacji, ceł, ubezpieczeń społecznych i zdrowotnych oraz innych tytułów publicznoprawnych | G31: 16500000 | H31: 16500000 Podatek dochodowy - zaliczki i nadpłata | I31: Bilansowe | J31: -557949 | K31: 0 | L31: 0 | M31: 0 | N31: 0 | O31: 557948 | P31: 0 | Q31: 0 | R31: 0 | S31: 1 | T31: 0 | U31: -728950 | V31: -728950 | W31: -728950 | X31: 0 | Y31: =COUNTIF(_25B[Nazwa konta],'24 Bilans Mapowanie'!H31) -> 1
A32: Aktywa | B32: B. Aktywa obrotowe | C32: IV. Krótkoterminowe rozliczenia międzyokresowe | G32: 17000000 | H32: 17000000 Rozliczenia międzyokresowe kosztów | I32: Bilansowe | J32: -159844.67 | K32: 27941.1 | L32: -17248.9 | M32: 6281.1 | N32: 29811.1 | O32: 6281 | P32: 26991.1 | Q32: 6281.1 | R32: 49601.1 | S32: -57748.9 | T32: 6281.1 | U32: 6281.1 | V32: -69092.67 | W32: -69092.67 | X32: 0 | Y32: =COUNTIF(_25B[Nazwa konta],'24 Bilans Mapowanie'!H32) -> 1
A33: Aktywa | B33: B. Aktywa obrotowe | C33: IV. Krótkoterminowe rozliczenia międzyokresowe | G33: 17000030 | H33: 17000030 Rozliczenia międzyokresowe kosztów - ubezpiecz | I33: Bilansowe | J33: -23080.09 | K33: -3252.34 | L33: 6768.4 | M33: 127.94 | N33: -28478.58 | O33: -9115.79 | P33: 612.68 | Q33: 4514.43 | R33: 6659.68 | S33: 12008.92 | T33: 5719.68 | U33: 5719.68 | V33: -21795.39 | W33: -21795.39 | X33: 0 | Y33: =COUNTIF(_25B[Nazwa konta],'24 Bilans Mapowanie'!H33) -> 1
A34: Aktywa | B34: A. Aktywa trwałe | C34: II. Rzeczowe aktywa trwałe | D34: 3. Zaliczki na środki trwałe | G34: 17006000 | H34: 17006000 Zaliczki na środki trwałe | I34: Bilansowe | J34: 0 | K34: 0 | L34: 0 | M34: -10000 | N34: 0 | O34: 0 | P34: 0 | Q34: 10000 | R34: 0 | S34: 0 | T34: 0 | U34: 0 | V34: 0 | W34: 0 | X34: 0 | Y34: =COUNTIF(_25B[Nazwa konta],'24 Bilans Mapowanie'!H34) -> 1
A35: Aktywa | B35: B. Aktywa obrotowe | C35: III. Inwestycje krótkoterminowe | D35: 1. Krótkoterminowe aktywa finansowe | E35: c) środki pieniężne i inne aktywa pieniężne | F35: - środki pieniężne w kasie i na rachunkach | G35: 18579900 | H35: 18579900 mBank PLN | I35: Bilansowe | J35: -118969.27 | K35: 22664.33 | L35: 8491.62 | M35: -1200077 | N35: 1187917.9 | O35: -574892.54 | P35: 420467.34 | Q35: -74535.7 | R35: -84251.6 | S35: -33433.01 | T35: 109214.94 | U35: 219483.51 | V35: -117919.48 | W35: -117919.48 | X35: 0 | Y35: =COUNTIF(_25B[Nazwa konta],'24 Bilans Mapowanie'!H35) -> 1
A36: Aktywa | B36: B. Aktywa obrotowe | C36: III. Inwestycje krótkoterminowe | D36: 1. Krótkoterminowe aktywa finansowe | E36: c) środki pieniężne i inne aktywa pieniężne | F36: - środki pieniężne w kasie i na rachunkach | G36: 18580000 | H36: 18580000 mBank USD | I36: Bilansowe | J36: 0 | K36: 0 | L36: 0 | M36: -415.7 | N36: -4620.34 | O36: 0 | P36: -15074.92 | Q36: 4171.42 | R36: 1225.45 | S36: 580.75 | T36: 106.19 | U36: 14027.15 | V36: 0 | W36: 0 | X36: 0 | Y36: =COUNTIF(_25B[Nazwa konta],'24 Bilans Mapowanie'!H36) -> 1
A37: Aktywa | B37: B. Aktywa obrotowe | C37: III. Inwestycje krótkoterminowe | D37: 1. Krótkoterminowe aktywa finansowe | E37: c) środki pieniężne i inne aktywa pieniężne | F37: - środki pieniężne w kasie i na rachunkach | G37: 18580100 | H37: 18580100 mBank EUR | I37: Bilansowe | J37: -38867.72 | K37: 19608.05 | L37: -102444.52 | M37: 94122.38 | N37: -19672.2 | O37: 26029.72 | P37: -238837.21 | Q37: -17259.72 | R37: 5321.46 | S37: 16924.71 | T37: -2774.91 | U37: 257849.96 | V37: 0 | W37: 0 | X37: 0 | Y37: =COUNTIF(_25B[Nazwa konta],'24 Bilans Mapowanie'!H37) -> 1
A38: Aktywa | B38: B. Aktywa obrotowe | C38: III. Inwestycje krótkoterminowe | D38: 1. Krótkoterminowe aktywa finansowe | E38: c) środki pieniężne i inne aktywa pieniężne | F38: - środki pieniężne w kasie i na rachunkach | G38: 18580200 | H38: 18580200 mBank PLN karty debetowe | I38: Bilansowe | J38: -10393.47 | K38: 3016 | L38: -4981 | M38: 6022 | N38: 10 | O38: 3019 | P38: -4960 | Q38: 2016 | R38: 3019 | S38: 110 | T38: -469 | U38: 537 | V38: -3054.47 | W38: -3054.47 | X38: 0 | Y38: =COUNTIF(_25B[Nazwa konta],'24 Bilans Mapowanie'!H38) -> 1
A39: Aktywa | B39: B. Aktywa obrotowe | C39: III. Inwestycje krótkoterminowe | D39: 1. Krótkoterminowe aktywa finansowe | E39: c) środki pieniężne i inne aktywa pieniężne | F39: - środki pieniężne w kasie i na rachunkach | G39: 19000000 | H39: 19000000 Środki pienięzne w kasie | I39: Bilansowe | J39: -5799.08 | K39: 2574.92 | L39: -916.41 | M39: -2583 | N39: 2932.8 | O39: 3000 | P39: -3834.67 | Q39: 815.12 | R39: -3112.45 | S39: 6665.71 | T39: -389.78 | U39: -3477.44 | V39: -4124.28 | W39: -4124.28 | X39: 0 | Y39: =COUNTIF(_25B[Nazwa konta],'24 Bilans Mapowanie'!H39) -> 1
A40: Aktywa | B40: B. Aktywa obrotowe | C40: III. Inwestycje krótkoterminowe | D40: 1. Krótkoterminowe aktywa finansowe | E40: c) środki pieniężne i inne aktywa pieniężne | F40: - środki pieniężne w kasie i na rachunkach | G40: 19002000 | H40: 19002000 Inne środki pieniężne | I40: Bilansowe | J40: -5000 | K40: -21476 | L40: 9187.68 | M40: -6165.22 | N40: -21527.5 | O40: -532.73 | P40: 6828.28 | Q40: 0 | R40: -2261.47 | S40: 26046.24 | T40: 6917.82 | U40: 7982.9 | V40: -9.5387804e-09 | W40: -9.5387804e-09 | X40: 0 | Y40: =COUNTIF(_25B[Nazwa konta],'24 Bilans Mapowanie'!H40) -> 1
A41: Pasywa | B41: A. Kapitał (fundusz) własny | C41: I. Kapitał (fundusz) podstawowy | G41: 20000000 | H41: 20000000 Kapitał zakładowy | I41: Bilansowe | J41: 50000 | K41: 0 | L41: 0 | M41: 0 | N41: 0 | O41: 0 | P41: 0 | Q41: 0 | R41: 0 | S41: 0 | T41: 0 | U41: 0 | V41: 50000 | W41: 50000 | X41: 0 | Y41: =COUNTIF(_25B[Nazwa konta],'24 Bilans Mapowanie'!H41) -> 1
A42: Pasywa | B42: A. Kapitał (fundusz) własny | C42: V. Zysk/ (strata) z lat ubiegłych | G42: 21000000 | H42: 21000000 Zysk zatrzymany | I42: Bilansowe | J42: 1256953.8 | K42: 0 | L42: 0 | M42: 0 | N42: 0 | O42: 0 | P42: 635497.26 | Q42: 0 | R42: 0 | S42: 0 | T42: 0 | U42: 0 | V42: 1892451 | W42: 1892451 | X42: 0 | Y42: =COUNTIF(_25B[Nazwa konta],'24 Bilans Mapowanie'!H42) -> 1
A43: Pasywa | B43: A. Kapitał (fundusz) własny | C43: V. Zysk/ (strata) z lat ubiegłych | G43: 21500000 | H43: 21500000 Profit of the period | I43: Bilansowe | J43: 650798.11 | K43: 0 | L43: 0 | M43: 0 | N43: 0 | O43: 0 | P43: -635497.26 | Q43: 0 | R43: 0 | S43: 0 | T43: 0 | U43: 0 | V43: 15300.85 | W43: 15300.85 | X43: 0 | Y43: =COUNTIF(_25B[Nazwa konta],'24 Bilans Mapowanie'!H43) -> 1
A44: Pasywa | B44: B. Zobowiązania i rezerwy na zobowiązania | C44: I. Rezerwy na zobowiązania | D44: 2. Rezerwa na świadczenia emerytalne i podobne | E44: a) długoterminowe | G44: 30500000 | H44: 30500000 Rezerwa na odprawę emerytalną | I44: Bilansowe | J44: 431910 | K44: 0 | L44: 0 | M44: 0 | N44: 0 | O44: 0 | P44: 0 | Q44: 0 | R44: 0 | S44: 0 | T44: 0 | U44: 83398 | V44: 515308 | W44: 515308 | X44: 0 | Y44: =COUNTIF(_25B[Nazwa konta],'24 Bilans Mapowanie'!H44) -> 1
A45: Pasywa | B45: B. Zobowiązania i rezerwy na zobowiązania | C45: I. Rezerwy na zobowiązania | D45: 3. Pozostałe rezerwy | E45: b) krótkoterminowe | G45: 33506033 | H45: 33506033 Rezerwa na premię roczną | I45: Bilansowe | J45: 1731688 | K45: 0 | L45: 0 | M45: 0 | N45: -1693374 | O45: 0 | P45: 0 | Q45: 0 | R45: 0 | S45: 0 | T45: 0 | U45: 1419719 | V45: 1458033 | W45: 1458033 | X45: 0 | Y45: =COUNTIF(_25B[Nazwa konta],'24 Bilans Mapowanie'!H45) -> 1
A46: Pasywa | B46: B. Zobowiązania i rezerwy na zobowiązania | C46: I. Rezerwy na zobowiązania | D46: 3. Pozostałe rezerwy | E46: a) długoterminowe | G46: 33506050 | H46: 33506050 Rezerwa urlopowa | I46: Bilansowe | J46: 767709 | K46: 0 | L46: 0 | M46: 0 | N46: 0 | O46: 0 | P46: 0 | Q46: 0 | R46: 0 | S46: 0 | T46: 0 | U46: -26873.41 | V46: 740835.59 | W46: 740835.59 | X46: 0 | Y46: =COUNTIF(_25B[Nazwa konta],'24 Bilans Mapowanie'!H46) -> 1
A47: Pasywa | B47: B. Zobowiązania i rezerwy na zobowiązania | C47: III. Zobowiązania krótkoterminowe | D47: 3. Zobowiązania wobec pozostałych jednostek | E47: h) z tytułu wynagrodzeń | G47: 33506000 | H47: 33506000 Krótkoterminowe zobowiązania wobec pracowników | I47: Bilansowe | J47: 53 | K47: 3382.66 | L47: 106 | M47: -682197.48 | N47: 682234.18 | O47: 123.42 | P47: -2706.67 | Q47: -754052.84 | R47: 748405.94 | S47: 4651.79 | T47: -12.41 | U47: 12.41 | V47: -3.3412562e-10 | W47: -3.3412562e-10 | X47: 0 | Y47: =COUNTIF(_25B[Nazwa konta],'24 Bilans Mapowanie'!H47) -> 1
A48: Pasywa | B48: B. Zobowiązania i rezerwy na zobowiązania | C48: I. Rezerwy na zobowiązania | D48: 3. Pozostałe rezerwy | E48: a) długoterminowe | G48: 34014000 | H48: 34014000 Inne rezerwy | I48: Bilansowe | J48: 17750 | K48: 0 | L48: 0 | M48: 0 | N48: 0 | O48: 0 | P48: 0 | Q48: 0 | R48: 0 | S48: 0 | T48: 0 | U48: 9600 | V48: 27350 | W48: 27350 | X48: 0 | Y48: =COUNTIF(_25B[Nazwa konta],'24 Bilans Mapowanie'!H48) -> 1
A49: Pasywa | B49: B. Zobowiązania i rezerwy na zobowiązania | C49: III. Zobowiązania krótkoterminowe | D49: 3. Zobowiązania wobec pozostałych jednostek | E49: d) z tytułu dostaw i usług, o okresie wymagalności: | F49: - do 12 miesięcy | G49: 34500000 | H49: 34500000 Zobowiązania handlowe - podmioty niepowiązane | I49: Bilansowe | J49: 58587.33 | K49: -75500.95 | L49: 27423.46 | M49: -47190.7 | N49: 276719.25 | O49: -158920.88 | P49: -60292.43 | Q49: -33969.5 | R49: 29761.68 | S49: -12177.21 | T49: -24530.4 | U49: 107090.49 | V49: 87000.14 | W49: 87000.14 | X49: 0 | Y49: =COUNTIF(_25B[Nazwa konta],'24 Bilans Mapowanie'!H49) -> 1
A50: Pasywa | B50: B. Zobowiązania i rezerwy na zobowiązania | C50: III. Zobowiązania krótkoterminowe | D50: 3. Zobowiązania wobec pozostałych jednostek | E50: d) z tytułu dostaw i usług, o okresie wymagalności: | F50: - do 12 miesięcy | G50: 34504000 | H50: 34504000 Dostawy niefakturowane - podmioty niepowiązane | I50: Bilansowe | J50: 38051.43 | K50: -38051.43 | L50: 0 | M50: 0 | N50: 0 | O50: 0 | P50: 0 | Q50: 0 | R50: 0 | S50: 0 | T50: 0 | U50: 56387.4 | V50: 56387.4 | W50: 56387.4 | X50: 0 | Y50: =COUNTIF(_25B[Nazwa konta],'24 Bilans Mapowanie'!H50) -> 1
A51: Aktywa | B51: B. Aktywa obrotowe | C51: II. Należności krótkoterminowe | D51: 3. Należności od pozostałych jednostek | E51: c) inne | G51: 34515000 | H51: 34515000 Faktura do przypisania (SD) | I51: Bilansowe | J51: -93807.9 | K51: 93807.9 | L51: 0 | M51: 0 | N51: 0 | O51: 0 | P51: 0 | Q51: 0 | R51: 0 | S51: 0 | T51: 0 | U51: 0 | V51: 0 | W51: 0 | X51: 0 | Y51: =COUNTIF(_25B[Nazwa konta],'24 Bilans Mapowanie'!H51) -> 1
A52: Aktywa | B52: B. Aktywa obrotowe | C52: II. Należności krótkoterminowe | D52: 1. Należności od jednostek powiązanych | E52: a) z tytułu dostaw i usług, o okresie spłaty: | F52: - do 12 miesięcy | G52: 34550000 | H52: 34550000 Zobowiązania handlowe - podmioty powiązane | I52: Bilansowe | J52: 0 | K52: 0 | L52: 107503.79 | M52: 1231453 | N52: -1338956.8 | O52: 0 | P52: 23375.94 | Q52: -13421.14 | R52: -9954.8 | S52: 66921.68 | T52: -64469.85 | U52: -2451.83 | V52: 6.9121597e-11 | W52: 6.9121597e-11 | X52: 0 | Y52: =COUNTIF(_25B[Nazwa konta],'24 Bilans Mapowanie'!H52) -> 1
A53: Pasywa | B53: B. Zobowiązania i rezerwy na zobowiązania | C53: III. Zobowiązania krótkoterminowe | D53: 3. Zobowiązania wobec pozostałych jednostek | E53: d) z tytułu dostaw i usług, o okresie wymagalności: | F53: - do 12 miesięcy | G53: 34550999 | H53: 34550999 Zobowiąz handlowe podm powiąz - wycena bilansowa | I53: Bilansowe | J53: 29.08 | K53: 0 | L53: 0 | M53: 0 | N53: 0 | O53: 0 | P53: 0 | Q53: 0 | R53: 0 | S53: 0 | T53: 0 | U53: -29.08 | V53: 0 | W53: 0 | X53: 0 | Y53: =COUNTIF(_25B[Nazwa konta],'24 Bilans Mapowanie'!H53) -> 1
A54: Pasywa | B54: B. Zobowiązania i rezerwy na zobowiązania | C54: III. Zobowiązania krótkoterminowe | D54: 3. Zobowiązania wobec pozostałych jednostek | E54: g) z tytułu podatków, ceł, ubezpieczeń społecznych i zdrowotnych oraz innych tytułów publicznoprawnych | G54: 35002010 | H54: 35002010 VAT Należny | I54: Bilansowe | J54: 1102.78 | K54: 256.48 | L54: 325.18 | M54: 512.96 | N54: -93.18 | O54: 47461.02 | P54: 13678.48 | Q54: 822.97 | R54: 22266.73 | S54: 258.28 | T54: 258.12 | U54: 272.02 | V54: 87121.84 | W54: 87121.84 | X54: 0 | Y54: =COUNTIF(_25B[Nazwa konta],'24 Bilans Mapowanie'!H54) -> 1
A55: Pasywa | B55: B. Zobowiązania i rezerwy na zobowiązania | C55: III. Zobowiązania krótkoterminowe | D55: 3. Zobowiązania wobec pozostałych jednostek | E55: g) z tytułu podatków, ceł, ubezpieczeń społecznych i zdrowotnych oraz innych tytułów publicznoprawnych | G55: 35002100 | H55: 35002100 VAT należny EU | I55: Bilansowe | J55: 0 | K55: 0 | L55: 0 | M55: 0 | N55: 0 | O55: 0 | P55: 0 | Q55: 0 | R55: 0 | S55: 65.2 | T55: 103.69 | U55: 68 | V55: 236.89 | W55: 236.89 | X55: 0 | Y55: =COUNTIF(_25B[Nazwa konta],'24 Bilans Mapowanie'!H55) -> 1
A56: Pasywa | B56: B. Zobowiązania i rezerwy na zobowiązania | C56: III. Zobowiązania krótkoterminowe | D56: 3. Zobowiązania wobec pozostałych jednostek | E56: g) z tytułu podatków, ceł, ubezpieczeń społecznych i zdrowotnych oraz innych tytułów publicznoprawnych | G56: 35004001 | H56: 35004001 Zobowiązania wobec US - PIT | I56: Bilansowe | J56: 90737 | K56: -1448 | L56: 1816 | M56: -91105 | N56: 267860 | O56: -131887 | P56: -15065 | Q56: -120908 | R56: 115651 | S56: -159 | T56: 13827 | U56: -129319 | V56: 0 | W56: 0 | X56: 0 | Y56: =COUNTIF(_25B[Nazwa konta],'24 Bilans Mapowanie'!H56) -> 1
A57: Pasywa | B57: B. Zobowiązania i rezerwy na zobowiązania | C57: III. Zobowiązania krótkoterminowe | D57: 3. Zobowiązania wobec pozostałych jednostek | E57: g) z tytułu podatków, ceł, ubezpieczeń społecznych i zdrowotnych oraz innych tytułów publicznoprawnych | G57: 35006000 | H57: 35006000 Zobowiazania z tytułu ubezpieczeń społecznych | I57: Bilansowe | J57: 352824.99 | K57: -1026.29 | L57: -7579.2 | M57: -344219.5 | N57: 892880.01 | O57: -491438.28 | P57: -81610.91 | Q57: -319830.82 | R57: 331739.46 | S57: -33984.48 | T57: -3757.68 | U57: -293997.3 | V57: -5.8207661e-10 | W57: -5.8207661e-10 | X57: 0 | Y57: =COUNTIF(_25B[Nazwa konta],'24 Bilans Mapowanie'!H57) -> 1
A58: Aktywa | B58: A. Aktywa trwałe | C58: V. Długoterminowe rozliczenia międzyokresowe | D58: 2. Inne rozliczenia międzyokresowe | G58: 36500010 | H58: 36500010 Przychody z frachtu powyżej lub ponizej manifestu | I58: Bilansowe | J58: -122.99 | K58: 0 | L58: -0.02 | M58: 0.15 | N58: 0 | O58: -0.08 | P58: 0.51 | Q58: -0.02 | R58: 0 | S58: 1.23 | T58: -0.03 | U58: 0.04 | V58: -121.21 | W58: -121.21 | X58: 0 | Y58: =COUNTIF(_25B[Nazwa konta],'24 Bilans Mapowanie'!H58) -> 1
A59: Pasywa | B59: B. Zobowiązania i rezerwy na zobowiązania | C59: III. Zobowiązania krótkoterminowe | D59: 3. Należności od pozostałych jednostek | G59: 16000000 | H59: 16000000 Other receivables | I59: Bilansowe | T59: 0 | U59: 5419 | V59: 5419 | W59: 5419 | X59: 0 | Y59: =COUNTIF(_25B[Nazwa konta],'24 Bilans Mapowanie'!H59) -> 1
A60: Aktywa | B60: B. Aktywa obrotowe | C60: II. Należności krótkoterminowe | D60: 3. Należności od pozostałych jednostek | E60: b) z tytułu podatków, dotacji, ceł, ubezpieczeń społecznych i zdrowotnych oraz innych tytułów publicznoprawnych | G60: 35002000 | H60: 35002000 Zobowiązania wobec US - VAT | I60: Bilansowe | T60: -584 | U60: 0 | V60: -584 | W60: -584 | X60: 0 | Y60: =COUNTIF(_25B[Nazwa konta],'24 Bilans Mapowanie'!H60) -> 1
A61: =IF(ISNUMBER(SEARCH("aktywa",B61)),"Aktywa","Pasywa") -> Pasywa | B61: A. Kapitał (fundusz) własny | C61: VI. Zysk/ (strata) netto | H61: Zysk netto bieżącego okresu | J61: 379978.41 | K61: 440442.24 | L61: 229502.04 | M61: -6575.01 | N61: -1787117.1 | O61: -374801.78 | P61: 700535.63 | Q61: 1136584.7 | R61: -1211578.9 | S61: -300040 | T61: -51451.93 | U61: 1186810.6 | V61: 342288.94 | W61: 342288.94 | X61: 0 | Y61: =COUNTIF(_25B[Nazwa konta],'24 Bilans Mapowanie'!H61) -> 1
J62: =SUM(J2:J61) -> -1.6065314e-08 | K62: =SUM(K2:K61) -> 1.0652002e-08 | L62: =SUM(L2:L61) -> -7.7707227e-09 | M62: =SUM(M2:M61) -> -8.1854523e-11 | N62: =SUM(N2:N61) -> 8.1490725e-09 | O62: =SUM(O2:O61) -> -7.5087883e-09 | P62: =SUM(P2:P61) -> 0 | Q62: =SUM(Q2:Q61) -> 0 | ... V62: =SUM(V2:V61) -> -2.6193447e-09
J63: -1

Sheet Dane -->

Sheet 2025 ZOiS
E1: =SUM(E3:E170) -> 2.6263294e-09 | F1: =SUM(F3:F170) -> 1.1670664e-10 | G1: =SUM(G3:G170) -> 5.0204108e-10 | H1: =SUM(H3:H170) -> -5.8207661e-10 | I1: =SUM(I3:I170) -> 9.8953024e-10 | J1: =SUM(J3:J170) -> -2.3283064e-10 | K1: =SUM(K3:K170) -> -3.1435547e-09 | L1: =SUM(L3:L170) -> 9.0983576e-10 | ... S1: =SUM(S3:S170) -> 2.3646862e-11
A2: Rodzaj | B2: Numer konta | C2: Nazwa konta | D2: Rodzaj konta (bilansowe/wynikowe) | E2: 2025/Jan | F2: 2025/Feb | G2: 2025/Mar | H2: 2025/Apr | I2: 2025/May | J2: 2025/Jun | K2: 2025/Jul | L2: 2025/Aug | M2: 2025/Sep | N2: 2025/Oct | O2: 2025/Nov | P2: 2025/Dec | Q2: BZ | R2: BZ 2025 | S2: Check:
A3: Przychody ze sprzedaży | B3: 45510000 | C3: 45510000 Prowizja Cost+ | D3: Wynikowe | E3: -1877205 | F3: -1844622 | G3: -1802379 | H3: -1430181 | I3: -1741817 | J3: -1686073 | K3: -1733363 | L3: -1733363 | M3: -1733363 | N3: -1711660 | O3: -1711660 | P3: -3177425 | Q3: =SUM(E3:P3) -> -22183111 | R3: -22183111 | S3: =Q3-R3 -> 0
A4: Przychody ze sprzedaży | B4: 44000000 | C4: 44000000 Przychód operacyjny - opłata za konosament | D4: Wynikowe | E4: 0 | F4: 0 | G4: 0 | H4: 0 | I4: 0 | J4: 0 | K4: 0 | L4: 0 | M4: 0 | N4: 0 | O4: 0 | P4: 0 | Q4: =SUM(E4:P4) -> 0 | R4: 0 | S4: =Q4-R4 -> 0
A5: Przychody ze sprzedaży | B5: 44000005 | C5: 44000005 Przychód operacyjny - opłata dokumentacyjna EXP | D5: Wynikowe | E5: 0 | F5: 0 | G5: 0 | H5: 0 | I5: 0 | J5: 0 | K5: 0 | L5: 0 | M5: 0 | N5: 0 | O5: 0 | P5: 0 | Q5: =SUM(E5:P5) -> 0 | R5: 0 | S5: =Q5-R5 -> 0
A6: Przychody ze sprzedaży | B6: 44006000 | C6: 44006000 Przychód operacyjny - korekta manifestu | D6: Wynikowe | E6: 0 | F6: 0 | G6: 0 | H6: 0 | I6: 0 | J6: 0 | K6: 0 | L6: 0 | M6: 0 | N6: 0 | O6: 0 | P6: 0 | Q6: =SUM(E6:P6) -> 0 | R6: 0 | S6: =Q6-R6 -> 0
A7: Amortyzacja | B7: 61000000 | C7: 61000000 Oprogramowanie i licencje IT - Amortyzacja | D7: Wynikowe | E7: 926.5 | F7: 926.5 | G7: 926.5 | H7: 926.5 | I7: 926.5 | J7: 926.5 | K7: 926.5 | L7: 926.5 | M7: 926.5 | N7: 926.5 | O7: 926.5 | P7: 926.5 | Q7: =SUM(E7:P7) -> 11118 | R7: 11118 | S7: =Q7-R7 -> 0
A8: Amortyzacja | B8: 61502000 | C8: 61502000 Budynki - Amortyzacja | D8: Wynikowe | E8: 17326.2 | F8: 17326.2 | G8: 17326.21 | H8: 17326.2 | I8: 17326.2 | J8: 17326.2 | K8: 17326.2 | L8: 17326.2 | M8: 17326.21 | N8: 17326.2 | O8: 17326.2 | P8: 17326.2 | Q8: =SUM(E8:P8) -> 207914.42 | R8: 207914.42 | S8: =Q8-R8 -> 0
A9: Amortyzacja | B9: 61504000 | C9: 61504000 Nakłady w obcych środkach trwał - Amortyzacja | D9: Wynikowe | E9: 313.46 | F9: 313.45 | G9: 313.46 | H9: 313.46 | I9: 6769.34 | J9: 1604.64 | K9: 1604.64 | L9: 1604.63 | M9: 1604.64 | N9: 1604.63 | O9: 1604.63 | P9: 1604.64 | Q9: =SUM(E9:P9) -> 19255.62 | R9: 19255.62 | S9: =Q9-R9 -> 0
A10: Amortyzacja | B10: 61508000 | C10: 61508000 Komputery i sprzęt IT - Amortyzacja | D10: Wynikowe | E10: 10218.3 | F10: 8464.79 | G10: 11588.15 | H10: 24240.21 | I10: 459 | J10: 0 | K10: 16357.33 | L10: 579 | M10: 4146.34 | N10: 12895.39 | O10: 2065.04 | P10: 11369.44 | Q10: =SUM(E10:P10) -> 102382.99 | R10: 102382.99 | S10: =Q10-R10 -> 0
A11: Amortyzacja | B11: 61512000 | C11: 61512000 Meble - Amortyzacja | D11: Wynikowe | E11: 965.04 | F11: 1635.1 | G11: 3421.14 | H11: 18409.02 | I11: 1749.81 | J11: 1749.8 | K11: 3748.51 | L11: 1749.81 | M11: 1749.8 | N11: 4649.8 | O11: 1749.8 | P11: 816.98 | Q11: =SUM(E11:P11) -> 42394.61 | R11: 42394.61 | S11: =Q11-R11 -> 0
A12: Amortyzacja | B12: 61518000 | C12: 61518000 Samochody - Amortyzacja | D12: Wynikowe | E12: 16100.98 | F12: 16101 | G12: 16100.99 | H12: 13559.44 | I12: 8113.52 | J12: 6162.77 | K12: 6162.45 | L12: 6162.46 | M12: 6162.48 | N12: 6162.47 | O12: 6162.46 | P12: 6162.46 | Q12: =SUM(E12:P12) -> 113113.48 | R12: 113113.48 | S12: =Q12-R12 -> 0
A13: Zużycie materiałów i energii | B13: 58502000 | C13: 58502000 Energia cieplna | D13: Wynikowe | E13: 4570.88 | F13: 4099.71 | G13: 4862.37 | H13: 4987.16 | I13: 4558.32 | J13: 4744.18 | K13: 8241.36 | L13: 5397.11 | M13: 5554.37 | N13: 4288.71 | O13: 5699.53 | P13: 5270.55 | Q13: =SUM(E13:P13) -> 62274.25 | R13: 62274.25 | S13: =Q13-R13 -> 0
A14: Zużycie materiałów i energii | B14: 58502001 | C14: 58502001 Woda | D14: Wynikowe | E14: 928.32 | F14: 1511.16 | G14: 1199.06 | H14: 1726 | I14: 844.52 | J14: 966.37 | K14: -148.66 | L14: 1216.82 | M14: 1255.33 | N14: 1280.2 | O14: 814.72 | P14: 1139.18 | Q14: =SUM(E14:P14) -> 12733.02 | R14: 12733.02 | S14: =Q14-R14 -> 0
... A88: Pozostałe koszty rodzajowe | B88: 58568011 | C88: 58568011 Upominki promocyjne dla innych | D88: Wynikowe | E88: 1000 | F88: 0 | G88: 0 | H88: 0 | I88: 261.23 | J88: 0 | K88: 0 | L88: 0 | M88: 0 | N88: 0 | O88: 0 | P88: -1261.23 | Q88: =SUM(E88:P88) -> 0 | R88: 0 | S88: =Q88-R88 -> 0
B89: 11000100 | C89: 11000100 Oprogramowanie i licencje IT - Wartość nabycia | D89: Bilansowe | E89: 77463.01 | F89: 0 | G89: 0 | H89: 0 | I89: 0 | J89: 0 | K89: 0 | L89: 0 | M89: 0 | N89: 0 | O89: 0 | P89: 0 | Q89: =SUM(E89:P89) -> 77463.01 | R89: 77463.01 | S89: =Q89-R89 -> 0
B90: 11000400 | C90: 11000400 Oprogramowanie i licencje IT - Umorzenie | D90: Bilansowe | E90: -59859.51 | F90: -926.5 | G90: -926.5 | H90: -926.5 | I90: -926.5 | J90: -926.5 | K90: -926.5 | L90: -926.5 | M90: -926.5 | N90: -926.5 | O90: -926.5 | P90: -926.5 | Q90: =SUM(E90:P90) -> -70051.01 | R90: -70051.01 | S90: =Q90-R90 -> 0
B91: 11502100 | C91: 11502100 Budynki - Wartość nabycia | D91: Bilansowe | E91: 8316577 | F91: 0 | G91: 0 | H91: 0 | I91: 0 | J91: 0 | K91: 0 | L91: 0 | M91: 0 | N91: 0 | O91: 0 | P91: 0 | Q91: =SUM(E91:P91) -> 8316577 | R91: 8316577 | S91: =Q91-R91 -> 0
B92: 11502400 | C92: 11502400 Budynki - Umorzenie | D92: Bilansowe | E92: -1679956.6 | F92: -17326.2 | G92: -17326.21 | H92: -17326.2 | I92: -17326.2 | J92: -17326.2 | K92: -17326.2 | L92: -17326.2 | M92: -17326.21 | N92: -17326.2 | O92: -17326.2 | P92: -17326.2 | Q92: =SUM(E92:P92) -> -1870544.8 | R92: -1870544.8 | S92: =Q92-R92 -> 0
B93: 11504100 | C93: 11504100 Nakłady w obcych środkach trwał - Wartość nabycia | D93: Bilansowe | E93: 204102.98 | F93: 0 | G93: 0 | H93: 0 | I93: 0 | J93: 0 | K93: 0 | L93: 0 | M93: 0 | N93: 0 | O93: 0 | P93: 0 | Q93: =SUM(E93:P93) -> 204102.98 | R93: 204102.98 | S93: =Q93-R93 -> 0
B94: 11504400 | C94: 11504400 Nakłady w obcych środkach trwał - Umorzenie | D94: Bilansowe | E94: -43327.35 | F94: -313.45 | G94: -313.46 | H94: -313.46 | I94: -6769.34 | J94: -1604.64 | K94: -1604.64 | L94: -1604.63 | M94: -1604.64 | N94: -1604.63 | O94: -1604.63 | P94: -1604.64 | Q94: =SUM(E94:P94) -> -62269.51 | R94: -62269.51 | S94: =Q94-R94 -> 0
B95: 11508100 | C95: 11508100 Komputery i sprzęt IT - Wartość nabycia | D95: Bilansowe | E95: 1021948.2 | F95: 6806.51 | G95: -2240.07 | H95: 22451.59 | I95: 459 | J95: 0 | K95: 13387.33 | L95: -1499.06 | M95: 157.44 | N95: 9879.54 | O95: 2065.04 | P95: 6725.93 | Q95: =SUM(E95:P95) -> 1080141.5 | R95: 1080141.5 | S95: =Q95-R95 -> 0
B96: 11508400 | C96: 11508400 Komputery i sprzęt IT - Umorzenie | D96: Bilansowe | E96: -1009268.7 | F96: -3437.15 | G96: -3035.42 | H96: -22451.59 | I96: -459 | J96: 0 | K96: -13387.33 | L96: 920.06 | M96: 421.56 | N96: -9879.54 | O96: -2065.04 | P96: -6725.93 | Q96: =SUM(E96:P96) -> -1069368.1 | R96: -1069368.1 | S96: =Q96-R96 -> 0
